Workbook
Name HistoryDate: History!$A:$A
Name HistorySecurity: History!$B:$B
Name HistoryPrice: History!$E:$E
Name HistoryQuantity: History!$D:$D
Name HistoryAction: History!$C:$C
Name HistoryTotal: History!$F:$F

Sheet Dashboard
B2: =Now() -> 46210.805 | I2: =if(OR((weekday(B2))=1,(weekday(B2))=7),"Market Closed",if(time(hour(now()),minute(now()),second(now()))>TIME(15,30,0),"Market Closed",if((time(hour(now()),minute(now()),second(now()))>TIME(9,15,0)),"Market Open","Market Closed"))) -> Market Closed
B3: INDEX
L4: EUROPE
B5: N.Y & N.DAQ | C5: N.Y & N.DAQ | D5: NASDAQ | E5: N.Y & N.DAQ | F5: NSE | G5: BSE | H5: TOKYO | I5: TAIWAN | J5: HONG KONG | K5: KOREA | L5: LONDON | M5: PARIS | N5: GERMANY | O5: EUROZONE
B6: Dow Jones | C6: S&500 | D6: Nasdaq | E6: Russell | F6: NIFTY 50 | G6: SENSEX | H6: Nikkei 225 | I6: TWSE | J6: HSI | K6: KOSPI | L6: FTSE 100 | M6: CAC 40 | N6: DAX | O6: STOXX 50
B7: .DJI | C7: .INX | D7: .IXIC | E7: RUT | F7: NIFTY_50 | G7: SENSEX | H7: NI225 | I7: IX0001 | J7: INDEXHANGSENG:HSI | K7: KOSPI | L7: UKX | M7: PX1 | N7: INDEXDB:DAX | O7: SX5E
B8: =IFERROR(__xludf.DUMMYFUNCTION("GOOGLEFINANCE(B7)"),53179.02) -> 53179.02 | C8: =IFERROR(__xludf.DUMMYFUNCTION("GOOGLEFINANCE(C7)"),7525.82) -> 7525.82 | D8: =IFERROR(__xludf.DUMMYFUNCTION("GOOGLEFINANCE(D7)"),25928.17) -> 25928.17 | E8: =IFERROR(__xludf.DUMMYFUNCTION("GOOGLEFINANCE(E7)"),3009.54) -> 3009.54 | F8: =IFERROR(__xludf.DUMMYFUNCTION("GOOGLEFINANCE(F7)"),24398.7) -> 24398.7 | G8: =IFERROR(__xludf.DUMMYFUNCTION("GOOGLEFINANCE(G7)"),78180.72) -> 78180.72 | H8: =IFERROR(__xludf.DUMMYFUNCTION("GOOGLEFINANCE(H7)"),68256.96) -> 68256.96 | I8: =IFERROR(__xludf.DUMMYFUNCTION("GOOGLEFINANCE(I7)"),45479.11) -> 45479.11 | J8: =IFERROR(__xludf.DUMMYFUNCTION("GOOGLEFINANCE(J7)"),23496.89) -> 23496.89 | K8: =IFERROR(__xludf.DUMMYFUNCTION("GOOGLEFINANCE(K7)"),7656.31) -> 7656.31 | L8: =IFERROR(__xludf.DUMMYFUNCTION("GOOGLEFINANCE(L7)"),10729.99) -> 10729.99 | M8: =IFERROR(__xludf.DUMMYFUNCTION("GOOGLEFINANCE(M7)"),8500.94) -> 8500.94 | N8: =IFERROR(__xludf.DUMMYFUNCTION("GOOGLEFINANCE(N7)"),25644.75) -> 25644.75 | O8: =IFERROR(__xludf.DUMMYFUNCTION("GOOGLEFINANCE(O7)"),6361.62) -> 6361.62
B9: =IFERROR(__xludf.DUMMYFUNCTION("GOOGLEFINANCE(B7,""Change"")"),123.11) -> 123.11 | C9: =IFERROR(__xludf.DUMMYFUNCTION("GOOGLEFINANCE(C7,""Change"")"),-11.61) -> -11.61 | D9: =IFERROR(__xludf.DUMMYFUNCTION("GOOGLEFINANCE(D7,""Change"")"),-192.99) -> -192.99 | E9: =IFERROR(__xludf.DUMMYFUNCTION("GOOGLEFINANCE(E7,""Change"")"),13.43) -> 13.43 | F9: =IFERROR(__xludf.DUMMYFUNCTION("GOOGLEFINANCE(F7,""Change"")"),-31.65) -> -31.65 | G9: =IFERROR(__xludf.DUMMYFUNCTION("GOOGLEFINANCE(G7,""Change"")"),-104.35) -> -104.35 | H9: =IFERROR(__xludf.DUMMYFUNCTION("GOOGLEFINANCE(H7,""Change"")"),-1480.73) -> -1480.73 | I9: =IFERROR(__xludf.DUMMYFUNCTION("GOOGLEFINANCE(I7,""Change"")"),-1077.28) -> -1077.28 | J9: =IFERROR(__xludf.DUMMYFUNCTION("GOOGLEFINANCE(J7,""Change"")"),-119.43) -> -119.43 | K9: =IFERROR(__xludf.DUMMYFUNCTION("GOOGLEFINANCE(K7,""Change"")"),-395.02) -> -395.02 | L9: =IFERROR(__xludf.DUMMYFUNCTION("GOOGLEFINANCE(L7,""Change"")"),78.22) -> 78.22 | M9: =IFERROR(__xludf.DUMMYFUNCTION("GOOGLEFINANCE(M7,""Change"")"),21.07) -> 21.07 | N9: =IFERROR(__xludf.DUMMYFUNCTION("GOOGLEFINANCE(N7,""Change"")"),-173.14) -> -173.14 | O9: =IFERROR(__xludf.DUMMYFUNCTION("GOOGLEFINANCE(O7,""Change"")"),-36.39) -> -36.39
B10: =B9/B8 -> 0.0023150107 | C10: =C9/C8 -> -0.001542689 | D10: =D9/D8 -> -0.0074432557 | E10: =E9/E8 -> 0.004462476 | F10: =F9/F8 -> -0.0012972003 | G10: =G9/G8 -> -0.0013347281 | H10: =H9/H8 -> -0.021693465 | I10: =I9/I8 -> -0.023687359 | ... O10: =O9/O8 -> -0.0057202411
B11: =IFERROR(__xludf.DUMMYFUNCTION("SPARKLINE(INDEX(GOOGLEFINANCE(B7,""Price"",WORKDAY(TODAY(),-252),today()),,2))"),"") | C11: =IFERROR(__xludf.DUMMYFUNCTION("SPARKLINE(INDEX(GOOGLEFINANCE(C7,""Price"",WORKDAY(TODAY(),-252),today()),,2))"),"") | D11: =IFERROR(__xludf.DUMMYFUNCTION("SPARKLINE(INDEX(GOOGLEFINANCE(D7,""Price"",WORKDAY(TODAY(),-252),today()),,2))"),"") | E11: =IFERROR(__xludf.DUMMYFUNCTION("SPARKLINE(INDEX(GOOGLEFINANCE(E7,""Price"",WORKDAY(TODAY(),-252),today()),,2))"),"") | F11: =IFERROR(__xludf.DUMMYFUNCTION("SPARKLINE(INDEX(GOOGLEFINANCE(F7,""Price"",WORKDAY(TODAY(),-252),today()),,2))"),"") | G11: =IFERROR(__xludf.DUMMYFUNCTION("SPARKLINE(INDEX(GOOGLEFINANCE(G7,""Price"",WORKDAY(TODAY(),-252),today()),,2))"),"") | H11: =IFERROR(__xludf.DUMMYFUNCTION("SPARKLINE(INDEX(GOOGLEFINANCE(H7,""Price"",WORKDAY(TODAY(),-252),today()),,2))"),"") | I11: =IFERROR(__xludf.DUMMYFUNCTION("SPARKLINE(INDEX(GOOGLEFINANCE(I7,""Price"",WORKDAY(TODAY(),-252),today()),,2))"),"") | J11: =IFERROR(__xludf.DUMMYFUNCTION("SPARKLINE(INDEX(GOOGLEFINANCE(J7,""Price"",WORKDAY(TODAY(),-252),today()),,2))"),"") | K11: =IFERROR(__xludf.DUMMYFUNCTION("SPARKLINE(INDEX(GOOGLEFINANCE(K7,""Price"",WORKDAY(TODAY(),-252),today()),,2))"),"") | L11: =IFERROR(__xludf.DUMMYFUNCTION("SPARKLINE(INDEX(GOOGLEFINANCE(L7,""Price"",WORKDAY(TODAY(),-252),today()),,2))"),"") | M11: =IFERROR(__xludf.DUMMYFUNCTION("SPARKLINE(INDEX(GOOGLEFINANCE(M7,""Price"",WORKDAY(TODAY(),-252),today()),,2))"),"") | N11: =IFERROR(__xludf.DUMMYFUNCTION("SPARKLINE(INDEX(GOOGLEFINANCE(N7,""Price"",WORKDAY(TODAY(),-252),today()),,2))"),"") | O11: =IFERROR(__xludf.DUMMYFUNCTION("SPARKLINE(INDEX(GOOGLEFINANCE(O7,""Price"",WORKDAY(TODAY(),-252),today()),,2))"),"")
B15: Single Stock Analysis | D15: =IFERROR(__xludf.DUMMYFUNCTION("GOOGLEFINANCE(C16,""Name"")"),"Affle 3i Ltd") -> Affle 3i Ltd | J15: ADRS
B16: Stock Overview | C16: NSE:AFFLE | D16: 12 Month Trend Lines | J16: HDFC | K16: ICICI | L16: INFOSYS | M16: WIPRO | N16: DR.REDDY | O16: YATRA ONLINE
B17: Stock Price | C17: =IFERROR(__xludf.DUMMYFUNCTION("GOOGLEFINANCE(C16,""price"")"),1465.1) -> 1465.1 | D17: =IFERROR(__xludf.DUMMYFUNCTION("SPARKLINE(INDEX(GOOGLEFINANCE(C16,""Price"",WORKDAY(TODAY(),-252),today()),,2),{""CHARTTYPE"",""COLUMN""})"),"") | J17: HDB | K17: IBN | L17: INFY | M17: WIT | N17: RDY | O17: YTRA
B18: 52 % Change | C18: =if(isblank(C16),"",(C17-C20)/C20) -> -0.32974976 | J18: =IFERROR(__xludf.DUMMYFUNCTION("GOOGLEFINANCE(J17)"),27.29) -> 27.29 | K18: =IFERROR(__xludf.DUMMYFUNCTION("GOOGLEFINANCE(K17)"),29.89) -> 29.89 | L18: =IFERROR(__xludf.DUMMYFUNCTION("GOOGLEFINANCE(L17)"),11.36) -> 11.36 | M18: =IFERROR(__xludf.DUMMYFUNCTION("GOOGLEFINANCE(M17)"),1.89) -> 1.89 | N18: =IFERROR(__xludf.DUMMYFUNCTION("GOOGLEFINANCE(N17)"),14.55) -> 14.55 | O18: =IFERROR(__xludf.DUMMYFUNCTION("GOOGLEFINANCE(O17)"),0.91) -> 0.91
B19: Signal | C19: =if(C18<-10%,"Buy","Hold") -> Buy | J19: =IFERROR(__xludf.DUMMYFUNCTION("GOOGLEFINANCE(J17,""Change"")"),-0.11) -> -0.11 | K19: =IFERROR(__xludf.DUMMYFUNCTION("GOOGLEFINANCE(K17,""Change"")"),-0.19) -> -0.19 | L19: =IFERROR(__xludf.DUMMYFUNCTION("GOOGLEFINANCE(L17,""Change"")"),0.48) -> 0.48 | M19: =IFERROR(__xludf.DUMMYFUNCTION("GOOGLEFINANCE(M17,""Change"")"),0.04) -> 0.04 | N19: =IFERROR(__xludf.DUMMYFUNCTION("GOOGLEFINANCE(N17,""Change"")"),0.19) -> 0.19 | O19: =IFERROR(__xludf.DUMMYFUNCTION("GOOGLEFINANCE(O17,""Change"")"),0.03) -> 0.03
B20: 52 Week High | C20: =IFERROR(__xludf.DUMMYFUNCTION("GOOGLEFINANCE(C16,""HIGH52"")"),2185.9) -> 2185.9 | J20: =J19/J18 -> -0.0040307805 | K20: =K19/K18 -> -0.006356641 | L20: =L19/L18 -> 0.042253521 | M20: =M19/M18 -> 0.021164021 | N20: =N19/N18 -> 0.013058419 | O20: =O19/O18 -> 0.032967033
B21: 52 Week Low | C21: =IFERROR(__xludf.DUMMYFUNCTION("GOOGLEFINANCE(C16,""LOW52"")"),1251.3) -> 1251.3 | J21: =IFERROR(__xludf.DUMMYFUNCTION("SPARKLINE(INDEX(GOOGLEFINANCE(J17,""Price"",WORKDAY(TODAY(),-252),today()),,2))"),"") | K21: =IFERROR(__xludf.DUMMYFUNCTION("SPARKLINE(INDEX(GOOGLEFINANCE(K17,""Price"",WORKDAY(TODAY(),-252),today()),,2))"),"") | L21: =IFERROR(__xludf.DUMMYFUNCTION("SPARKLINE(INDEX(GOOGLEFINANCE(L17,""Price"",WORKDAY(TODAY(),-252),today()),,2))"),"") | M21: =IFERROR(__xludf.DUMMYFUNCTION("SPARKLINE(INDEX(GOOGLEFINANCE(M17,""Price"",WORKDAY(TODAY(),-252),today()),,2))"),"") | N21: =IFERROR(__xludf.DUMMYFUNCTION("SPARKLINE(INDEX(GOOGLEFINANCE(N17,""Price"",WORKDAY(TODAY(),-252),today()),,2))"),"") | O21: =IFERROR(__xludf.DUMMYFUNCTION("SPARKLINE(INDEX(GOOGLEFINANCE(O17,""Price"",WORKDAY(TODAY(),-252),today()),,2))"),"")
B22: Market Cap (BN) | C22: =IFERROR(__xludf.DUMMYFUNCTION("googlefinance(C16,""Marketcap"")/1000000000"),206.059572106) -> 206.05957
B23: EPS | C23: =IFERROR(__xludf.DUMMYFUNCTION("GOOGLEFINANCE(C16,""EPS"")"),32.38) -> 32.38 | D23: Days Gainer | G23: =offset(B29:B122,MATCH(MAX(I29:I122),I29:I122,0),0,1) -> #N/A | I23: =(Max(I29:I122)) -> #N/A
B24: PE | C24: =IFERROR(__xludf.DUMMYFUNCTION("GOOGLEFINANCE(C16,""PE"")"),45.25) -> 45.25 | D24: Days Losser | G24: =offset(B29:B122,MATCH(MIN(I29:I122),I29:I122,0),0,1) -> #N/A | I24: =(Min(I29:I122)) -> #N/A
B25: Watchlists
B26: Portfolio Holdings
B27: Note: Target are set upon Mega cap - 10 to 20, Large cap - 15 to 25, Mid cap - 20 to 30, Small cap - 25 to 35
B28: Ticker | C28: Company Name | D28: 10% TB | E28: 15% TB | F28: Mk Cap | G28: Price | H28: MTB S | I28: % Ch | J28: 52Wk H | K28: 52 Wk L | L28: TB % | M28: MTB | N28: Cap Bar | O28: Mk Cap (In 1 Cr)
B29: BOM:514183 | C29: =IFERROR(__xludf.DUMMYFUNCTION("if(ISBLANK(B29),"""",GOOGLEFINANCE(B29,""NAME""))"),"Black Rose Industries Ltd") -> Black Rose Industries Ltd | D29: =if(ISBLANK(B29),"",if(L29<-10%,"B","H")) -> B | E29: =if(ISBLANK(B29),"",if(L29<-15%,"B","H")) -> B | F29: =IF(ISBLANK(B29), "", IF(O29 > 600000, "Mega Cap", IF(O29 > 30000, "Large Cap", IF(O29 > 7500, "Mid Cap", "Small Cap")))) -> Small Cap | G29: =IFERROR(__xludf.DUMMYFUNCTION("if(ISBLANK(B29),"""",GOOGLEFINANCE(B29,""price""))"),113.4) -> 113.4 | H29: =if(ISBLANK(B29),"",if(ISBLANK(M29),"",if(M29=0,"Extra",if(G29<M29,"Buy","Hold")))) -> Hold | I29: =IFERROR(__xludf.DUMMYFUNCTION("if(ISBLANK(B29),"""",GOOGLEFINANCE(B29,""CHANGEPCT"")/100)"),0.024399999999999998) -> 0.0244 | J29: =IFERROR(__xludf.DUMMYFUNCTION("if(ISBLANK(B29),"""",GOOGLEFINANCE(B29,""HIGH52""))"),137.95) -> 137.95 | K29: =IFERROR(__xludf.DUMMYFUNCTION("if(ISBLANK(B29),"""",GOOGLEFINANCE(B29,""LOW52""))"),61.0) -> 61 | L29: =if(isblank(B29),"",(G29-J29)/J29) -> -0.17796303 | M29: =J29-(J29*0.45) -> 75.8725 | N29: =IF(ISBLANK(B29), "", IF(AND(O29 >= 0, O29 <= 7500), "||||", IF(AND(O29 > 7500, O29 <= 30000), "|||", IF(AND(O29 > 30000, O29 <= 600000), "||", IF(O29 > 600000, "|", ""))))) -> |||| | O29: =IFERROR(__xludf.DUMMYFUNCTION("if(ISBLANK(B29),"""",googlefinance(B29,""Marketcap"")/10000000)"),571.0470062) -> 571.04701
B30: BOM:541167 | C30: =IFERROR(__xludf.DUMMYFUNCTION("if(ISBLANK(B30),"""",GOOGLEFINANCE(B30,""NAME""))"),"Yasho Industries Ltd") -> Yasho Industries Ltd | D30: =if(ISBLANK(B30),"",if(L30<-10%,"B","H")) -> H | E30: =if(ISBLANK(B30),"",if(L30<-15%,"B","H")) -> H | F30: =IF(ISBLANK(B30), "", IF(O30 > 600000, "Mega Cap", IF(O30 > 30000, "Large Cap", IF(O30 > 7500, "Mid Cap", "Small Cap")))) -> Small Cap | G30: =IFERROR(__xludf.DUMMYFUNCTION("if(ISBLANK(B30),"""",GOOGLEFINANCE(B30,""price""))"),2887.0) -> 2887 | H30: =if(ISBLANK(B30),"",if(ISBLANK(M30),"",if(M30=0,"Extra",if(G30<M30,"Buy","Hold")))) -> Hold | I30: =IFERROR(__xludf.DUMMYFUNCTION("if(ISBLANK(B30),"""",GOOGLEFINANCE(B30,""CHANGEPCT"")/100)"),0.0060999999999999995) -> 0.0061 | J30: =IFERROR(__xludf.DUMMYFUNCTION("if(ISBLANK(B30),"""",GOOGLEFINANCE(B30,""HIGH52""))"),3176.3) -> 3176.3 | K30: =IFERROR(__xludf.DUMMYFUNCTION("if(ISBLANK(B30),"""",GOOGLEFINANCE(B30,""LOW52""))"),1151.0) -> 1151 | L30: =if(isblank(B30),"",(G30-J30)/J30) -> -0.091080817 | M30: =J30-(J30*0.35) -> 2064.595 | N30: =IF(ISBLANK(B30), "", IF(AND(O30 >= 0, O30 <= 7500), "||||", IF(AND(O30 > 7500, O30 <= 30000), "|||", IF(AND(O30 > 30000, O30 <= 600000), "||", IF(O30 > 600000, "|", ""))))) -> |||| | O30: =IFERROR(__xludf.DUMMYFUNCTION("if(ISBLANK(B30),"""",googlefinance(B30,""Marketcap"")/10000000)"),3477.7469218) -> 3477.7469
B31: NSE:AARTIIND | C31: =IFERROR(__xludf.DUMMYFUNCTION("if(ISBLANK(B31),"""",GOOGLEFINANCE(B31,""NAME""))"),"Aarti Industries Ltd") -> Aarti Industries Ltd | D31: =if(ISBLANK(B31),"",if(L31<-10%,"B","H")) -> H | E31: =if(ISBLANK(B31),"",if(L31<-15%,"B","H")) -> H | F31: =IF(ISBLANK(B31), "", IF(O31 > 600000, "Mega Cap", IF(O31 > 30000, "Large Cap", IF(O31 > 7500, "Mid Cap", "Small Cap")))) -> Mid Cap | G31: =IFERROR(__xludf.DUMMYFUNCTION("if(ISBLANK(B31),"""",GOOGLEFINANCE(B31,""price""))"),478.6) -> 478.6 | H31: =if(ISBLANK(B31),"",if(ISBLANK(M31),"",if(M31=0,"Extra",if(G31<M31,"Buy","Hold")))) -> Hold | I31: =IFERROR(__xludf.DUMMYFUNCTION("if(ISBLANK(B31),"""",GOOGLEFINANCE(B31,""CHANGEPCT"")/100)"),-0.0203) -> -0.0203 | J31: =IFERROR(__xludf.DUMMYFUNCTION("if(ISBLANK(B31),"""",GOOGLEFINANCE(B31,""HIGH52""))"),523.1) -> 523.1 | K31: =IFERROR(__xludf.DUMMYFUNCTION("if(ISBLANK(B31),"""",GOOGLEFINANCE(B31,""LOW52""))"),338.05) -> 338.05 | L31: =if(isblank(B31),"",(G31-J31)/J31) -> -0.085069776 | M31: =J31-(J31*0.55) -> 235.395 | N31: =IF(ISBLANK(B31), "", IF(AND(O31 >= 0, O31 <= 7500), "||||", IF(AND(O31 > 7500, O31 <= 30000), "|||", IF(AND(O31 > 30000, O31 <= 600000), "||", IF(O31 > 600000, "|", ""))))) -> ||| | O31: =IFERROR(__xludf.DUMMYFUNCTION("if(ISBLANK(B31),"""",googlefinance(B31,""Marketcap"")/10000000)"),17360.0952973) -> 17360.095
B32: NSE:AFFLE | C32: =IFERROR(__xludf.DUMMYFUNCTION("if(ISBLANK(B32),"""",GOOGLEFINANCE(B32,""NAME""))"),"Affle 3i Ltd") -> Affle 3i Ltd | D32: =if(ISBLANK(B32),"",if(L32<-10%,"B","H")) -> B | E32: =if(ISBLANK(B32),"",if(L32<-15%,"B","H")) -> B | F32: =IF(ISBLANK(B32), "", IF(O32 > 600000, "Mega Cap", IF(O32 > 30000, "Large Cap", IF(O32 > 7500, "Mid Cap", "Small Cap")))) -> Mid Cap | G32: =IFERROR(__xludf.DUMMYFUNCTION("if(ISBLANK(B32),"""",GOOGLEFINANCE(B32,""price""))"),1465.1) -> 1465.1 | H32: =if(ISBLANK(B32),"",if(ISBLANK(M32),"",if(M32=0,"Extra",if(G32<M32,"Buy","Hold")))) -> Buy | I32: =IFERROR(__xludf.DUMMYFUNCTION("if(ISBLANK(B32),"""",GOOGLEFINANCE(B32,""CHANGEPCT"")/100)"),0.012199999999999999) -> 0.0122 | J32: =IFERROR(__xludf.DUMMYFUNCTION("if(ISBLANK(B32),"""",GOOGLEFINANCE(B32,""HIGH52""))"),2185.9) -> 2185.9 | K32: =IFERROR(__xludf.DUMMYFUNCTION("if(ISBLANK(B32),"""",GOOGLEFINANCE(B32,""LOW52""))"),1251.3) -> 1251.3 | L32: =if(isblank(B32),"",(G32-J32)/J32) -> -0.32974976 | M32: =J32-(J32*0.27) -> 1595.707 | N32: =IF(ISBLANK(B32), "", IF(AND(O32 >= 0, O32 <= 7500), "||||", IF(AND(O32 > 7500, O32 <= 30000), "|||", IF(AND(O32 > 30000, O32 <= 600000), "||", IF(O32 > 600000, "|", ""))))) -> ||| | O32: =IFERROR(__xludf.DUMMYFUNCTION("if(ISBLANK(B32),"""",googlefinance(B32,""Marketcap"")/10000000)"),20605.9572106) -> 20605.957
B33: NSE:ALKYLAMINE | C33: =IFERROR(__xludf.DUMMYFUNCTION("if(ISBLANK(B33),"""",GOOGLEFINANCE(B33,""NAME""))"),"Alkyl Amines Chemicals Ltd") -> Alkyl Amines Chemicals Ltd | D33: =if(ISBLANK(B33),"",if(L33<-10%,"B","H")) -> B | E33: =if(ISBLANK(B33),"",if(L33<-15%,"B","H")) -> B | F33: =IF(ISBLANK(B33), "", IF(O33 > 600000, "Mega Cap", IF(O33 > 30000, "Large Cap", IF(O33 > 7500, "Mid Cap", "Small Cap")))) -> Mid Cap | G33: =IFERROR(__xludf.DUMMYFUNCTION("if(ISBLANK(B33),"""",GOOGLEFINANCE(B33,""price""))"),1802.0) -> 1802 | H33: =if(ISBLANK(B33),"",if(ISBLANK(M33),"",if(M33=0,"Extra",if(G33<M33,"Buy","Hold")))) -> Hold | I33: =IFERROR(__xludf.DUMMYFUNCTION("if(ISBLANK(B33),"""",GOOGLEFINANCE(B33,""CHANGEPCT"")/100)"),0.0018) -> 0.0018 | J33: =IFERROR(__xludf.DUMMYFUNCTION("if(ISBLANK(B33),"""",GOOGLEFINANCE(B33,""HIGH52""))"),2438.8) -> 2438.8 | K33: =IFERROR(__xludf.DUMMYFUNCTION("if(ISBLANK(B33),"""",GOOGLEFINANCE(B33,""LOW52""))"),1212.0) -> 1212 | L33: =if(isblank(B33),"",(G33-J33)/J33) -> -0.26111202 | M33: =J33-(J33*0.4) -> 1463.28 | N33: =IF(ISBLANK(B33), "", IF(AND(O33 >= 0, O33 <= 7500), "||||", IF(AND(O33 > 7500, O33 <= 30000), "|||", IF(AND(O33 > 30000, O33 <= 600000), "||", IF(O33 > 600000, "|", ""))))) -> ||| | O33: =IFERROR(__xludf.DUMMYFUNCTION("if(ISBLANK(B33),"""",googlefinance(B33,""Marketcap"")/10000000)"),9157.1022823) -> 9157.1023
B34: NSE:AMIORG | C34: =IFERROR(__xludf.DUMMYFUNCTION("if(ISBLANK(B34),"""",GOOGLEFINANCE(B34,""NAME""))"),"#N/A") -> #N/A | D34: =if(ISBLANK(B34),"",if(L34<-10%,"B","H")) -> #N/A | E34: =if(ISBLANK(B34),"",if(L34<-15%,"B","H")) -> #N/A | F34: =IF(ISBLANK(B34), "", IF(O34 > 600000, "Mega Cap", IF(O34 > 30000, "Large Cap", IF(O34 > 7500, "Mid Cap", "Small Cap")))) -> #N/A | G34: =IFERROR(__xludf.DUMMYFUNCTION("if(ISBLANK(B34),"""",GOOGLEFINANCE(B34,""price""))"),"#N/A") -> #N/A | H34: =if(ISBLANK(B34),"",if(ISBLANK(M34),"",if(M34=0,"Extra",if(G34<M34,"Buy","Hold")))) -> #N/A | I34: =IFERROR(__xludf.DUMMYFUNCTION("if(ISBLANK(B34),"""",GOOGLEFINANCE(B34,""CHANGEPCT"")/100)"),"#N/A") -> #N/A | J34: =IFERROR(__xludf.DUMMYFUNCTION("if(ISBLANK(B34),"""",GOOGLEFINANCE(B34,""HIGH52""))"),"#N/A") -> #N/A | K34: =IFERROR(__xludf.DUMMYFUNCTION("if(ISBLANK(B34),"""",GOOGLEFINANCE(B34,""LOW52""))"),"#N/A") -> #N/A | L34: =if(isblank(B34),"",(G34-J34)/J34) -> #N/A | M34: =J34-(J34*0.27) -> #N/A | N34: =IF(ISBLANK(B34), "", IF(AND(O34 >= 0, O34 <= 7500), "||||", IF(AND(O34 > 7500, O34 <= 30000), "|||", IF(AND(O34 > 30000, O34 <= 600000), "||", IF(O34 > 600000, "|", ""))))) -> #N/A | O34: =IFERROR(__xludf.DUMMYFUNCTION("if(ISBLANK(B34),"""",googlefinance(B34,""Marketcap"")/10000000)"),"#N/A") -> #N/A
B35: NSE:ASIANPAINT | C35: =IFERROR(__xludf.DUMMYFUNCTION("if(ISBLANK(B35),"""",GOOGLEFINANCE(B35,""NAME""))"),"Asian Paints Ltd") -> Asian Paints Ltd | D35: =if(ISBLANK(B35),"",if(L35<-10%,"B","H")) -> H | E35: =if(ISBLANK(B35),"",if(L35<-15%,"B","H")) -> H | F35: =IF(ISBLANK(B35), "", IF(O35 > 600000, "Mega Cap", IF(O35 > 30000, "Large Cap", IF(O35 > 7500, "Mid Cap", "Small Cap")))) -> Large Cap | G35: =IFERROR(__xludf.DUMMYFUNCTION("if(ISBLANK(B35),"""",GOOGLEFINANCE(B35,""price""))"),2730.2) -> 2730.2 | H35: =if(ISBLANK(B35),"",if(ISBLANK(M35),"",if(M35=0,"Extra",if(G35<M35,"Buy","Hold")))) -> Hold | I35: =IFERROR(__xludf.DUMMYFUNCTION("if(ISBLANK(B35),"""",GOOGLEFINANCE(B35,""CHANGEPCT"")/100)"),-0.009000000000000001) -> -0.009 | J35: =IFERROR(__xludf.DUMMYFUNCTION("if(ISBLANK(B35),"""",GOOGLEFINANCE(B35,""HIGH52""))"),2985.7) -> 2985.7 | K35: =IFERROR(__xludf.DUMMYFUNCTION("if(ISBLANK(B35),"""",GOOGLEFINANCE(B35,""LOW52""))"),2115.0) -> 2115 | L35: =if(isblank(B35),"",(G35-J35)/J35) -> -0.085574572 | M35: =J35-(J35*0.4) -> 1791.42 | N35: =IF(ISBLANK(B35), "", IF(AND(O35 >= 0, O35 <= 7500), "||||", IF(AND(O35 > 7500, O35 <= 30000), "|||", IF(AND(O35 > 30000, O35 <= 600000), "||", IF(O35 > 600000, "|", ""))))) -> || | O35: =IFERROR(__xludf.DUMMYFUNCTION("if(ISBLANK(B35),"""",googlefinance(B35,""Marketcap"")/10000000)"),262067.7477967) -> 262067.75
B36: NSE:ASTRAL | C36: =IFERROR(__xludf.DUMMYFUNCTION("if(ISBLANK(B36),"""",GOOGLEFINANCE(B36,""NAME""))"),"Astral Ltd") -> Astral Ltd | D36: =if(ISBLANK(B36),"",if(L36<-10%,"B","H")) -> B | E36: =if(ISBLANK(B36),"",if(L36<-15%,"B","H")) -> B | F36: =IF(ISBLANK(B36), "", IF(O36 > 600000, "Mega Cap", IF(O36 > 30000, "Large Cap", IF(O36 > 7500, "Mid Cap", "Small Cap")))) -> Large Cap | G36: =IFERROR(__xludf.DUMMYFUNCTION("if(ISBLANK(B36),"""",GOOGLEFINANCE(B36,""price""))"),1356.9) -> 1356.9 | H36: =if(ISBLANK(B36),"",if(ISBLANK(M36),"",if(M36=0,"Extra",if(G36<M36,"Buy","Hold")))) -> Hold | I36: =IFERROR(__xludf.DUMMYFUNCTION("if(ISBLANK(B36),"""",GOOGLEFINANCE(B36,""CHANGEPCT"")/100)"),-0.0231) -> -0.0231 | J36: =IFERROR(__xludf.DUMMYFUNCTION("if(ISBLANK(B36),"""",GOOGLEFINANCE(B36,""HIGH52""))"),1768.7) -> 1768.7 | K36: =IFERROR(__xludf.DUMMYFUNCTION("if(ISBLANK(B36),"""",GOOGLEFINANCE(B36,""LOW52""))"),1263.7) -> 1263.7 | L36: =if(isblank(B36),"",(G36-J36)/J36) -> -0.23282637 | M36: =J36-(J36*0.5) -> 884.35 | N36: =IF(ISBLANK(B36), "", IF(AND(O36 >= 0, O36 <= 7500), "||||", IF(AND(O36 > 7500, O36 <= 30000), "|||", IF(AND(O36 > 30000, O36 <= 600000), "||", IF(O36 > 600000, "|", ""))))) -> || | O36: =IFERROR(__xludf.DUMMYFUNCTION("if(ISBLANK(B36),"""",googlefinance(B36,""Marketcap"")/10000000)"),36451.0430988) -> 36451.043
B37: NSE:AUBANK | C37: =IFERROR(__xludf.DUMMYFUNCTION("if(ISBLANK(B37),"""",GOOGLEFINANCE(B37,""NAME""))"),"AU Small Finance Bank Ltd") -> AU Small Finance Bank Ltd | D37: =if(ISBLANK(B37),"",if(L37<-10%,"B","H")) -> H | E37: =if(ISBLANK(B37),"",if(L37<-15%,"B","H")) -> H | F37: =IF(ISBLANK(B37), "", IF(O37 > 600000, "Mega Cap", IF(O37 > 30000, "Large Cap", IF(O37 > 7500, "Mid Cap", "Small Cap")))) -> Large Cap | G37: =IFERROR(__xludf.DUMMYFUNCTION("if(ISBLANK(B37),"""",GOOGLEFINANCE(B37,""price""))"),1066.0) -> 1066 | H37: =if(ISBLANK(B37),"",if(ISBLANK(M37),"",if(M37=0,"Extra",if(G37<M37,"Buy","Hold")))) -> Hold | I37: =IFERROR(__xludf.DUMMYFUNCTION("if(ISBLANK(B37),"""",GOOGLEFINANCE(B37,""CHANGEPCT"")/100)"),0.0043) -> 0.0043 | J37: =IFERROR(__xludf.DUMMYFUNCTION("if(ISBLANK(B37),"""",GOOGLEFINANCE(B37,""HIGH52""))"),1079.55) -> 1079.55 | K37: =IFERROR(__xludf.DUMMYFUNCTION("if(ISBLANK(B37),"""",GOOGLEFINANCE(B37,""LOW52""))"),682.15) -> 682.15 | L37: =if(isblank(B37),"",(G37-J37)/J37) -> -0.012551526 | M37: =J37-(J37*0.35) -> 701.7075 | N37: =IF(ISBLANK(B37), "", IF(AND(O37 >= 0, O37 <= 7500), "||||", IF(AND(O37 > 7500, O37 <= 30000), "|||", IF(AND(O37 > 30000, O37 <= 600000), "||", IF(O37 > 600000, "|", ""))))) -> || | O37: =IFERROR(__xludf.DUMMYFUNCTION("if(ISBLANK(B37),"""",googlefinance(B37,""Marketcap"")/10000000)"),79446.9502445) -> 79446.95
B38: NSE:BAJFINANCE | C38: =IFERROR(__xludf.DUMMYFUNCTION("if(ISBLANK(B38),"""",GOOGLEFINANCE(B38,""NAME""))"),"Bajaj Finance Ltd") -> Bajaj Finance Ltd | D38: =if(ISBLANK(B38),"",if(L38<-10%,"B","H")) -> H | E38: =if(ISBLANK(B38),"",if(L38<-15%,"B","H")) -> H | F38: =IF(ISBLANK(B38), "", IF(O38 > 600000, "Mega Cap", IF(O38 > 30000, "Large Cap", IF(O38 > 7500, "Mid Cap", "Small Cap")))) -> Large Cap | G38: =IFERROR(__xludf.DUMMYFUNCTION("if(ISBLANK(B38),"""",GOOGLEFINANCE(B38,""price""))"),1039.4) -> 1039.4 | H38: =if(ISBLANK(B38),"",if(ISBLANK(M38),"",if(M38=0,"Extra",if(G38<M38,"Buy","Hold")))) -> Hold | I38: =IFERROR(__xludf.DUMMYFUNCTION("if(ISBLANK(B38),"""",GOOGLEFINANCE(B38,""CHANGEPCT"")/100)"),0.01) -> 0.01 | J38: =IFERROR(__xludf.DUMMYFUNCTION("if(ISBLANK(B38),"""",GOOGLEFINANCE(B38,""HIGH52""))"),1102.5) -> 1102.5 | K38: =IFERROR(__xludf.DUMMYFUNCTION("if(ISBLANK(B38),"""",GOOGLEFINANCE(B38,""LOW52""))"),787.9) -> 787.9 | L38: =if(isblank(B38),"",(G38-J38)/J38) -> -0.05723356 | M38: =J38-(J38*0.25) -> 826.875 | N38: =IF(ISBLANK(B38), "", IF(AND(O38 >= 0, O38 <= 7500), "||||", IF(AND(O38 > 7500, O38 <= 30000), "|||", IF(AND(O38 > 30000, O38 <= 600000), "||", IF(O38 > 600000, "|", ""))))) -> || | O38: =IFERROR(__xludf.DUMMYFUNCTION("if(ISBLANK(B38),"""",googlefinance(B38,""Marketcap"")/10000000)"),64744.715915) -> 64744.716
B39: NSE:BATAINDIA | C39: =IFERROR(__xludf.DUMMYFUNCTION("if(ISBLANK(B39),"""",GOOGLEFINANCE(B39,""NAME""))"),"Bata India Ltd") -> Bata India Ltd | D39: =if(ISBLANK(B39),"",if(L39<-10%,"B","H")) -> B | E39: =if(ISBLANK(B39),"",if(L39<-15%,"B","H")) -> B | F39: =IF(ISBLANK(B39), "", IF(O39 > 600000, "Mega Cap", IF(O39 > 30000, "Large Cap", IF(O39 > 7500, "Mid Cap", "Small Cap")))) -> Mid Cap | G39: =IFERROR(__xludf.DUMMYFUNCTION("if(ISBLANK(B39),"""",GOOGLEFINANCE(B39,""price""))"),684.0) -> 684 | H39: =if(ISBLANK(B39),"",if(ISBLANK(M39),"",if(M39=0,"Extra",if(G39<M39,"Buy","Hold")))) -> Buy | I39: =IFERROR(__xludf.DUMMYFUNCTION("if(ISBLANK(B39),"""",GOOGLEFINANCE(B39,""CHANGEPCT"")/100)"),-0.0074) -> -0.0074 | J39: =IFERROR(__xludf.DUMMYFUNCTION("if(ISBLANK(B39),"""",GOOGLEFINANCE(B39,""HIGH52""))"),1284.9) -> 1284.9 | K39: =IFERROR(__xludf.DUMMYFUNCTION("if(ISBLANK(B39),"""",GOOGLEFINANCE(B39,""LOW52""))"),605.0) -> 605 | L39: =if(isblank(B39),"",(G39-J39)/J39) -> -0.46766285 | M39: =J39-(J39*0.27) -> 937.977 | N39: =IF(ISBLANK(B39), "", IF(AND(O39 >= 0, O39 <= 7500), "||||", IF(AND(O39 > 7500, O39 <= 30000), "|||", IF(AND(O39 > 30000, O39 <= 600000), "||", IF(O39 > 600000, "|", ""))))) -> ||| | O39: =IFERROR(__xludf.DUMMYFUNCTION("if(ISBLANK(B39),"""",googlefinance(B39,""Marketcap"")/10000000)"),8779.2723946) -> 8779.2724
B40: NSE:BERGEPAINT | C40: =IFERROR(__xludf.DUMMYFUNCTION("if(ISBLANK(B40),"""",GOOGLEFINANCE(B40,""NAME""))"),"Berger Paints India Ltd") -> Berger Paints India Ltd | D40: =if(ISBLANK(B40),"",if(L40<-10%,"B","H")) -> B | E40: =if(ISBLANK(B40),"",if(L40<-15%,"B","H")) -> B | F40: =IF(ISBLANK(B40), "", IF(O40 > 600000, "Mega Cap", IF(O40 > 30000, "Large Cap", IF(O40 > 7500, "Mid Cap", "Small Cap")))) -> Large Cap | G40: =IFERROR(__xludf.DUMMYFUNCTION("if(ISBLANK(B40),"""",GOOGLEFINANCE(B40,""price""))"),509.9) -> 509.9 | H40: =if(ISBLANK(B40),"",if(ISBLANK(M40),"",if(M40=0,"Extra",if(G40<M40,"Buy","Hold")))) -> Hold | I40: =IFERROR(__xludf.DUMMYFUNCTION("if(ISBLANK(B40),"""",GOOGLEFINANCE(B40,""CHANGEPCT"")/100)"),-0.0229) -> -0.0229 | J40: =IFERROR(__xludf.DUMMYFUNCTION("if(ISBLANK(B40),"""",GOOGLEFINANCE(B40,""HIGH52""))"),600.0) -> 600 | K40: =IFERROR(__xludf.DUMMYFUNCTION("if(ISBLANK(B40),"""",GOOGLEFINANCE(B40,""LOW52""))"),391.1) -> 391.1 | L40: =if(isblank(B40),"",(G40-J40)/J40) -> -0.15016667 | M40: =J40-(J40*0.3) -> 420 | N40: =IF(ISBLANK(B40), "", IF(AND(O40 >= 0, O40 <= 7500), "||||", IF(AND(O40 > 7500, O40 <= 30000), "|||", IF(AND(O40 > 30000, O40 <= 600000), "||", IF(O40 > 600000, "|", ""))))) -> || | O40: =IFERROR(__xludf.DUMMYFUNCTION("if(ISBLANK(B40),"""",googlefinance(B40,""Marketcap"")/10000000)"),59337.4062917) -> 59337.406
B41: NSE:BSE | C41: =IFERROR(__xludf.DUMMYFUNCTION("if(ISBLANK(B41),"""",GOOGLEFINANCE(B41,""NAME""))"),"BSE Ltd") -> BSE Ltd | D41: =if(ISBLANK(B41),"",if(L41<-10%,"B","H")) -> B | E41: =if(ISBLANK(B41),"",if(L41<-15%,"B","H")) -> B | F41: =IF(ISBLANK(B41), "", IF(O41 > 600000, "Mega Cap", IF(O41 > 30000, "Large Cap", IF(O41 > 7500, "Mid Cap", "Small Cap")))) -> Large Cap | G41: =IFERROR(__xludf.DUMMYFUNCTION("if(ISBLANK(B41),"""",GOOGLEFINANCE(B41,""price""))"),3678.7) -> 3678.7 | H41: =if(ISBLANK(B41),"",if(ISBLANK(M41),"",if(M41=0,"Extra",if(G41<M41,"Buy","Hold")))) -> Hold | I41: =IFERROR(__xludf.DUMMYFUNCTION("if(ISBLANK(B41),"""",GOOGLEFINANCE(B41,""CHANGEPCT"")/100)"),-0.0326) -> -0.0326 | J41: =IFERROR(__xludf.DUMMYFUNCTION("if(ISBLANK(B41),"""",GOOGLEFINANCE(B41,""HIGH52""))"),4446.8) -> 4446.8 | K41: =IFERROR(__xludf.DUMMYFUNCTION("if(ISBLANK(B41),"""",GOOGLEFINANCE(B41,""LOW52""))"),2021.5) -> 2021.5 | L41: =if(isblank(B41),"",(G41-J41)/J41) -> -0.17273095 | M41: =J41-(J41*0.55) -> 2001.06 | N41: =IF(ISBLANK(B41), "", IF(AND(O41 >= 0, O41 <= 7500), "||||", IF(AND(O41 > 7500, O41 <= 30000), "|||", IF(AND(O41 > 30000, O41 <= 600000), "||", IF(O41 > 600000, "|", ""))))) -> || | O41: =IFERROR(__xludf.DUMMYFUNCTION("if(ISBLANK(B41),"""",googlefinance(B41,""Marketcap"")/10000000)"),149833.1179282) -> 149833.12
B42: NSE:CAMS | C42: =IFERROR(__xludf.DUMMYFUNCTION("if(ISBLANK(B42),"""",GOOGLEFINANCE(B42,""NAME""))"),"Computer Age Management Services Ltd") -> Computer Age Management Services Ltd | D42: =if(ISBLANK(B42),"",if(L42<-10%,"B","H")) -> H | E42: =if(ISBLANK(B42),"",if(L42<-15%,"B","H")) -> H | F42: =IF(ISBLANK(B42), "", IF(O42 > 600000, "Mega Cap", IF(O42 > 30000, "Large Cap", IF(O42 > 7500, "Mid Cap", "Small Cap")))) -> Mid Cap | G42: =IFERROR(__xludf.DUMMYFUNCTION("if(ISBLANK(B42),"""",GOOGLEFINANCE(B42,""price""))"),777.35) -> 777.35 | H42: =if(ISBLANK(B42),"",if(ISBLANK(M42),"",if(M42=0,"Extra",if(G42<M42,"Buy","Hold")))) -> Hold | I42: =IFERROR(__xludf.DUMMYFUNCTION("if(ISBLANK(B42),"""",GOOGLEFINANCE(B42,""CHANGEPCT"")/100)"),-0.014499999999999999) -> -0.0145 | J42: =IFERROR(__xludf.DUMMYFUNCTION("if(ISBLANK(B42),"""",GOOGLEFINANCE(B42,""HIGH52""))"),857.8) -> 857.8 | K42: =IFERROR(__xludf.DUMMYFUNCTION("if(ISBLANK(B42),"""",GOOGLEFINANCE(B42,""LOW52""))"),611.4) -> 611.4 | L42: =if(isblank(B42),"",(G42-J42)/J42) -> -0.09378643 | M42: =J42-(J42*0.45) -> 471.79 | N42: =IF(ISBLANK(B42), "", IF(AND(O42 >= 0, O42 <= 7500), "||||", IF(AND(O42 > 7500, O42 <= 30000), "|||", IF(AND(O42 > 30000, O42 <= 600000), "||", IF(O42 > 600000, "|", ""))))) -> ||| | O42: =IFERROR(__xludf.DUMMYFUNCTION("if(ISBLANK(B42),"""",googlefinance(B42,""Marketcap"")/10000000)"),19294.1917485) -> 19294.192
B43: NSE:CDSL | C43: =IFERROR(__xludf.DUMMYFUNCTION("if(ISBLANK(B43),"""",GOOGLEFINANCE(B43,""NAME""))"),"Central Depository Services (India) Ltd") -> Central Depository Services (India) Ltd | D43: =if(ISBLANK(B43),"",if(L43<-10%,"B","H")) -> B | E43: =if(ISBLANK(B43),"",if(L43<-15%,"B","H")) -> B | F43: =IF(ISBLANK(B43), "", IF(O43 > 600000, "Mega Cap", IF(O43 > 30000, "Large Cap", IF(O43 > 7500, "Mid Cap", "Small Cap")))) -> Mid Cap | G43: =IFERROR(__xludf.DUMMYFUNCTION("if(ISBLANK(B43),"""",GOOGLEFINANCE(B43,""price""))"),1358.0) -> 1358 | H43: =if(ISBLANK(B43),"",if(ISBLANK(M43),"",if(M43=0,"Extra",if(G43<M43,"Buy","Hold")))) -> Hold | I43: =IFERROR(__xludf.DUMMYFUNCTION("if(ISBLANK(B43),"""",GOOGLEFINANCE(B43,""CHANGEPCT"")/100)"),-4.0E-4) -> -0.0004 | J43: =IFERROR(__xludf.DUMMYFUNCTION("if(ISBLANK(B43),"""",GOOGLEFINANCE(B43,""HIGH52""))"),1794.9) -> 1794.9 | K43: =IFERROR(__xludf.DUMMYFUNCTION("if(ISBLANK(B43),"""",GOOGLEFINANCE(B43,""LOW52""))"),1116.3) -> 1116.3 | L43: =if(isblank(B43),"",(G43-J43)/J43) -> -0.24341189 | M43: =J43-(J43*0.55) -> 807.705 | N43: =IF(ISBLANK(B43), "", IF(AND(O43 >= 0, O43 <= 7500), "||||", IF(AND(O43 > 7500, O43 <= 30000), "|||", IF(AND(O43 > 30000, O43 <= 600000), "||", IF(O43 > 600000, "|", ""))))) -> ||| | O43: =IFERROR(__xludf.DUMMYFUNCTION("if(ISBLANK(B43),"""",googlefinance(B43,""Marketcap"")/10000000)"),28382.18642) -> 28382.186
B44: NSE:CGPOWER | C44: =IFERROR(__xludf.DUMMYFUNCTION("if(ISBLANK(B44),"""",GOOGLEFINANCE(B44,""NAME""))"),"CG Power and Industrial Solutions Ltd") -> CG Power and Industrial Solutions Ltd | D44: =if(ISBLANK(B44),"",if(L44<-10%,"B","H")) -> H | E44: =if(ISBLANK(B44),"",if(L44<-15%,"B","H")) -> H | F44: =IF(ISBLANK(B44), "", IF(O44 > 600000, "Mega Cap", IF(O44 > 30000, "Large Cap", IF(O44 > 7500, "Mid Cap", "Small Cap")))) -> Large Cap | G44: =IFERROR(__xludf.DUMMYFUNCTION("if(ISBLANK(B44),"""",GOOGLEFINANCE(B44,""price""))"),910.45) -> 910.45 | H44: =if(ISBLANK(B44),"",if(ISBLANK(M44),"",if(M44=0,"Extra",if(G44<M44,"Buy","Hold")))) -> Extra | I44: =IFERROR(__xludf.DUMMYFUNCTION("if(ISBLANK(B44),"""",GOOGLEFINANCE(B44,""CHANGEPCT"")/100)"),-0.0158) -> -0.0158 | J44: =IFERROR(__xludf.DUMMYFUNCTION("if(ISBLANK(B44),"""",GOOGLEFINANCE(B44,""HIGH52""))"),980.9) -> 980.9 | K44: =IFERROR(__xludf.DUMMYFUNCTION("if(ISBLANK(B44),"""",GOOGLEFINANCE(B44,""LOW52""))"),525.5) -> 525.5 | L44: =if(isblank(B44),"",(G44-J44)/J44) -> -0.071821796 | M44: 0 | N44: =IF(ISBLANK(B44), "", IF(AND(O44 >= 0, O44 <= 7500), "||||", IF(AND(O44 > 7500, O44 <= 30000), "|||", IF(AND(O44 > 30000, O44 <= 600000), "||", IF(O44 > 600000, "|", ""))))) -> || | O44: =IFERROR(__xludf.DUMMYFUNCTION("if(ISBLANK(B44),"""",googlefinance(B44,""Marketcap"")/10000000)"),139273.68) -> 139273.68
B45: NSE:CLEAN | C45: =IFERROR(__xludf.DUMMYFUNCTION("if(ISBLANK(B45),"""",GOOGLEFINANCE(B45,""NAME""))"),"Clean Science and Technology Ltd") -> Clean Science and Technology Ltd | D45: =if(ISBLANK(B45),"",if(L45<-10%,"B","H")) -> B | E45: =if(ISBLANK(B45),"",if(L45<-15%,"B","H")) -> B | F45: =IF(ISBLANK(B45), "", IF(O45 > 600000, "Mega Cap", IF(O45 > 30000, "Large Cap", IF(O45 > 7500, "Mid Cap", "Small Cap")))) -> Mid Cap | G45: =IFERROR(__xludf.DUMMYFUNCTION("if(ISBLANK(B45),"""",GOOGLEFINANCE(B45,""price""))"),798.0) -> 798 | H45: =if(ISBLANK(B45),"",if(ISBLANK(M45),"",if(M45=0,"Extra",if(G45<M45,"Buy","Hold")))) -> Buy | I45: =IFERROR(__xludf.DUMMYFUNCTION("if(ISBLANK(B45),"""",GOOGLEFINANCE(B45,""CHANGEPCT"")/100)"),0.0067) -> 0.0067 | J45: =IFERROR(__xludf.DUMMYFUNCTION("if(ISBLANK(B45),"""",GOOGLEFINANCE(B45,""HIGH52""))"),1490.0) -> 1490 | K45: =IFERROR(__xludf.DUMMYFUNCTION("if(ISBLANK(B45),"""",GOOGLEFINANCE(B45,""LOW52""))"),652.0) -> 652 | L45: =if(isblank(B45),"",(G45-J45)/J45) -> -0.46442953 | M45: =J45-(J45*0.4) -> 894 | N45: =IF(ISBLANK(B45), "", IF(AND(O45 >= 0, O45 <= 7500), "||||", IF(AND(O45 > 7500, O45 <= 30000), "|||", IF(AND(O45 > 30000, O45 <= 600000), "||", IF(O45 > 600000, "|", ""))))) -> ||| | O45: =IFERROR(__xludf.DUMMYFUNCTION("if(ISBLANK(B45),"""",googlefinance(B45,""Marketcap"")/10000000)"),8537.4206266) -> 8537.4206
B46: NSE:COLPAL | C46: =IFERROR(__xludf.DUMMYFUNCTION("if(ISBLANK(B46),"""",GOOGLEFINANCE(B46,""NAME""))"),"Colgate-Palmolive (India) Ltd") -> Colgate-Palmolive (India) Ltd | D46: =if(ISBLANK(B46),"",if(L46<-10%,"B","H")) -> B | E46: =if(ISBLANK(B46),"",if(L46<-15%,"B","H")) -> B | F46: =IF(ISBLANK(B46), "", IF(O46 > 600000, "Mega Cap", IF(O46 > 30000, "Large Cap", IF(O46 > 7500, "Mid Cap", "Small Cap")))) -> Large Cap | G46: =IFERROR(__xludf.DUMMYFUNCTION("if(ISBLANK(B46),"""",GOOGLEFINANCE(B46,""price""))"),2076.4) -> 2076.4 | H46: =if(ISBLANK(B46),"",if(ISBLANK(M46),"",if(M46=0,"Extra",if(G46<M46,"Buy","Hold")))) -> Hold | I46: =IFERROR(__xludf.DUMMYFUNCTION("if(ISBLANK(B46),"""",GOOGLEFINANCE(B46,""CHANGEPCT"")/100)"),-0.0015) -> -0.0015 | J46: =IFERROR(__xludf.DUMMYFUNCTION("if(ISBLANK(B46),"""",GOOGLEFINANCE(B46,""HIGH52""))"),2504.0) -> 2504 | K46: =IFERROR(__xludf.DUMMYFUNCTION("if(ISBLANK(B46),"""",GOOGLEFINANCE(B46,""LOW52""))"),1782.0) -> 1782 | L46: =if(isblank(B46),"",(G46-J46)/J46) -> -0.17076677 | M46: =J46-(J46*0.45) -> 1377.2 | N46: =IF(ISBLANK(B46), "", IF(AND(O46 >= 0, O46 <= 7500), "||||", IF(AND(O46 > 7500, O46 <= 30000), "|||", IF(AND(O46 > 30000, O46 <= 600000), "||", IF(O46 > 600000, "|", ""))))) -> || | O46: =IFERROR(__xludf.DUMMYFUNCTION("if(ISBLANK(B46),"""",googlefinance(B46,""Marketcap"")/10000000)"),56475.0873278) -> 56475.087
B47: NSE:DABUR | C47: =IFERROR(__xludf.DUMMYFUNCTION("if(ISBLANK(B47),"""",GOOGLEFINANCE(B47,""NAME""))"),"Dabur India Ltd") -> Dabur India Ltd | D47: =if(ISBLANK(B47),"",if(L47<-10%,"B","H")) -> B | E47: =if(ISBLANK(B47),"",if(L47<-15%,"B","H")) -> B | F47: =IF(ISBLANK(B47), "", IF(O47 > 600000, "Mega Cap", IF(O47 > 30000, "Large Cap", IF(O47 > 7500, "Mid Cap", "Small Cap")))) -> Large Cap | G47: =IFERROR(__xludf.DUMMYFUNCTION("if(ISBLANK(B47),"""",GOOGLEFINANCE(B47,""price""))"),454.0) -> 454 | H47: =if(ISBLANK(B47),"",if(ISBLANK(M47),"",if(M47=0,"Extra",if(G47<M47,"Buy","Hold")))) -> Hold | I47: =IFERROR(__xludf.DUMMYFUNCTION("if(ISBLANK(B47),"""",GOOGLEFINANCE(B47,""CHANGEPCT"")/100)"),0.009399999999999999) -> 0.0094 | J47: =IFERROR(__xludf.DUMMYFUNCTION("if(ISBLANK(B47),"""",GOOGLEFINANCE(B47,""HIGH52""))"),577.0) -> 577 | K47: =IFERROR(__xludf.DUMMYFUNCTION("if(ISBLANK(B47),"""",GOOGLEFINANCE(B47,""LOW52""))"),403.35) -> 403.35 | L47: =if(isblank(B47),"",(G47-J47)/J47) -> -0.21317158 | M47: =J47-(J47*0.35) -> 375.05 | N47: =IF(ISBLANK(B47), "", IF(AND(O47 >= 0, O47 <= 7500), "||||", IF(AND(O47 > 7500, O47 <= 30000), "|||", IF(AND(O47 > 30000, O47 <= 600000), "||", IF(O47 > 600000, "|", ""))))) -> || | O47: =IFERROR(__xludf.DUMMYFUNCTION("if(ISBLANK(B47),"""",googlefinance(B47,""Marketcap"")/10000000)"),80157.8625102) -> 80157.863
B48: NSE:DEEPAKNTR | C48: =IFERROR(__xludf.DUMMYFUNCTION("if(ISBLANK(B48),"""",GOOGLEFINANCE(B48,""NAME""))"),"Deepak Nitrite Ltd") -> Deepak Nitrite Ltd | D48: =if(ISBLANK(B48),"",if(L48<-10%,"B","H")) -> B | E48: =if(ISBLANK(B48),"",if(L48<-15%,"B","H")) -> B | F48: =IF(ISBLANK(B48), "", IF(O48 > 600000, "Mega Cap", IF(O48 > 30000, "Large Cap", IF(O48 > 7500, "Mid Cap", "Small Cap")))) -> Mid Cap | G48: =IFERROR(__xludf.DUMMYFUNCTION("if(ISBLANK(B48),"""",GOOGLEFINANCE(B48,""price""))"),1606.8) -> 1606.8 | H48: =if(ISBLANK(B48),"",if(ISBLANK(M48),"",if(M48=0,"Extra",if(G48<M48,"Buy","Hold")))) -> Hold | I48: =IFERROR(__xludf.DUMMYFUNCTION("if(ISBLANK(B48),"""",GOOGLEFINANCE(B48,""CHANGEPCT"")/100)"),0.0029) -> 0.0029 | J48: =IFERROR(__xludf.DUMMYFUNCTION("if(ISBLANK(B48),"""",GOOGLEFINANCE(B48,""HIGH52""))"),1999.5) -> 1999.5 | K48: =IFERROR(__xludf.DUMMYFUNCTION("if(ISBLANK(B48),"""",GOOGLEFINANCE(B48,""LOW52""))"),1280.0) -> 1280 | L48: =if(isblank(B48),"",(G48-J48)/J48) -> -0.1963991 | M48: =J48-(J48*0.45) -> 1099.725 | N48: =IF(ISBLANK(B48), "", IF(AND(O48 >= 0, O48 <= 7500), "||||", IF(AND(O48 > 7500, O48 <= 30000), "|||", IF(AND(O48 > 30000, O48 <= 600000), "||", IF(O48 > 600000, "|", ""))))) -> ||| | O48: =IFERROR(__xludf.DUMMYFUNCTION("if(ISBLANK(B48),"""",googlefinance(B48,""Marketcap"")/10000000)"),21915.6279059) -> 21915.628
B49: NSE:DIXON | C49: =IFERROR(__xludf.DUMMYFUNCTION("if(ISBLANK(B49),"""",GOOGLEFINANCE(B49,""NAME""))"),"Dixon Technologies (India) Ltd") -> Dixon Technologies (India) Ltd | D49: =if(ISBLANK(B49),"",if(L49<-10%,"B","H")) -> B | E49: =if(ISBLANK(B49),"",if(L49<-15%,"B","H")) -> B | F49: =IF(ISBLANK(B49), "", IF(O49 > 600000, "Mega Cap", IF(O49 > 30000, "Large Cap", IF(O49 > 7500, "Mid Cap", "Small Cap")))) -> Large Cap | G49: =IFERROR(__xludf.DUMMYFUNCTION("if(ISBLANK(B49),"""",GOOGLEFINANCE(B49,""price""))"),13237.0) -> 13237 | H49: =if(ISBLANK(B49),"",if(ISBLANK(M49),"",if(M49=0,"Extra",if(G49<M49,"Buy","Hold")))) -> Hold | I49: =IFERROR(__xludf.DUMMYFUNCTION("if(ISBLANK(B49),"""",GOOGLEFINANCE(B49,""CHANGEPCT"")/100)"),-0.005) -> -0.005 | J49: =IFERROR(__xludf.DUMMYFUNCTION("if(ISBLANK(B49),"""",GOOGLEFINANCE(B49,""HIGH52""))"),18471.0) -> 18471 | K49: =IFERROR(__xludf.DUMMYFUNCTION("if(ISBLANK(B49),"""",GOOGLEFINANCE(B49,""LOW52""))"),9600.0) -> 9600 | L49: =if(isblank(B49),"",(G49-J49)/J49) -> -0.28336311 | M49: =J49-(J49*0.35) -> 12006.15 | N49: =IF(ISBLANK(B49), "", IF(AND(O49 >= 0, O49 <= 7500), "||||", IF(AND(O49 > 7500, O49 <= 30000), "|||", IF(AND(O49 > 30000, O49 <= 600000), "||", IF(O49 > 600000, "|", ""))))) -> || | O49: =IFERROR(__xludf.DUMMYFUNCTION("if(ISBLANK(B49),"""",googlefinance(B49,""Marketcap"")/10000000)"),80859.432304) -> 80859.432
B50: NSE:DMART | C50: =IFERROR(__xludf.DUMMYFUNCTION("if(ISBLANK(B50),"""",GOOGLEFINANCE(B50,""NAME""))"),"Avenue Supermarts Ltd") -> Avenue Supermarts Ltd | D50: =if(ISBLANK(B50),"",if(L50<-10%,"B","H")) -> B | E50: =if(ISBLANK(B50),"",if(L50<-15%,"B","H")) -> B | F50: =IF(ISBLANK(B50), "", IF(O50 > 600000, "Mega Cap", IF(O50 > 30000, "Large Cap", IF(O50 > 7500, "Mid Cap", "Small Cap")))) -> Large Cap | G50: =IFERROR(__xludf.DUMMYFUNCTION("if(ISBLANK(B50),"""",GOOGLEFINANCE(B50,""price""))"),4070.0) -> 4070 | H50: =if(ISBLANK(B50),"",if(ISBLANK(M50),"",if(M50=0,"Extra",if(G50<M50,"Buy","Hold")))) -> Hold | I50: =IFERROR(__xludf.DUMMYFUNCTION("if(ISBLANK(B50),"""",GOOGLEFINANCE(B50,""CHANGEPCT"")/100)"),0.0013) -> 0.0013 | J50: =IFERROR(__xludf.DUMMYFUNCTION("if(ISBLANK(B50),"""",GOOGLEFINANCE(B50,""HIGH52""))"),4949.5) -> 4949.5 | K50: =IFERROR(__xludf.DUMMYFUNCTION("if(ISBLANK(B50),"""",GOOGLEFINANCE(B50,""LOW52""))"),3529.0) -> 3529 | L50: =if(isblank(B50),"",(G50-J50)/J50) -> -0.17769472 | M50: =J50-(J50*0.45) -> 2722.225 | N50: =IF(ISBLANK(B50), "", IF(AND(O50 >= 0, O50 <= 7500), "||||", IF(AND(O50 > 7500, O50 <= 30000), "|||", IF(AND(O50 > 30000, O50 <= 600000), "||", IF(O50 > 600000, "|", ""))))) -> || | O50: =IFERROR(__xludf.DUMMYFUNCTION("if(ISBLANK(B50),"""",googlefinance(B50,""Marketcap"")/10000000)"),264613.3948661) -> 264613.39
B51: NSE:FCL | C51: =IFERROR(__xludf.DUMMYFUNCTION("if(ISBLANK(B51),"""",GOOGLEFINANCE(B51,""NAME""))"),"Fineotex Chemical Ltd") -> Fineotex Chemical Ltd | D51: =if(ISBLANK(B51),"",if(L51<-10%,"B","H")) -> B | E51: =if(ISBLANK(B51),"",if(L51<-15%,"B","H")) -> B | F51: =IF(ISBLANK(B51), "", IF(O51 > 600000, "Mega Cap", IF(O51 > 30000, "Large Cap", IF(O51 > 7500, "Mid Cap", "Small Cap")))) -> Small Cap | G51: =IFERROR(__xludf.DUMMYFUNCTION("if(ISBLANK(B51),"""",GOOGLEFINANCE(B51,""price""))"),37.19) -> 37.19 | H51: =if(ISBLANK(B51),"",if(ISBLANK(M51),"",if(M51=0,"Extra",if(G51<M51,"Buy","Hold")))) -> Hold | I51: =IFERROR(__xludf.DUMMYFUNCTION("if(ISBLANK(B51),"""",GOOGLEFINANCE(B51,""CHANGEPCT"")/100)"),-0.0059) -> -0.0059 | J51: =IFERROR(__xludf.DUMMYFUNCTION("if(ISBLANK(B51),"""",GOOGLEFINANCE(B51,""HIGH52""))"),47.18) -> 47.18 | K51: =IFERROR(__xludf.DUMMYFUNCTION("if(ISBLANK(B51),"""",GOOGLEFINANCE(B51,""LOW52""))"),19.1) -> 19.1 | L51: =if(isblank(B51),"",(G51-J51)/J51) -> -0.21174226 | M51: =J51-(J51*0.55) -> 21.231 | N51: =IF(ISBLANK(B51), "", IF(AND(O51 >= 0, O51 <= 7500), "||||", IF(AND(O51 > 7500, O51 <= 30000), "|||", IF(AND(O51 > 30000, O51 <= 600000), "||", IF(O51 > 600000, "|", ""))))) -> |||| | O51: =IFERROR(__xludf.DUMMYFUNCTION("if(ISBLANK(B51),"""",googlefinance(B51,""Marketcap"")/10000000)"),4330.77534) -> 4330.7753
B52: NSE:FEDERALBNK | C52: =IFERROR(__xludf.DUMMYFUNCTION("if(ISBLANK(B52),"""",GOOGLEFINANCE(B52,""NAME""))"),"Federal Bank Ltd") -> Federal Bank Ltd | D52: =if(ISBLANK(B52),"",if(L52<-10%,"B","H")) -> H | E52: =if(ISBLANK(B52),"",if(L52<-15%,"B","H")) -> H | F52: =IF(ISBLANK(B52), "", IF(O52 > 600000, "Mega Cap", IF(O52 > 30000, "Large Cap", IF(O52 > 7500, "Mid Cap", "Small Cap")))) -> Large Cap | G52: =IFERROR(__xludf.DUMMYFUNCTION("if(ISBLANK(B52),"""",GOOGLEFINANCE(B52,""price""))"),331.2) -> 331.2 | H52: =if(ISBLANK(B52),"",if(ISBLANK(M52),"",if(M52=0,"Extra",if(G52<M52,"Buy","Hold")))) -> Hold | I52: =IFERROR(__xludf.DUMMYFUNCTION("if(ISBLANK(B52),"""",GOOGLEFINANCE(B52,""CHANGEPCT"")/100)"),0.0027) -> 0.0027 | J52: =IFERROR(__xludf.DUMMYFUNCTION("if(ISBLANK(B52),"""",GOOGLEFINANCE(B52,""HIGH52""))"),334.3) -> 334.3 | K52: =IFERROR(__xludf.DUMMYFUNCTION("if(ISBLANK(B52),"""",GOOGLEFINANCE(B52,""LOW52""))"),185.11) -> 185.11 | L52: =if(isblank(B52),"",(G52-J52)/J52) -> -0.009273108 | M52: =J52-(J52*0.25) -> 250.725 | N52: =IF(ISBLANK(B52), "", IF(AND(O52 >= 0, O52 <= 7500), "||||", IF(AND(O52 > 7500, O52 <= 30000), "|||", IF(AND(O52 > 30000, O52 <= 600000), "||", IF(O52 > 600000, "|", ""))))) -> || | O52: =IFERROR(__xludf.DUMMYFUNCTION("if(ISBLANK(B52),"""",googlefinance(B52,""Marketcap"")/10000000)"),81475.6907902) -> 81475.691
B53: NSE:FINEORG | C53: =IFERROR(__xludf.DUMMYFUNCTION("if(ISBLANK(B53),"""",GOOGLEFINANCE(B53,""NAME""))"),"Fine Organic Industries Ltd") -> Fine Organic Industries Ltd | D53: =if(ISBLANK(B53),"",if(L53<-10%,"B","H")) -> H | E53: =if(ISBLANK(B53),"",if(L53<-15%,"B","H")) -> H | F53: =IF(ISBLANK(B53), "", IF(O53 > 600000, "Mega Cap", IF(O53 > 30000, "Large Cap", IF(O53 > 7500, "Mid Cap", "Small Cap")))) -> Mid Cap | G53: =IFERROR(__xludf.DUMMYFUNCTION("if(ISBLANK(B53),"""",GOOGLEFINANCE(B53,""price""))"),4999.0) -> 4999 | H53: =if(ISBLANK(B53),"",if(ISBLANK(M53),"",if(M53=0,"Extra",if(G53<M53,"Buy","Hold")))) -> Hold | I53: =IFERROR(__xludf.DUMMYFUNCTION("if(ISBLANK(B53),"""",GOOGLEFINANCE(B53,""CHANGEPCT"")/100)"),-0.027000000000000003) -> -0.027 | J53: =IFERROR(__xludf.DUMMYFUNCTION("if(ISBLANK(B53),"""",GOOGLEFINANCE(B53,""HIGH52""))"),5494.0) -> 5494 | K53: =IFERROR(__xludf.DUMMYFUNCTION("if(ISBLANK(B53),"""",GOOGLEFINANCE(B53,""LOW52""))"),3856.0) -> 3856 | L53: =if(isblank(B53),"",(G53-J53)/J53) -> -0.090098289 | M53: =J53-(J53*0.45) -> 3021.7 | N53: =IF(ISBLANK(B53), "", IF(AND(O53 >= 0, O53 <= 7500), "||||", IF(AND(O53 > 7500, O53 <= 30000), "|||", IF(AND(O53 > 30000, O53 <= 600000), "||", IF(O53 > 600000, "|", ""))))) -> ||| | O53: =IFERROR(__xludf.DUMMYFUNCTION("if(ISBLANK(B53),"""",googlefinance(B53,""Marketcap"")/10000000)"),15346.0574365) -> 15346.057
B54: NSE:GREENPANEL | C54: =IFERROR(__xludf.DUMMYFUNCTION("if(ISBLANK(B54),"""",GOOGLEFINANCE(B54,""NAME""))"),"Greenpanel Industries Ltd") -> Greenpanel Industries Ltd | D54: =if(ISBLANK(B54),"",if(L54<-10%,"B","H")) -> B | E54: =if(ISBLANK(B54),"",if(L54<-15%,"B","H")) -> B | F54: =IF(ISBLANK(B54), "", IF(O54 > 600000, "Mega Cap", IF(O54 > 30000, "Large Cap", IF(O54 > 7500, "Mid Cap", "Small Cap")))) -> Small Cap | G54: =IFERROR(__xludf.DUMMYFUNCTION("if(ISBLANK(B54),"""",GOOGLEFINANCE(B54,""price""))"),196.37) -> 196.37 | H54: =if(ISBLANK(B54),"",if(ISBLANK(M54),"",if(M54=0,"Extra",if(G54<M54,"Buy","Hold")))) -> Hold | I54: =IFERROR(__xludf.DUMMYFUNCTION("if(ISBLANK(B54),"""",GOOGLEFINANCE(B54,""CHANGEPCT"")/100)"),0.0405) -> 0.0405 | J54: =IFERROR(__xludf.DUMMYFUNCTION("if(ISBLANK(B54),"""",GOOGLEFINANCE(B54,""HIGH52""))"),335.2) -> 335.2 | K54: =IFERROR(__xludf.DUMMYFUNCTION("if(ISBLANK(B54),"""",GOOGLEFINANCE(B54,""LOW52""))"),163.01) -> 163.01 | L54: =if(isblank(B54),"",(G54-J54)/J54) -> -0.41417064 | M54: =J54-(J54*0.55) -> 150.84 | N54: =IF(ISBLANK(B54), "", IF(AND(O54 >= 0, O54 <= 7500), "||||", IF(AND(O54 > 7500, O54 <= 30000), "|||", IF(AND(O54 > 30000, O54 <= 600000), "||", IF(O54 > 600000, "|", ""))))) -> |||| | O54: =IFERROR(__xludf.DUMMYFUNCTION("if(ISBLANK(B54),"""",googlefinance(B54,""Marketcap"")/10000000)"),2399.2711934) -> 2399.2712
B55: NSE:GVKPIL | C55: =IFERROR(__xludf.DUMMYFUNCTION("if(ISBLANK(B55),"""",GOOGLEFINANCE(B55,""NAME""))"),"GVK Power & Infrastructure Ltd") -> GVK Power & Infrastructure Ltd | D55: =if(ISBLANK(B55),"",if(L55<-10%,"B","H")) -> B | E55: =if(ISBLANK(B55),"",if(L55<-15%,"B","H")) -> B | F55: =IF(ISBLANK(B55), "", IF(O55 > 600000, "Mega Cap", IF(O55 > 30000, "Large Cap", IF(O55 > 7500, "Mid Cap", "Small Cap")))) -> Small Cap | G55: =IFERROR(__xludf.DUMMYFUNCTION("if(ISBLANK(B55),"""",GOOGLEFINANCE(B55,""price""))"),2.61) -> 2.61 | H55: =if(ISBLANK(B55),"",if(ISBLANK(M55),"",if(M55=0,"Extra",if(G55<M55,"Buy","Hold")))) -> Hold | I55: =IFERROR(__xludf.DUMMYFUNCTION("if(ISBLANK(B55),"""",GOOGLEFINANCE(B55,""CHANGEPCT"")/100)"),-0.011399999999999999) -> -0.0114 | J55: =IFERROR(__xludf.DUMMYFUNCTION("if(ISBLANK(B55),"""",GOOGLEFINANCE(B55,""HIGH52""))"),4.24) -> 4.24 | K55: =IFERROR(__xludf.DUMMYFUNCTION("if(ISBLANK(B55),"""",GOOGLEFINANCE(B55,""LOW52""))"),2.37) -> 2.37 | L55: =if(isblank(B55),"",(G55-J55)/J55) -> -0.38443396 | M55: =J55-(J55*0.8) -> 0.848 | N55: =IF(ISBLANK(B55), "", IF(AND(O55 >= 0, O55 <= 7500), "||||", IF(AND(O55 > 7500, O55 <= 30000), "|||", IF(AND(O55 > 30000, O55 <= 600000), "||", IF(O55 > 600000, "|", ""))))) -> |||| | O55: =IFERROR(__xludf.DUMMYFUNCTION("if(ISBLANK(B55),"""",googlefinance(B55,""Marketcap"")/10000000)"),412.2669829) -> 412.26698
B56: NSE:HAPPSTMNDS | C56: =IFERROR(__xludf.DUMMYFUNCTION("if(ISBLANK(B56),"""",GOOGLEFINANCE(B56,""NAME""))"),"Happiest Minds Technologies Ltd") -> Happiest Minds Technologies Ltd | D56: =if(ISBLANK(B56),"",if(L56<-10%,"B","H")) -> B | E56: =if(ISBLANK(B56),"",if(L56<-15%,"B","H")) -> B | F56: =IF(ISBLANK(B56), "", IF(O56 > 600000, "Mega Cap", IF(O56 > 30000, "Large Cap", IF(O56 > 7500, "Mid Cap", "Small Cap")))) -> Small Cap | G56: =IFERROR(__xludf.DUMMYFUNCTION("if(ISBLANK(B56),"""",GOOGLEFINANCE(B56,""price""))"),349.5) -> 349.5 | H56: =if(ISBLANK(B56),"",if(ISBLANK(M56),"",if(M56=0,"Extra",if(G56<M56,"Buy","Hold")))) -> Buy | I56: =IFERROR(__xludf.DUMMYFUNCTION("if(ISBLANK(B56),"""",GOOGLEFINANCE(B56,""CHANGEPCT"")/100)"),0.0062) -> 0.0062 | J56: =IFERROR(__xludf.DUMMYFUNCTION("if(ISBLANK(B56),"""",GOOGLEFINANCE(B56,""HIGH52""))"),651.9) -> 651.9 | K56: =IFERROR(__xludf.DUMMYFUNCTION("if(ISBLANK(B56),"""",GOOGLEFINANCE(B56,""LOW52""))"),330.2) -> 330.2 | L56: =if(isblank(B56),"",(G56-J56)/J56) -> -0.46387483 | M56: =J56-(J56*0.45) -> 358.545 | N56: =IF(ISBLANK(B56), "", IF(AND(O56 >= 0, O56 <= 7500), "||||", IF(AND(O56 > 7500, O56 <= 30000), "|||", IF(AND(O56 > 30000, O56 <= 600000), "||", IF(O56 > 600000, "|", ""))))) -> |||| | O56: =IFERROR(__xludf.DUMMYFUNCTION("if(ISBLANK(B56),"""",googlefinance(B56,""Marketcap"")/10000000)"),5251.653405) -> 5251.6534
B57: NSE:HCLTECH | C57: =IFERROR(__xludf.DUMMYFUNCTION("if(ISBLANK(B57),"""",GOOGLEFINANCE(B57,""NAME""))"),"HCL Technologies Ltd") -> HCL Technologies Ltd | D57: =if(ISBLANK(B57),"",if(L57<-10%,"B","H")) -> B | E57: =if(ISBLANK(B57),"",if(L57<-15%,"B","H")) -> B | F57: =IF(ISBLANK(B57), "", IF(O57 > 600000, "Mega Cap", IF(O57 > 30000, "Large Cap", IF(O57 > 7500, "Mid Cap", "Small Cap")))) -> Large Cap | G57: =IFERROR(__xludf.DUMMYFUNCTION("if(ISBLANK(B57),"""",GOOGLEFINANCE(B57,""price""))"),1170.0) -> 1170 | H57: =if(ISBLANK(B57),"",if(ISBLANK(M57),"",if(M57=0,"Extra",if(G57<M57,"Buy","Hold")))) -> Hold | I57: =IFERROR(__xludf.DUMMYFUNCTION("if(ISBLANK(B57),"""",GOOGLEFINANCE(B57,""CHANGEPCT"")/100)"),0.0316) -> 0.0316 | J57: =IFERROR(__xludf.DUMMYFUNCTION("if(ISBLANK(B57),"""",GOOGLEFINANCE(B57,""HIGH52""))"),1780.1) -> 1780.1 | K57: =IFERROR(__xludf.DUMMYFUNCTION("if(ISBLANK(B57),"""",GOOGLEFINANCE(B57,""LOW52""))"),1030.0) -> 1030 | L57: =if(isblank(B57),"",(G57-J57)/J57) -> -0.34273355 | M57: =J57-(J57*0.4) -> 1068.06 | N57: =IF(ISBLANK(B57), "", IF(AND(O57 >= 0, O57 <= 7500), "||||", IF(AND(O57 > 7500, O57 <= 30000), "|||", IF(AND(O57 > 30000, O57 <= 600000), "||", IF(O57 > 600000, "|", ""))))) -> || | O57: =IFERROR(__xludf.DUMMYFUNCTION("if(ISBLANK(B57),"""",googlefinance(B57,""Marketcap"")/10000000)"),316574.622) -> 316574.62
B58: NSE:HDFCAMC | C58: =IFERROR(__xludf.DUMMYFUNCTION("if(ISBLANK(B58),"""",GOOGLEFINANCE(B58,""NAME""))"),"HDFC Asset Management Company Ltd") -> HDFC Asset Management Company Ltd | D58: =if(ISBLANK(B58),"",if(L58<-10%,"B","H")) -> H | E58: =if(ISBLANK(B58),"",if(L58<-15%,"B","H")) -> H | F58: =IF(ISBLANK(B58), "", IF(O58 > 600000, "Mega Cap", IF(O58 > 30000, "Large Cap", IF(O58 > 7500, "Mid Cap", "Small Cap")))) -> Large Cap | G58: =IFERROR(__xludf.DUMMYFUNCTION("if(ISBLANK(B58),"""",GOOGLEFINANCE(B58,""price""))"),2784.0) -> 2784 | H58: =if(ISBLANK(B58),"",if(ISBLANK(M58),"",if(M58=0,"Extra",if(G58<M58,"Buy","Hold")))) -> Hold | I58: =IFERROR(__xludf.DUMMYFUNCTION("if(ISBLANK(B58),"""",GOOGLEFINANCE(B58,""CHANGEPCT"")/100)"),0.0038) -> 0.0038 | J58: =IFERROR(__xludf.DUMMYFUNCTION("if(ISBLANK(B58),"""",GOOGLEFINANCE(B58,""HIGH52""))"),2967.25) -> 2967.25 | K58: =IFERROR(__xludf.DUMMYFUNCTION("if(ISBLANK(B58),"""",GOOGLEFINANCE(B58,""LOW52""))"),2205.6) -> 2205.6 | L58: =if(isblank(B58),"",(G58-J58)/J58) -> -0.06175752 | M58: =J58-(J58*0.35) -> 1928.7125 | N58: =IF(ISBLANK(B58), "", IF(AND(O58 >= 0, O58 <= 7500), "||||", IF(AND(O58 > 7500, O58 <= 30000), "|||", IF(AND(O58 > 30000, O58 <= 600000), "||", IF(O58 > 600000, "|", ""))))) -> || | O58: =IFERROR(__xludf.DUMMYFUNCTION("if(ISBLANK(B58),"""",googlefinance(B58,""Marketcap"")/10000000)"),119337.07872) -> 119337.08
B59: NSE:HDFCBANK | C59: =IFERROR(__xludf.DUMMYFUNCTION("if(ISBLANK(B59),"""",GOOGLEFINANCE(B59,""NAME""))"),"HDFC Bank Ltd") -> HDFC Bank Ltd | D59: =if(ISBLANK(B59),"",if(L59<-10%,"B","H")) -> B | E59: =if(ISBLANK(B59),"",if(L59<-15%,"B","H")) -> B | F59: =IF(ISBLANK(B59), "", IF(O59 > 600000, "Mega Cap", IF(O59 > 30000, "Large Cap", IF(O59 > 7500, "Mid Cap", "Small Cap")))) -> Mid Cap | G59: =IFERROR(__xludf.DUMMYFUNCTION("if(ISBLANK(B59),"""",GOOGLEFINANCE(B59,""price""))"),827.5) -> 827.5 | H59: =if(ISBLANK(B59),"",if(ISBLANK(M59),"",if(M59=0,"Extra",if(G59<M59,"Buy","Hold")))) -> Hold | I59: =IFERROR(__xludf.DUMMYFUNCTION("if(ISBLANK(B59),"""",GOOGLEFINANCE(B59,""CHANGEPCT"")/100)"),-0.0028000000000000004) -> -0.0028 | J59: =IFERROR(__xludf.DUMMYFUNCTION("if(ISBLANK(B59),"""",GOOGLEFINANCE(B59,""HIGH52""))"),1020.5) -> 1020.5 | K59: =IFERROR(__xludf.DUMMYFUNCTION("if(ISBLANK(B59),"""",GOOGLEFINANCE(B59,""LOW52""))"),726.65) -> 726.65 | L59: =if(isblank(B59),"",(G59-J59)/J59) -> -0.18912298 | M59: =J59-(J59*0.2) -> 816.4 | N59: =IF(ISBLANK(B59), "", IF(AND(O59 >= 0, O59 <= 7500), "||||", IF(AND(O59 > 7500, O59 <= 30000), "|||", IF(AND(O59 > 30000, O59 <= 600000), "||", IF(O59 > 600000, "|", ""))))) -> ||| | O59: =IFERROR(__xludf.DUMMYFUNCTION("if(ISBLANK(B59),"""",googlefinance(B59,""Marketcap"")/10000000)"),13727.1521463) -> 13727.152
B60: NSE:HDFCLIFE | C60: =IFERROR(__xludf.DUMMYFUNCTION("if(ISBLANK(B60),"""",GOOGLEFINANCE(B60,""NAME""))"),"HDFC Life Insurance Company Ltd") -> HDFC Life Insurance Company Ltd | D60: =if(ISBLANK(B60),"",if(L60<-10%,"B","H")) -> B | E60: =if(ISBLANK(B60),"",if(L60<-15%,"B","H")) -> B | F60: =IF(ISBLANK(B60), "", IF(O60 > 600000, "Mega Cap", IF(O60 > 30000, "Large Cap", IF(O60 > 7500, "Mid Cap", "Small Cap")))) -> Large Cap | G60: =IFERROR(__xludf.DUMMYFUNCTION("if(ISBLANK(B60),"""",GOOGLEFINANCE(B60,""price""))"),572.75) -> 572.75 | H60: =if(ISBLANK(B60),"",if(ISBLANK(M60),"",if(M60=0,"Extra",if(G60<M60,"Buy","Hold")))) -> Buy | I60: =IFERROR(__xludf.DUMMYFUNCTION("if(ISBLANK(B60),"""",GOOGLEFINANCE(B60,""CHANGEPCT"")/100)"),0.0152) -> 0.0152 | J60: =IFERROR(__xludf.DUMMYFUNCTION("if(ISBLANK(B60),"""",GOOGLEFINANCE(B60,""HIGH52""))"),815.0) -> 815 | K60: =IFERROR(__xludf.DUMMYFUNCTION("if(ISBLANK(B60),"""",GOOGLEFINANCE(B60,""LOW52""))"),543.0) -> 543 | L60: =if(isblank(B60),"",(G60-J60)/J60) -> -0.29723926 | M60: =J60-(J60*0.25) -> 611.25 | N60: =IF(ISBLANK(B60), "", IF(AND(O60 >= 0, O60 <= 7500), "||||", IF(AND(O60 > 7500, O60 <= 30000), "|||", IF(AND(O60 > 30000, O60 <= 600000), "||", IF(O60 > 600000, "|", ""))))) -> || | O60: =IFERROR(__xludf.DUMMYFUNCTION("if(ISBLANK(B60),"""",googlefinance(B60,""Marketcap"")/10000000)"),124397.577125) -> 124397.58
B61: NSE:HINDUNILVR | C61: =IFERROR(__xludf.DUMMYFUNCTION("if(ISBLANK(B61),"""",GOOGLEFINANCE(B61,""NAME""))"),"Hindustan Unilever Ltd") -> Hindustan Unilever Ltd | D61: =if(ISBLANK(B61),"",if(L61<-10%,"B","H")) -> B | E61: =if(ISBLANK(B61),"",if(L61<-15%,"B","H")) -> B | F61: =IF(ISBLANK(B61), "", IF(O61 > 600000, "Mega Cap", IF(O61 > 30000, "Large Cap", IF(O61 > 7500, "Mid Cap", "Small Cap")))) -> Large Cap | G61: =IFERROR(__xludf.DUMMYFUNCTION("if(ISBLANK(B61),"""",GOOGLEFINANCE(B61,""price""))"),2203.1) -> 2203.1 | H61: =if(ISBLANK(B61),"",if(ISBLANK(M61),"",if(M61=0,"Extra",if(G61<M61,"Buy","Hold")))) -> Hold | I61: =IFERROR(__xludf.DUMMYFUNCTION("if(ISBLANK(B61),"""",GOOGLEFINANCE(B61,""CHANGEPCT"")/100)"),5.0E-4) -> 0.0005 | J61: =IFERROR(__xludf.DUMMYFUNCTION("if(ISBLANK(B61),"""",GOOGLEFINANCE(B61,""HIGH52""))"),2715.44) -> 2715.44 | K61: =IFERROR(__xludf.DUMMYFUNCTION("if(ISBLANK(B61),"""",GOOGLEFINANCE(B61,""LOW52""))"),2022.5) -> 2022.5 | L61: =if(isblank(B61),"",(G61-J61)/J61) -> -0.1886766 | M61: =J61-(J61*0.35) -> 1765.036 | N61: =IF(ISBLANK(B61), "", IF(AND(O61 >= 0, O61 <= 7500), "||||", IF(AND(O61 > 7500, O61 <= 30000), "|||", IF(AND(O61 > 30000, O61 <= 600000), "||", IF(O61 > 600000, "|", ""))))) -> || | O61: =IFERROR(__xludf.DUMMYFUNCTION("if(ISBLANK(B61),"""",googlefinance(B61,""Marketcap"")/10000000)"),519039.3151724) -> 519039.32
B62: NSE:HLEGLAS | C62: =IFERROR(__xludf.DUMMYFUNCTION("if(ISBLANK(B62),"""",GOOGLEFINANCE(B62,""NAME""))"),"HLE Glascoat Ltd") -> HLE Glascoat Ltd | D62: =if(ISBLANK(B62),"",if(L62<-10%,"B","H")) -> B | E62: =if(ISBLANK(B62),"",if(L62<-15%,"B","H")) -> B | F62: =IF(ISBLANK(B62), "", IF(O62 > 600000, "Mega Cap", IF(O62 > 30000, "Large Cap", IF(O62 > 7500, "Mid Cap", "Small Cap")))) -> Small Cap | G62: =IFERROR(__xludf.DUMMYFUNCTION("if(ISBLANK(B62),"""",GOOGLEFINANCE(B62,""price""))"),404.0) -> 404 | H62: =if(ISBLANK(B62),"",if(ISBLANK(M62),"",if(M62=0,"Extra",if(G62<M62,"Buy","Hold")))) -> Hold | I62: =IFERROR(__xludf.DUMMYFUNCTION("if(ISBLANK(B62),"""",GOOGLEFINANCE(B62,""CHANGEPCT"")/100)"),0.042800000000000005) -> 0.0428 | J62: =IFERROR(__xludf.DUMMYFUNCTION("if(ISBLANK(B62),"""",GOOGLEFINANCE(B62,""HIGH52""))"),661.95) -> 661.95 | K62: =IFERROR(__xludf.DUMMYFUNCTION("if(ISBLANK(B62),"""",GOOGLEFINANCE(B62,""LOW52""))"),250.0) -> 250 | L62: =if(isblank(B62),"",(G62-J62)/J62) -> -0.389682 | M62: =J62-(J62*0.65) -> 231.6825 | N62: =IF(ISBLANK(B62), "", IF(AND(O62 >= 0, O62 <= 7500), "||||", IF(AND(O62 > 7500, O62 <= 30000), "|||", IF(AND(O62 > 30000, O62 <= 600000), "||", IF(O62 > 600000, "|", ""))))) -> |||| | O62: =IFERROR(__xludf.DUMMYFUNCTION("if(ISBLANK(B62),"""",googlefinance(B62,""Marketcap"")/10000000)"),2805.971496) -> 2805.9715
B63: NSE:HNDFDS | C63: =IFERROR(__xludf.DUMMYFUNCTION("if(ISBLANK(B63),"""",GOOGLEFINANCE(B63,""NAME""))"),"Hindustan Foods Ltd(NDA)") -> Hindustan Foods Ltd(NDA) | D63: =if(ISBLANK(B63),"",if(L63<-10%,"B","H")) -> H | E63: =if(ISBLANK(B63),"",if(L63<-15%,"B","H")) -> H | F63: =IF(ISBLANK(B63), "", IF(O63 > 600000, "Mega Cap", IF(O63 > 30000, "Large Cap", IF(O63 > 7500, "Mid Cap", "Small Cap")))) -> Small Cap | G63: =IFERROR(__xludf.DUMMYFUNCTION("if(ISBLANK(B63),"""",GOOGLEFINANCE(B63,""price""))"),540.0) -> 540 | H63: =if(ISBLANK(B63),"",if(ISBLANK(M63),"",if(M63=0,"Extra",if(G63<M63,"Buy","Hold")))) -> Hold | I63: =IFERROR(__xludf.DUMMYFUNCTION("if(ISBLANK(B63),"""",GOOGLEFINANCE(B63,""CHANGEPCT"")/100)"),-0.0029) -> -0.0029 | J63: =IFERROR(__xludf.DUMMYFUNCTION("if(ISBLANK(B63),"""",GOOGLEFINANCE(B63,""HIGH52""))"),584.9) -> 584.9 | K63: =IFERROR(__xludf.DUMMYFUNCTION("if(ISBLANK(B63),"""",GOOGLEFINANCE(B63,""LOW52""))"),442.0) -> 442 | L63: =if(isblank(B63),"",(G63-J63)/J63) -> -0.076765259 | M63: =J63-(J63*0.3) -> 409.43 | N63: =IF(ISBLANK(B63), "", IF(AND(O63 >= 0, O63 <= 7500), "||||", IF(AND(O63 > 7500, O63 <= 30000), "|||", IF(AND(O63 > 30000, O63 <= 600000), "||", IF(O63 > 600000, "|", ""))))) -> |||| | O63: =IFERROR(__xludf.DUMMYFUNCTION("if(ISBLANK(B63),"""",googlefinance(B63,""Marketcap"")/10000000)"),6542.7804) -> 6542.7804
B64: NSE:ICICIBANK | C64: =IFERROR(__xludf.DUMMYFUNCTION("if(ISBLANK(B64),"""",GOOGLEFINANCE(B64,""NAME""))"),"ICICI Bank Ltd") -> ICICI Bank Ltd | D64: =if(ISBLANK(B64),"",if(L64<-10%,"B","H")) -> H | E64: =if(ISBLANK(B64),"",if(L64<-15%,"B","H")) -> H | F64: =IF(ISBLANK(B64), "", IF(O64 > 600000, "Mega Cap", IF(O64 > 30000, "Large Cap", IF(O64 > 7500, "Mid Cap", "Small Cap")))) -> Mid Cap | G64: =IFERROR(__xludf.DUMMYFUNCTION("if(ISBLANK(B64),"""",GOOGLEFINANCE(B64,""price""))"),1412.0) -> 1412 | H64: =if(ISBLANK(B64),"",if(ISBLANK(M64),"",if(M64=0,"Extra",if(G64<M64,"Buy","Hold")))) -> Hold | I64: =IFERROR(__xludf.DUMMYFUNCTION("if(ISBLANK(B64),"""",GOOGLEFINANCE(B64,""CHANGEPCT"")/100)"),-0.0104) -> -0.0104 | J64: =IFERROR(__xludf.DUMMYFUNCTION("if(ISBLANK(B64),"""",GOOGLEFINANCE(B64,""HIGH52""))"),1500.0) -> 1500 | K64: =IFERROR(__xludf.DUMMYFUNCTION("if(ISBLANK(B64),"""",GOOGLEFINANCE(B64,""LOW52""))"),1187.6) -> 1187.6 | L64: =if(isblank(B64),"",(G64-J64)/J64) -> -0.058666667 | M64: =J64-(J64*0.2) -> 1200 | N64: =IF(ISBLANK(B64), "", IF(AND(O64 >= 0, O64 <= 7500), "||||", IF(AND(O64 > 7500, O64 <= 30000), "|||", IF(AND(O64 > 30000, O64 <= 600000), "||", IF(O64 > 600000, "|", ""))))) -> ||| | O64: =IFERROR(__xludf.DUMMYFUNCTION("if(ISBLANK(B64),"""",googlefinance(B64,""Marketcap"")/10000000)"),10778.4593179) -> 10778.459
B65: NSE:IEX | C65: =IFERROR(__xludf.DUMMYFUNCTION("if(ISBLANK(B65),"""",GOOGLEFINANCE(B65,""NAME""))"),"Indian Energy Exchange Ltd") -> Indian Energy Exchange Ltd | D65: =if(ISBLANK(B65),"",if(L65<-10%,"B","H")) -> B | E65: =if(ISBLANK(B65),"",if(L65<-15%,"B","H")) -> B | F65: =IF(ISBLANK(B65), "", IF(O65 > 600000, "Mega Cap", IF(O65 > 30000, "Large Cap", IF(O65 > 7500, "Mid Cap", "Small Cap")))) -> Mid Cap | G65: =IFERROR(__xludf.DUMMYFUNCTION("if(ISBLANK(B65),"""",GOOGLEFINANCE(B65,""price""))"),122.44) -> 122.44 | H65: =if(ISBLANK(B65),"",if(ISBLANK(M65),"",if(M65=0,"Extra",if(G65<M65,"Buy","Hold")))) -> Extra | I65: =IFERROR(__xludf.DUMMYFUNCTION("if(ISBLANK(B65),"""",GOOGLEFINANCE(B65,""CHANGEPCT"")/100)"),-0.0101) -> -0.0101 | J65: =IFERROR(__xludf.DUMMYFUNCTION("if(ISBLANK(B65),"""",GOOGLEFINANCE(B65,""HIGH52""))"),211.75) -> 211.75 | K65: =IFERROR(__xludf.DUMMYFUNCTION("if(ISBLANK(B65),"""",GOOGLEFINANCE(B65,""LOW52""))"),114.6) -> 114.6 | L65: =if(isblank(B65),"",(G65-J65)/J65) -> -0.42177096 | M65: 0 | N65: =IF(ISBLANK(B65), "", IF(AND(O65 >= 0, O65 <= 7500), "||||", IF(AND(O65 > 7500, O65 <= 30000), "|||", IF(AND(O65 > 30000, O65 <= 600000), "||", IF(O65 > 600000, "|", ""))))) -> ||| | O65: =IFERROR(__xludf.DUMMYFUNCTION("if(ISBLANK(B65),"""",googlefinance(B65,""Marketcap"")/10000000)"),10891.223141) -> 10891.223
B66: NSE:INFY | C66: =IFERROR(__xludf.DUMMYFUNCTION("if(ISBLANK(B66),"""",GOOGLEFINANCE(B66,""NAME""))"),"Infosys Ltd") -> Infosys Ltd | D66: =if(ISBLANK(B66),"",if(L66<-10%,"B","H")) -> B | E66: =if(ISBLANK(B66),"",if(L66<-15%,"B","H")) -> B | F66: =IF(ISBLANK(B66), "", IF(O66 > 600000, "Mega Cap", IF(O66 > 30000, "Large Cap", IF(O66 > 7500, "Mid Cap", "Small Cap")))) -> Small Cap | G66: =IFERROR(__xludf.DUMMYFUNCTION("if(ISBLANK(B66),"""",GOOGLEFINANCE(B66,""price""))"),1071.9) -> 1071.9 | H66: =if(ISBLANK(B66),"",if(ISBLANK(M66),"",if(M66=0,"Extra",if(G66<M66,"Buy","Hold")))) -> Hold | I66: =IFERROR(__xludf.DUMMYFUNCTION("if(ISBLANK(B66),"""",GOOGLEFINANCE(B66,""CHANGEPCT"")/100)"),0.0285) -> 0.0285 | J66: =IFERROR(__xludf.DUMMYFUNCTION("if(ISBLANK(B66),"""",GOOGLEFINANCE(B66,""HIGH52""))"),1728.0) -> 1728 | K66: =IFERROR(__xludf.DUMMYFUNCTION("if(ISBLANK(B66),"""",GOOGLEFINANCE(B66,""LOW52""))"),982.4) -> 982.4 | L66: =if(isblank(B66),"",(G66-J66)/J66) -> -0.3796875 | M66: =J66-(J66*0.4) -> 1036.8 | N66: =IF(ISBLANK(B66), "", IF(AND(O66 >= 0, O66 <= 7500), "||||", IF(AND(O66 > 7500, O66 <= 30000), "|||", IF(AND(O66 > 30000, O66 <= 600000), "||", IF(O66 > 600000, "|", ""))))) -> |||| | O66: =IFERROR(__xludf.DUMMYFUNCTION("if(ISBLANK(B66),"""",googlefinance(B66,""Marketcap"")/10000000)"),4537.1518373) -> 4537.1518
B67: NSE:IPL | C67: =IFERROR(__xludf.DUMMYFUNCTION("if(ISBLANK(B67),"""",GOOGLEFINANCE(B67,""NAME""))"),"India Pesticides Ltd") -> India Pesticides Ltd | D67: =if(ISBLANK(B67),"",if(L67<-10%,"B","H")) -> B | E67: =if(ISBLANK(B67),"",if(L67<-15%,"B","H")) -> B | F67: =IF(ISBLANK(B67), "", IF(O67 > 600000, "Mega Cap", IF(O67 > 30000, "Large Cap", IF(O67 > 7500, "Mid Cap", "Small Cap")))) -> Small Cap | G67: =IFERROR(__xludf.DUMMYFUNCTION("if(ISBLANK(B67),"""",GOOGLEFINANCE(B67,""price""))"),158.5) -> 158.5 | H67: =if(ISBLANK(B67),"",if(ISBLANK(M67),"",if(M67=0,"Extra",if(G67<M67,"Buy","Hold")))) -> Hold | I67: =IFERROR(__xludf.DUMMYFUNCTION("if(ISBLANK(B67),"""",GOOGLEFINANCE(B67,""CHANGEPCT"")/100)"),-0.0199) -> -0.0199 | J67: =IFERROR(__xludf.DUMMYFUNCTION("if(ISBLANK(B67),"""",GOOGLEFINANCE(B67,""HIGH52""))"),245.84) -> 245.84 | K67: =IFERROR(__xludf.DUMMYFUNCTION("if(ISBLANK(B67),"""",GOOGLEFINANCE(B67,""LOW52""))"),125.0) -> 125 | L67: =if(isblank(B67),"",(G67-J67)/J67) -> -0.35527172 | M67: =J67-(J67*0.75) -> 61.46 | N67: =IF(ISBLANK(B67), "", IF(AND(O67 >= 0, O67 <= 7500), "||||", IF(AND(O67 > 7500, O67 <= 30000), "|||", IF(AND(O67 > 30000, O67 <= 600000), "||", IF(O67 > 600000, "|", ""))))) -> |||| | O67: =IFERROR(__xludf.DUMMYFUNCTION("if(ISBLANK(B67),"""",googlefinance(B67,""Marketcap"")/10000000)"),1837.5610542) -> 1837.5611
B68: NSE:IRCON | C68: =IFERROR(__xludf.DUMMYFUNCTION("if(ISBLANK(B68),"""",GOOGLEFINANCE(B68,""NAME""))"),"Ircon International Ltd") -> Ircon International Ltd | D68: =if(ISBLANK(B68),"",if(L68<-10%,"B","H")) -> B | E68: =if(ISBLANK(B68),"",if(L68<-15%,"B","H")) -> B | F68: =IF(ISBLANK(B68), "", IF(O68 > 600000, "Mega Cap", IF(O68 > 30000, "Large Cap", IF(O68 > 7500, "Mid Cap", "Small Cap")))) -> Mid Cap | G68: =IFERROR(__xludf.DUMMYFUNCTION("if(ISBLANK(B68),"""",GOOGLEFINANCE(B68,""price""))"),133.03) -> 133.03 | H68: =if(ISBLANK(B68),"",if(ISBLANK(M68),"",if(M68=0,"Extra",if(G68<M68,"Buy","Hold")))) -> Hold | I68: =IFERROR(__xludf.DUMMYFUNCTION("if(ISBLANK(B68),"""",GOOGLEFINANCE(B68,""CHANGEPCT"")/100)"),-0.0092) -> -0.0092 | J68: =IFERROR(__xludf.DUMMYFUNCTION("if(ISBLANK(B68),"""",GOOGLEFINANCE(B68,""HIGH52""))"),200.15) -> 200.15 | K68: =IFERROR(__xludf.DUMMYFUNCTION("if(ISBLANK(B68),"""",GOOGLEFINANCE(B68,""LOW52""))"),114.5) -> 114.5 | L68: =if(isblank(B68),"",(G68-J68)/J68) -> -0.33534849 | M68: =J68-(J68*0.65) -> 70.0525 | N68: =IF(ISBLANK(B68), "", IF(AND(O68 >= 0, O68 <= 7500), "||||", IF(AND(O68 > 7500, O68 <= 30000), "|||", IF(AND(O68 > 30000, O68 <= 600000), "||", IF(O68 > 600000, "|", ""))))) -> ||| | O68: =IFERROR(__xludf.DUMMYFUNCTION("if(ISBLANK(B68),"""",googlefinance(B68,""Marketcap"")/10000000)"),12524.4403813) -> 12524.44
B69: NSE:IRCTC | C69: =IFERROR(__xludf.DUMMYFUNCTION("if(ISBLANK(B69),"""",GOOGLEFINANCE(B69,""NAME""))"),"Indian Railway Ctrng nd Trsm Corp Ltd") -> Indian Railway Ctrng nd Trsm Corp Ltd | D69: =if(ISBLANK(B69),"",if(L69<-10%,"B","H")) -> B | E69: =if(ISBLANK(B69),"",if(L69<-15%,"B","H")) -> B | F69: =IF(ISBLANK(B69), "", IF(O69 > 600000, "Mega Cap", IF(O69 > 30000, "Large Cap", IF(O69 > 7500, "Mid Cap", "Small Cap")))) -> Large Cap | G69: =IFERROR(__xludf.DUMMYFUNCTION("if(ISBLANK(B69),"""",GOOGLEFINANCE(B69,""price""))"),501.65) -> 501.65 | H69: =if(ISBLANK(B69),"",if(ISBLANK(M69),"",if(M69=0,"Extra",if(G69<M69,"Buy","Hold")))) -> Hold | I69: =IFERROR(__xludf.DUMMYFUNCTION("if(ISBLANK(B69),"""",GOOGLEFINANCE(B69,""CHANGEPCT"")/100)"),-0.0143) -> -0.0143 | J69: =IFERROR(__xludf.DUMMYFUNCTION("if(ISBLANK(B69),"""",GOOGLEFINANCE(B69,""HIGH52""))"),798.6) -> 798.6 | K69: =IFERROR(__xludf.DUMMYFUNCTION("if(ISBLANK(B69),"""",GOOGLEFINANCE(B69,""LOW52""))"),492.65) -> 492.65 | L69: =if(isblank(B69),"",(G69-J69)/J69) -> -0.37183822 | M69: =J69-(J69*0.45) -> 439.23 | N69: =IF(ISBLANK(B69), "", IF(AND(O69 >= 0, O69 <= 7500), "||||", IF(AND(O69 > 7500, O69 <= 30000), "|||", IF(AND(O69 > 30000, O69 <= 600000), "||", IF(O69 > 600000, "|", ""))))) -> || | O69: =IFERROR(__xludf.DUMMYFUNCTION("if(ISBLANK(B69),"""",googlefinance(B69,""Marketcap"")/10000000)"),40061.4856208) -> 40061.486
B70: NSE:IRFC | C70: =IFERROR(__xludf.DUMMYFUNCTION("if(ISBLANK(B70),"""",GOOGLEFINANCE(B70,""NAME""))"),"Indian Railway Finance Corp Ltd") -> Indian Railway Finance Corp Ltd | D70: =if(ISBLANK(B70),"",if(L70<-10%,"B","H")) -> B | E70: =if(ISBLANK(B70),"",if(L70<-15%,"B","H")) -> B | F70: =IF(ISBLANK(B70), "", IF(O70 > 600000, "Mega Cap", IF(O70 > 30000, "Large Cap", IF(O70 > 7500, "Mid Cap", "Small Cap")))) -> Large Cap | G70: =IFERROR(__xludf.DUMMYFUNCTION("if(ISBLANK(B70),"""",GOOGLEFINANCE(B70,""price""))"),89.9) -> 89.9 | H70: =if(ISBLANK(B70),"",if(ISBLANK(M70),"",if(M70=0,"Extra",if(G70<M70,"Buy","Hold")))) -> Hold | I70: =IFERROR(__xludf.DUMMYFUNCTION("if(ISBLANK(B70),"""",GOOGLEFINANCE(B70,""CHANGEPCT"")/100)"),-0.0038) -> -0.0038 | J70: =IFERROR(__xludf.DUMMYFUNCTION("if(ISBLANK(B70),"""",GOOGLEFINANCE(B70,""HIGH52""))"),140.0) -> 140 | K70: =IFERROR(__xludf.DUMMYFUNCTION("if(ISBLANK(B70),"""",GOOGLEFINANCE(B70,""LOW52""))"),87.0) -> 87 | L70: =if(isblank(B70),"",(G70-J70)/J70) -> -0.35785714 | M70: =J70-(J70*0.6) -> 56 | N70: =IF(ISBLANK(B70), "", IF(AND(O70 >= 0, O70 <= 7500), "||||", IF(AND(O70 > 7500, O70 <= 30000), "|||", IF(AND(O70 > 30000, O70 <= 600000), "||", IF(O70 > 600000, "|", ""))))) -> || | O70: =IFERROR(__xludf.DUMMYFUNCTION("if(ISBLANK(B70),"""",googlefinance(B70,""Marketcap"")/10000000)"),117593.1601603) -> 117593.16
B71: NSE:ITC | C71: =IFERROR(__xludf.DUMMYFUNCTION("if(ISBLANK(B71),"""",GOOGLEFINANCE(B71,""NAME""))"),"ITC Ltd") -> ITC Ltd | D71: =if(ISBLANK(B71),"",if(L71<-10%,"B","H")) -> B | E71: =if(ISBLANK(B71),"",if(L71<-15%,"B","H")) -> B | F71: =IF(ISBLANK(B71), "", IF(O71 > 600000, "Mega Cap", IF(O71 > 30000, "Large Cap", IF(O71 > 7500, "Mid Cap", "Small Cap")))) -> Large Cap | G71: =IFERROR(__xludf.DUMMYFUNCTION("if(ISBLANK(B71),"""",GOOGLEFINANCE(B71,""price""))"),288.0) -> 288 | H71: =if(ISBLANK(B71),"",if(ISBLANK(M71),"",if(M71=0,"Extra",if(G71<M71,"Buy","Hold")))) -> Hold | I71: =IFERROR(__xludf.DUMMYFUNCTION("if(ISBLANK(B71),"""",GOOGLEFINANCE(B71,""CHANGEPCT"")/100)"),-9.0E-4) -> -0.0009 | J71: =IFERROR(__xludf.DUMMYFUNCTION("if(ISBLANK(B71),"""",GOOGLEFINANCE(B71,""HIGH52""))"),427.0) -> 427 | K71: =IFERROR(__xludf.DUMMYFUNCTION("if(ISBLANK(B71),"""",GOOGLEFINANCE(B71,""LOW52""))"),275.05) -> 275.05 | L71: =if(isblank(B71),"",(G71-J71)/J71) -> -0.32552693 | M71: =J71-(J71*0.45) -> 234.85 | N71: =IF(ISBLANK(B71), "", IF(AND(O71 >= 0, O71 <= 7500), "||||", IF(AND(O71 > 7500, O71 <= 30000), "|||", IF(AND(O71 > 30000, O71 <= 600000), "||", IF(O71 > 600000, "|", ""))))) -> || | O71: =IFERROR(__xludf.DUMMYFUNCTION("if(ISBLANK(B71),"""",googlefinance(B71,""Marketcap"")/10000000)"),361544.4751617) -> 361544.48
B72: NSE:JIOFIN | C72: =IFERROR(__xludf.DUMMYFUNCTION("if(ISBLANK(B72),"""",GOOGLEFINANCE(B72,""NAME""))"),"Jio Financial Services Ltd") -> Jio Financial Services Ltd | D72: =if(ISBLANK(B72),"",if(L72<-10%,"B","H")) -> B | E72: =if(ISBLANK(B72),"",if(L72<-15%,"B","H")) -> B | F72: =IF(ISBLANK(B72), "", IF(O72 > 600000, "Mega Cap", IF(O72 > 30000, "Large Cap", IF(O72 > 7500, "Mid Cap", "Small Cap")))) -> Large Cap | G72: =IFERROR(__xludf.DUMMYFUNCTION("if(ISBLANK(B72),"""",GOOGLEFINANCE(B72,""price""))"),243.0) -> 243 | H72: =if(ISBLANK(B72),"",if(ISBLANK(M72),"",if(M72=0,"Extra",if(G72<M72,"Buy","Hold")))) -> Hold | I72: =IFERROR(__xludf.DUMMYFUNCTION("if(ISBLANK(B72),"""",GOOGLEFINANCE(B72,""CHANGEPCT"")/100)"),0.0125) -> 0.0125 | J72: =IFERROR(__xludf.DUMMYFUNCTION("if(ISBLANK(B72),"""",GOOGLEFINANCE(B72,""HIGH52""))"),338.6) -> 338.6 | K72: =IFERROR(__xludf.DUMMYFUNCTION("if(ISBLANK(B72),"""",GOOGLEFINANCE(B72,""LOW52""))"),223.3) -> 223.3 | L72: =if(isblank(B72),"",(G72-J72)/J72) -> -0.28233904 | M72: =J72-(J72*0.65) -> 118.51 | N72: =IF(ISBLANK(B72), "", IF(AND(O72 >= 0, O72 <= 7500), "||||", IF(AND(O72 > 7500, O72 <= 30000), "|||", IF(AND(O72 > 30000, O72 <= 600000), "||", IF(O72 > 600000, "|", ""))))) -> || | O72: =IFERROR(__xludf.DUMMYFUNCTION("if(ISBLANK(B72),"""",googlefinance(B72,""Marketcap"")/10000000)"),154808.5606037) -> 154808.56
B73: NSE:JUBLFOOD | C73: =IFERROR(__xludf.DUMMYFUNCTION("if(ISBLANK(B73),"""",GOOGLEFINANCE(B73,""NAME""))"),"Jubilant FoodWorks Ltd") -> Jubilant FoodWorks Ltd | D73: =if(ISBLANK(B73),"",if(L73<-10%,"B","H")) -> B | E73: =if(ISBLANK(B73),"",if(L73<-15%,"B","H")) -> B | F73: =IF(ISBLANK(B73), "", IF(O73 > 600000, "Mega Cap", IF(O73 > 30000, "Large Cap", IF(O73 > 7500, "Mid Cap", "Small Cap")))) -> Mid Cap | G73: =IFERROR(__xludf.DUMMYFUNCTION("if(ISBLANK(B73),"""",GOOGLEFINANCE(B73,""price""))"),455.7) -> 455.7 | H73: =if(ISBLANK(B73),"",if(ISBLANK(M73),"",if(M73=0,"Extra",if(G73<M73,"Buy","Hold")))) -> Buy | I73: =IFERROR(__xludf.DUMMYFUNCTION("if(ISBLANK(B73),"""",GOOGLEFINANCE(B73,""CHANGEPCT"")/100)"),0.0398) -> 0.0398 | J73: =IFERROR(__xludf.DUMMYFUNCTION("if(ISBLANK(B73),"""",GOOGLEFINANCE(B73,""HIGH52""))"),714.7) -> 714.7 | K73: =IFERROR(__xludf.DUMMYFUNCTION("if(ISBLANK(B73),"""",GOOGLEFINANCE(B73,""LOW52""))"),408.8) -> 408.8 | L73: =if(isblank(B73),"",(G73-J73)/J73) -> -0.36238981 | M73: =J73-(J73*0.35) -> 464.555 | N73: =IF(ISBLANK(B73), "", IF(AND(O73 >= 0, O73 <= 7500), "||||", IF(AND(O73 > 7500, O73 <= 30000), "|||", IF(AND(O73 > 30000, O73 <= 600000), "||", IF(O73 > 600000, "|", ""))))) -> ||| | O73: =IFERROR(__xludf.DUMMYFUNCTION("if(ISBLANK(B73),"""",googlefinance(B73,""Marketcap"")/10000000)"),29937.8209465) -> 29937.821
B74: NSE:LATENTVIEW | C74: =IFERROR(__xludf.DUMMYFUNCTION("if(ISBLANK(B74),"""",GOOGLEFINANCE(B74,""NAME""))"),"Latent View Analytics Ltd") -> Latent View Analytics Ltd | D74: =if(ISBLANK(B74),"",if(L74<-10%,"B","H")) -> B | E74: =if(ISBLANK(B74),"",if(L74<-15%,"B","H")) -> B | F74: =IF(ISBLANK(B74), "", IF(O74 > 600000, "Mega Cap", IF(O74 > 30000, "Large Cap", IF(O74 > 7500, "Mid Cap", "Small Cap")))) -> Small Cap | G74: =IFERROR(__xludf.DUMMYFUNCTION("if(ISBLANK(B74),"""",GOOGLEFINANCE(B74,""price""))"),301.8) -> 301.8 | H74: =if(ISBLANK(B74),"",if(ISBLANK(M74),"",if(M74=0,"Extra",if(G74<M74,"Buy","Hold")))) -> Hold | I74: =IFERROR(__xludf.DUMMYFUNCTION("if(ISBLANK(B74),"""",GOOGLEFINANCE(B74,""CHANGEPCT"")/100)"),0.0556) -> 0.0556 | J74: =IFERROR(__xludf.DUMMYFUNCTION("if(ISBLANK(B74),"""",GOOGLEFINANCE(B74,""HIGH52""))"),517.5) -> 517.5 | K74: =IFERROR(__xludf.DUMMYFUNCTION("if(ISBLANK(B74),"""",GOOGLEFINANCE(B74,""LOW52""))"),248.0) -> 248 | L74: =if(isblank(B74),"",(G74-J74)/J74) -> -0.41681159 | M74: =J74-(J74*0.45) -> 284.625 | N74: =IF(ISBLANK(B74), "", IF(AND(O74 >= 0, O74 <= 7500), "||||", IF(AND(O74 > 7500, O74 <= 30000), "|||", IF(AND(O74 > 30000, O74 <= 600000), "||", IF(O74 > 600000, "|", ""))))) -> |||| | O74: =IFERROR(__xludf.DUMMYFUNCTION("if(ISBLANK(B74),"""",googlefinance(B74,""Marketcap"")/10000000)"),6232.3834456) -> 6232.3834
B75: NSE:LICI | C75: =IFERROR(__xludf.DUMMYFUNCTION("if(ISBLANK(B75),"""",GOOGLEFINANCE(B75,""NAME""))"),"Life Insurance Corporation of India") -> Life Insurance Corporation of India | D75: =if(ISBLANK(B75),"",if(L75<-10%,"B","H")) -> H | E75: =if(ISBLANK(B75),"",if(L75<-15%,"B","H")) -> H | F75: =IF(ISBLANK(B75), "", IF(O75 > 600000, "Mega Cap", IF(O75 > 30000, "Large Cap", IF(O75 > 7500, "Mid Cap", "Small Cap")))) -> Large Cap | G75: =IFERROR(__xludf.DUMMYFUNCTION("if(ISBLANK(B75),"""",GOOGLEFINANCE(B75,""price""))"),435.5) -> 435.5 | H75: =if(ISBLANK(B75),"",if(ISBLANK(M75),"",if(M75=0,"Extra",if(G75<M75,"Buy","Hold")))) -> Hold | I75: =IFERROR(__xludf.DUMMYFUNCTION("if(ISBLANK(B75),"""",GOOGLEFINANCE(B75,""CHANGEPCT"")/100)"),0.0149) -> 0.0149 | J75: =IFERROR(__xludf.DUMMYFUNCTION("if(ISBLANK(B75),"""",GOOGLEFINANCE(B75,""HIGH52""))"),476.5) -> 476.5 | K75: =IFERROR(__xludf.DUMMYFUNCTION("if(ISBLANK(B75),"""",GOOGLEFINANCE(B75,""LOW52""))"),360.75) -> 360.75 | L75: =if(isblank(B75),"",(G75-J75)/J75) -> -0.086044071 | M75: =J75-(J75*0.45) -> 262.075 | N75: =IF(ISBLANK(B75), "", IF(AND(O75 >= 0, O75 <= 7500), "||||", IF(AND(O75 > 7500, O75 <= 30000), "|||", IF(AND(O75 > 30000, O75 <= 600000), "||", IF(O75 > 600000, "|", ""))))) -> || | O75: =IFERROR(__xludf.DUMMYFUNCTION("if(ISBLANK(B75),"""",googlefinance(B75,""Marketcap"")/10000000)"),275436.5896613) -> 275436.59
B76: NSE:LTIM | C76: =IFERROR(__xludf.DUMMYFUNCTION("if(ISBLANK(B76),"""",GOOGLEFINANCE(B76,""NAME""))"),"#N/A") -> #N/A | D76: =if(ISBLANK(B76),"",if(L76<-10%,"B","H")) -> #N/A | E76: =if(ISBLANK(B76),"",if(L76<-15%,"B","H")) -> #N/A | F76: =IF(ISBLANK(B76), "", IF(O76 > 600000, "Mega Cap", IF(O76 > 30000, "Large Cap", IF(O76 > 7500, "Mid Cap", "Small Cap")))) -> #N/A | G76: =IFERROR(__xludf.DUMMYFUNCTION("if(ISBLANK(B76),"""",GOOGLEFINANCE(B76,""price""))"),"#N/A") -> #N/A | H76: =if(ISBLANK(B76),"",if(ISBLANK(M76),"",if(M76=0,"Extra",if(G76<M76,"Buy","Hold")))) -> #N/A | I76: =IFERROR(__xludf.DUMMYFUNCTION("if(ISBLANK(B76),"""",GOOGLEFINANCE(B76,""CHANGEPCT"")/100)"),"#N/A") -> #N/A | J76: =IFERROR(__xludf.DUMMYFUNCTION("if(ISBLANK(B76),"""",GOOGLEFINANCE(B76,""HIGH52""))"),"#N/A") -> #N/A | K76: =IFERROR(__xludf.DUMMYFUNCTION("if(ISBLANK(B76),"""",GOOGLEFINANCE(B76,""LOW52""))"),"#N/A") -> #N/A | L76: =if(isblank(B76),"",(G76-J76)/J76) -> #N/A | M76: =J76-(J76*0.45) -> #N/A | N76: =IF(ISBLANK(B76), "", IF(AND(O76 >= 0, O76 <= 7500), "||||", IF(AND(O76 > 7500, O76 <= 30000), "|||", IF(AND(O76 > 30000, O76 <= 600000), "||", IF(O76 > 600000, "|", ""))))) -> #N/A | O76: =IFERROR(__xludf.DUMMYFUNCTION("if(ISBLANK(B76),"""",googlefinance(B76,""Marketcap"")/10000000)"),"#N/A") -> #N/A
B77: NSE:LTTS | C77: =IFERROR(__xludf.DUMMYFUNCTION("if(ISBLANK(B77),"""",GOOGLEFINANCE(B77,""NAME""))"),"L&T Technology Services Ltd") -> L&T Technology Services Ltd | D77: =if(ISBLANK(B77),"",if(L77<-10%,"B","H")) -> B | E77: =if(ISBLANK(B77),"",if(L77<-15%,"B","H")) -> B | F77: =IF(ISBLANK(B77), "", IF(O77 > 600000, "Mega Cap", IF(O77 > 30000, "Large Cap", IF(O77 > 7500, "Mid Cap", "Small Cap")))) -> Large Cap | G77: =IFERROR(__xludf.DUMMYFUNCTION("if(ISBLANK(B77),"""",GOOGLEFINANCE(B77,""price""))"),3238.0) -> 3238 | H77: =if(ISBLANK(B77),"",if(ISBLANK(M77),"",if(M77=0,"Extra",if(G77<M77,"Buy","Hold")))) -> Hold | I77: =IFERROR(__xludf.DUMMYFUNCTION("if(ISBLANK(B77),"""",GOOGLEFINANCE(B77,""CHANGEPCT"")/100)"),0.0241) -> 0.0241 | J77: =IFERROR(__xludf.DUMMYFUNCTION("if(ISBLANK(B77),"""",GOOGLEFINANCE(B77,""HIGH52""))"),4726.0) -> 4726 | K77: =IFERROR(__xludf.DUMMYFUNCTION("if(ISBLANK(B77),"""",GOOGLEFINANCE(B77,""LOW52""))"),3010.0) -> 3010 | L77: =if(isblank(B77),"",(G77-J77)/J77) -> -0.314854 | M77: =J77-(J77*0.35) -> 3071.9 | N77: =IF(ISBLANK(B77), "", IF(AND(O77 >= 0, O77 <= 7500), "||||", IF(AND(O77 > 7500, O77 <= 30000), "|||", IF(AND(O77 > 30000, O77 <= 600000), "||", IF(O77 > 600000, "|", ""))))) -> || | O77: =IFERROR(__xludf.DUMMYFUNCTION("if(ISBLANK(B77),"""",googlefinance(B77,""Marketcap"")/10000000)"),34344.9803) -> 34344.98
B78: NSE:MARUTI | C78: =IFERROR(__xludf.DUMMYFUNCTION("if(ISBLANK(B78),"""",GOOGLEFINANCE(B78,""NAME""))"),"Maruti Suzuki India Ltd") -> Maruti Suzuki India Ltd | D78: =if(ISBLANK(B78),"",if(L78<-10%,"B","H")) -> B | E78: =if(ISBLANK(B78),"",if(L78<-15%,"B","H")) -> B | F78: =IF(ISBLANK(B78), "", IF(O78 > 600000, "Mega Cap", IF(O78 > 30000, "Large Cap", IF(O78 > 7500, "Mid Cap", "Small Cap")))) -> Large Cap | G78: =IFERROR(__xludf.DUMMYFUNCTION("if(ISBLANK(B78),"""",GOOGLEFINANCE(B78,""price""))"),14528.0) -> 14528 | H78: =if(ISBLANK(B78),"",if(ISBLANK(M78),"",if(M78=0,"Extra",if(G78<M78,"Buy","Hold")))) -> Hold | I78: =IFERROR(__xludf.DUMMYFUNCTION("if(ISBLANK(B78),"""",GOOGLEFINANCE(B78,""CHANGEPCT"")/100)"),0.005) -> 0.005 | J78: =IFERROR(__xludf.DUMMYFUNCTION("if(ISBLANK(B78),"""",GOOGLEFINANCE(B78,""HIGH52""))"),17370.0) -> 17370 | K78: =IFERROR(__xludf.DUMMYFUNCTION("if(ISBLANK(B78),"""",GOOGLEFINANCE(B78,""LOW52""))"),12201.0) -> 12201 | L78: =if(isblank(B78),"",(G78-J78)/J78) -> -0.16361543 | M78: 5000 | N78: =IF(ISBLANK(B78), "", IF(AND(O78 >= 0, O78 <= 7500), "||||", IF(AND(O78 > 7500, O78 <= 30000), "|||", IF(AND(O78 > 30000, O78 <= 600000), "||", IF(O78 > 600000, "|", ""))))) -> || | O78: =IFERROR(__xludf.DUMMYFUNCTION("if(ISBLANK(B78),"""",googlefinance(B78,""Marketcap"")/10000000)"),457262.6497752) -> 457262.65
B79: NSE:MOLDTKPAC | C79: =IFERROR(__xludf.DUMMYFUNCTION("if(ISBLANK(B79),"""",GOOGLEFINANCE(B79,""NAME""))"),"Mold-Tek Packaging Ltd") -> Mold-Tek Packaging Ltd | D79: =if(ISBLANK(B79),"",if(L79<-10%,"B","H")) -> B | E79: =if(ISBLANK(B79),"",if(L79<-15%,"B","H")) -> B | F79: =IF(ISBLANK(B79), "", IF(O79 > 600000, "Mega Cap", IF(O79 > 30000, "Large Cap", IF(O79 > 7500, "Mid Cap", "Small Cap")))) -> Small Cap | G79: =IFERROR(__xludf.DUMMYFUNCTION("if(ISBLANK(B79),"""",GOOGLEFINANCE(B79,""price""))"),694.65) -> 694.65 | H79: =if(ISBLANK(B79),"",if(ISBLANK(M79),"",if(M79=0,"Extra",if(G79<M79,"Buy","Hold")))) -> Hold | I79: =IFERROR(__xludf.DUMMYFUNCTION("if(ISBLANK(B79),"""",GOOGLEFINANCE(B79,""CHANGEPCT"")/100)"),0.0184) -> 0.0184 | J79: =IFERROR(__xludf.DUMMYFUNCTION("if(ISBLANK(B79),"""",GOOGLEFINANCE(B79,""HIGH52""))"),892.9) -> 892.9 | K79: =IFERROR(__xludf.DUMMYFUNCTION("if(ISBLANK(B79),"""",GOOGLEFINANCE(B79,""LOW52""))"),464.9) -> 464.9 | L79: =if(isblank(B79),"",(G79-J79)/J79) -> -0.22202934 | M79: =J79-(J79*0.65) -> 312.515 | N79: =IF(ISBLANK(B79), "", IF(AND(O79 >= 0, O79 <= 7500), "||||", IF(AND(O79 > 7500, O79 <= 30000), "|||", IF(AND(O79 > 30000, O79 <= 600000), "||", IF(O79 > 600000, "|", ""))))) -> |||| | O79: =IFERROR(__xludf.DUMMYFUNCTION("if(ISBLANK(B79),"""",googlefinance(B79,""Marketcap"")/10000000)"),2309.5105308) -> 2309.5105
B80: NSE:MOTHERSON | C80: =IFERROR(__xludf.DUMMYFUNCTION("if(ISBLANK(B80),"""",GOOGLEFINANCE(B80,""NAME""))"),"Samvardhana Motherson International Ltd") -> Samvardhana Motherson International Ltd | D80: =if(ISBLANK(B80),"",if(L80<-10%,"B","H")) -> H | E80: =if(ISBLANK(B80),"",if(L80<-15%,"B","H")) -> H | F80: =IF(ISBLANK(B80), "", IF(O80 > 600000, "Mega Cap", IF(O80 > 30000, "Large Cap", IF(O80 > 7500, "Mid Cap", "Small Cap")))) -> Large Cap | G80: =IFERROR(__xludf.DUMMYFUNCTION("if(ISBLANK(B80),"""",GOOGLEFINANCE(B80,""price""))"),143.0) -> 143 | H80: =if(ISBLANK(B80),"",if(ISBLANK(M80),"",if(M80=0,"Extra",if(G80<M80,"Buy","Hold")))) -> Hold | I80: =IFERROR(__xludf.DUMMYFUNCTION("if(ISBLANK(B80),"""",GOOGLEFINANCE(B80,""CHANGEPCT"")/100)"),-0.016) -> -0.016 | J80: =IFERROR(__xludf.DUMMYFUNCTION("if(ISBLANK(B80),"""",GOOGLEFINANCE(B80,""HIGH52""))"),155.25) -> 155.25 | K80: =IFERROR(__xludf.DUMMYFUNCTION("if(ISBLANK(B80),"""",GOOGLEFINANCE(B80,""LOW52""))"),89.7) -> 89.7 | L80: =if(isblank(B80),"",(G80-J80)/J80) -> -0.078904992 | M80: =J80-(J80*0.55) -> 69.8625 | N80: =IF(ISBLANK(B80), "", IF(AND(O80 >= 0, O80 <= 7500), "||||", IF(AND(O80 > 7500, O80 <= 30000), "|||", IF(AND(O80 > 30000, O80 <= 600000), "||", IF(O80 > 600000, "|", ""))))) -> || | O80: =IFERROR(__xludf.DUMMYFUNCTION("if(ISBLANK(B80),"""",googlefinance(B80,""Marketcap"")/10000000)"),96944.2045) -> 96944.205
B81: NSE:MTARTECH | C81: =IFERROR(__xludf.DUMMYFUNCTION("if(ISBLANK(B81),"""",GOOGLEFINANCE(B81,""NAME""))"),"MTAR Technologies Ltd") -> MTAR Technologies Ltd | D81: =if(ISBLANK(B81),"",if(L81<-10%,"B","H")) -> B | E81: =if(ISBLANK(B81),"",if(L81<-15%,"B","H")) -> B | F81: =IF(ISBLANK(B81), "", IF(O81 > 600000, "Mega Cap", IF(O81 > 30000, "Large Cap", IF(O81 > 7500, "Mid Cap", "Small Cap")))) -> Mid Cap | G81: =IFERROR(__xludf.DUMMYFUNCTION("if(ISBLANK(B81),"""",GOOGLEFINANCE(B81,""price""))"),7000.0) -> 7000 | H81: =if(ISBLANK(B81),"",if(ISBLANK(M81),"",if(M81=0,"Extra",if(G81<M81,"Buy","Hold")))) -> Hold | I81: =IFERROR(__xludf.DUMMYFUNCTION("if(ISBLANK(B81),"""",GOOGLEFINANCE(B81,""CHANGEPCT"")/100)"),-0.0067) -> -0.0067 | J81: =IFERROR(__xludf.DUMMYFUNCTION("if(ISBLANK(B81),"""",GOOGLEFINANCE(B81,""HIGH52""))"),8714.0) -> 8714 | K81: =IFERROR(__xludf.DUMMYFUNCTION("if(ISBLANK(B81),"""",GOOGLEFINANCE(B81,""LOW52""))"),1390.5) -> 1390.5 | L81: =if(isblank(B81),"",(G81-J81)/J81) -> -0.19669497 | M81: =J81-(J81*0.45) -> 4792.7 | N81: =IF(ISBLANK(B81), "", IF(AND(O81 >= 0, O81 <= 7500), "||||", IF(AND(O81 > 7500, O81 <= 30000), "|||", IF(AND(O81 > 30000, O81 <= 600000), "||", IF(O81 > 600000, "|", ""))))) -> ||| | O81: =IFERROR(__xludf.DUMMYFUNCTION("if(ISBLANK(B81),"""",googlefinance(B81,""Marketcap"")/10000000)"),21547.2100835) -> 21547.21
B82: NSE:MUTHOOTFIN | C82: =IFERROR(__xludf.DUMMYFUNCTION("if(ISBLANK(B82),"""",GOOGLEFINANCE(B82,""NAME""))"),"Muthoot Finance Ltd") -> Muthoot Finance Ltd | D82: =if(ISBLANK(B82),"",if(L82<-10%,"B","H")) -> B | E82: =if(ISBLANK(B82),"",if(L82<-15%,"B","H")) -> B | F82: =IF(ISBLANK(B82), "", IF(O82 > 600000, "Mega Cap", IF(O82 > 30000, "Large Cap", IF(O82 > 7500, "Mid Cap", "Small Cap")))) -> Large Cap | G82: =IFERROR(__xludf.DUMMYFUNCTION("if(ISBLANK(B82),"""",GOOGLEFINANCE(B82,""price""))"),3116.0) -> 3116 | H82: =if(ISBLANK(B82),"",if(ISBLANK(M82),"",if(M82=0,"Extra",if(G82<M82,"Buy","Hold")))) -> Buy | I82: =IFERROR(__xludf.DUMMYFUNCTION("if(ISBLANK(B82),"""",GOOGLEFINANCE(B82,""CHANGEPCT"")/100)"),-0.0069) -> -0.0069 | J82: =IFERROR(__xludf.DUMMYFUNCTION("if(ISBLANK(B82),"""",GOOGLEFINANCE(B82,""HIGH52""))"),4149.5) -> 4149.5 | K82: =IFERROR(__xludf.DUMMYFUNCTION("if(ISBLANK(B82),"""",GOOGLEFINANCE(B82,""LOW52""))"),2476.6) -> 2476.6 | L82: =if(isblank(B82),"",(G82-J82)/J82) -> -0.24906615 | M82: =J82-(J82*0.2) -> 3319.6 | N82: =IF(ISBLANK(B82), "", IF(AND(O82 >= 0, O82 <= 7500), "||||", IF(AND(O82 > 7500, O82 <= 30000), "|||", IF(AND(O82 > 30000, O82 <= 600000), "||", IF(O82 > 600000, "|", ""))))) -> || | O82: =IFERROR(__xludf.DUMMYFUNCTION("if(ISBLANK(B82),"""",googlefinance(B82,""Marketcap"")/10000000)"),125546.230395) -> 125546.23
B83: NSE:NAZARA | C83: =IFERROR(__xludf.DUMMYFUNCTION("if(ISBLANK(B83),"""",GOOGLEFINANCE(B83,""NAME""))"),"Nazara Technologies Ltd") -> Nazara Technologies Ltd | D83: =if(ISBLANK(B83),"",if(L83<-10%,"B","H")) -> B | E83: =if(ISBLANK(B83),"",if(L83<-15%,"B","H")) -> B | F83: =IF(ISBLANK(B83), "", IF(O83 > 600000, "Mega Cap", IF(O83 > 30000, "Large Cap", IF(O83 > 7500, "Mid Cap", "Small Cap")))) -> Mid Cap | G83: =IFERROR(__xludf.DUMMYFUNCTION("if(ISBLANK(B83),"""",GOOGLEFINANCE(B83,""price""))"),301.9) -> 301.9 | H83: =if(ISBLANK(B83),"",if(ISBLANK(M83),"",if(M83=0,"Extra",if(G83<M83,"Buy","Hold")))) -> Hold | I83: =IFERROR(__xludf.DUMMYFUNCTION("if(ISBLANK(B83),"""",GOOGLEFINANCE(B83,""CHANGEPCT"")/100)"),0.0109) -> 0.0109 | J83: =IFERROR(__xludf.DUMMYFUNCTION("if(ISBLANK(B83),"""",GOOGLEFINANCE(B83,""HIGH52""))"),363.25) -> 363.25 | K83: =IFERROR(__xludf.DUMMYFUNCTION("if(ISBLANK(B83),"""",GOOGLEFINANCE(B83,""LOW52""))"),215.7) -> 215.7 | L83: =if(isblank(B83),"",(G83-J83)/J83) -> -0.16889195 | M83: =J83-(J83*0.3) -> 254.275 | N83: =IF(ISBLANK(B83), "", IF(AND(O83 >= 0, O83 <= 7500), "||||", IF(AND(O83 > 7500, O83 <= 30000), "|||", IF(AND(O83 > 30000, O83 <= 600000), "||", IF(O83 > 600000, "|", ""))))) -> ||| | O83: =IFERROR(__xludf.DUMMYFUNCTION("if(ISBLANK(B83),"""",googlefinance(B83,""Marketcap"")/10000000)"),11184.3351048) -> 11184.335
B84: NSE:NESTLEIND | C84: =IFERROR(__xludf.DUMMYFUNCTION("if(ISBLANK(B84),"""",GOOGLEFINANCE(B84,""NAME""))"),"Nestle India Ltd") -> Nestle India Ltd | D84: =if(ISBLANK(B84),"",if(L84<-10%,"B","H")) -> H | E84: =if(ISBLANK(B84),"",if(L84<-15%,"B","H")) -> H | F84: =IF(ISBLANK(B84), "", IF(O84 > 600000, "Mega Cap", IF(O84 > 30000, "Large Cap", IF(O84 > 7500, "Mid Cap", "Small Cap")))) -> Large Cap | G84: =IFERROR(__xludf.DUMMYFUNCTION("if(ISBLANK(B84),"""",GOOGLEFINANCE(B84,""price""))"),1466.9) -> 1466.9 | H84: =if(ISBLANK(B84),"",if(ISBLANK(M84),"",if(M84=0,"Extra",if(G84<M84,"Buy","Hold")))) -> Hold | I84: =IFERROR(__xludf.DUMMYFUNCTION("if(ISBLANK(B84),"""",GOOGLEFINANCE(B84,""CHANGEPCT"")/100)"),-0.0046) -> -0.0046 | J84: =IFERROR(__xludf.DUMMYFUNCTION("if(ISBLANK(B84),"""",GOOGLEFINANCE(B84,""HIGH52""))"),1498.1) -> 1498.1 | K84: =IFERROR(__xludf.DUMMYFUNCTION("if(ISBLANK(B84),"""",GOOGLEFINANCE(B84,""LOW52""))"),1084.7) -> 1084.7 | L84: =if(isblank(B84),"",(G84-J84)/J84) -> -0.02082638 | M84: =J84-(J84*0.3) -> 1048.67 | N84: =IF(ISBLANK(B84), "", IF(AND(O84 >= 0, O84 <= 7500), "||||", IF(AND(O84 > 7500, O84 <= 30000), "|||", IF(AND(O84 > 30000, O84 <= 600000), "||", IF(O84 > 600000, "|", ""))))) -> || | O84: =IFERROR(__xludf.DUMMYFUNCTION("if(ISBLANK(B84),"""",googlefinance(B84,""Marketcap"")/10000000)"),282864.3853677) -> 282864.39
B85: NSE:PARADEEP | C85: =IFERROR(__xludf.DUMMYFUNCTION("if(ISBLANK(B85),"""",GOOGLEFINANCE(B85,""NAME""))"),"Paradeep Phosphates Ltd") -> Paradeep Phosphates Ltd | D85: =if(ISBLANK(B85),"",if(L85<-10%,"B","H")) -> B | E85: =if(ISBLANK(B85),"",if(L85<-15%,"B","H")) -> B | F85: =IF(ISBLANK(B85), "", IF(O85 > 600000, "Mega Cap", IF(O85 > 30000, "Large Cap", IF(O85 > 7500, "Mid Cap", "Small Cap")))) -> Mid Cap | G85: =IFERROR(__xludf.DUMMYFUNCTION("if(ISBLANK(B85),"""",GOOGLEFINANCE(B85,""price""))"),139.3) -> 139.3 | H85: =if(ISBLANK(B85),"",if(ISBLANK(M85),"",if(M85=0,"Extra",if(G85<M85,"Buy","Hold")))) -> Buy | I85: =IFERROR(__xludf.DUMMYFUNCTION("if(ISBLANK(B85),"""",GOOGLEFINANCE(B85,""CHANGEPCT"")/100)"),-0.0253) -> -0.0253 | J85: =IFERROR(__xludf.DUMMYFUNCTION("if(ISBLANK(B85),"""",GOOGLEFINANCE(B85,""HIGH52""))"),234.39) -> 234.39 | K85: =IFERROR(__xludf.DUMMYFUNCTION("if(ISBLANK(B85),"""",GOOGLEFINANCE(B85,""LOW52""))"),99.7) -> 99.7 | L85: =if(isblank(B85),"",(G85-J85)/J85) -> -0.40569137 | M85: =J85-(J85*0.4) -> 140.634 | N85: =IF(ISBLANK(B85), "", IF(AND(O85 >= 0, O85 <= 7500), "||||", IF(AND(O85 > 7500, O85 <= 30000), "|||", IF(AND(O85 > 30000, O85 <= 600000), "||", IF(O85 > 600000, "|", ""))))) -> ||| | O85: =IFERROR(__xludf.DUMMYFUNCTION("if(ISBLANK(B85),"""",googlefinance(B85,""Marketcap"")/10000000)"),14455.528575) -> 14455.529
B86: NSE:PARAS | C86: =IFERROR(__xludf.DUMMYFUNCTION("if(ISBLANK(B86),"""",GOOGLEFINANCE(B86,""NAME""))"),"Paras Defence and Space Technologies Ltd") -> Paras Defence and Space Technologies Ltd | D86: =if(ISBLANK(B86),"",if(L86<-10%,"B","H")) -> B | E86: =if(ISBLANK(B86),"",if(L86<-15%,"B","H")) -> H | F86: =IF(ISBLANK(B86), "", IF(O86 > 600000, "Mega Cap", IF(O86 > 30000, "Large Cap", IF(O86 > 7500, "Mid Cap", "Small Cap")))) -> Mid Cap | G86: =IFERROR(__xludf.DUMMYFUNCTION("if(ISBLANK(B86),"""",GOOGLEFINANCE(B86,""price""))"),1292.0) -> 1292 | H86: =if(ISBLANK(B86),"",if(ISBLANK(M86),"",if(M86=0,"Extra",if(G86<M86,"Buy","Hold")))) -> Hold | I86: =IFERROR(__xludf.DUMMYFUNCTION("if(ISBLANK(B86),"""",GOOGLEFINANCE(B86,""CHANGEPCT"")/100)"),-0.0489) -> -0.0489 | J86: =IFERROR(__xludf.DUMMYFUNCTION("if(ISBLANK(B86),"""",GOOGLEFINANCE(B86,""HIGH52""))"),1443.0) -> 1443 | K86: =IFERROR(__xludf.DUMMYFUNCTION("if(ISBLANK(B86),"""",GOOGLEFINANCE(B86,""LOW52""))"),580.5) -> 580.5 | L86: =if(isblank(B86),"",(G86-J86)/J86) -> -0.1046431 | M86: =J86-(J86*0.5) -> 721.5 | N86: =IF(ISBLANK(B86), "", IF(AND(O86 >= 0, O86 <= 7500), "||||", IF(AND(O86 > 7500, O86 <= 30000), "|||", IF(AND(O86 > 30000, O86 <= 600000), "||", IF(O86 > 600000, "|", ""))))) -> ||| | O86: =IFERROR(__xludf.DUMMYFUNCTION("if(ISBLANK(B86),"""",googlefinance(B86,""Marketcap"")/10000000)"),10436.0546727) -> 10436.055
B87: NSE:PGHH | C87: =IFERROR(__xludf.DUMMYFUNCTION("if(ISBLANK(B87),"""",GOOGLEFINANCE(B87,""NAME""))"),"Procter & Gamble Hygiene & Health Care") -> Procter & Gamble Hygiene & Health Care | D87: =if(ISBLANK(B87),"",if(L87<-10%,"B","H")) -> B | E87: =if(ISBLANK(B87),"",if(L87<-15%,"B","H")) -> B | F87: =IF(ISBLANK(B87), "", IF(O87 > 600000, "Mega Cap", IF(O87 > 30000, "Large Cap", IF(O87 > 7500, "Mid Cap", "Small Cap")))) -> Mid Cap | G87: =IFERROR(__xludf.DUMMYFUNCTION("if(ISBLANK(B87),"""",GOOGLEFINANCE(B87,""price""))"),9024.0) -> 9024 | H87: =if(ISBLANK(B87),"",if(ISBLANK(M87),"",if(M87=0,"Extra",if(G87<M87,"Buy","Hold")))) -> Buy | I87: =IFERROR(__xludf.DUMMYFUNCTION("if(ISBLANK(B87),"""",GOOGLEFINANCE(B87,""CHANGEPCT"")/100)"),0.0069) -> 0.0069 | J87: =IFERROR(__xludf.DUMMYFUNCTION("if(ISBLANK(B87),"""",GOOGLEFINANCE(B87,""HIGH52""))"),14540.0) -> 14540 | K87: =IFERROR(__xludf.DUMMYFUNCTION("if(ISBLANK(B87),"""",GOOGLEFINANCE(B87,""LOW52""))"),8750.5) -> 8750.5 | L87: =if(isblank(B87),"",(G87-J87)/J87) -> -0.37936726 | M87: =J87-(J87*0.35) -> 9451 | N87: =IF(ISBLANK(B87), "", IF(AND(O87 >= 0, O87 <= 7500), "||||", IF(AND(O87 > 7500, O87 <= 30000), "|||", IF(AND(O87 > 30000, O87 <= 600000), "||", IF(O87 > 600000, "|", ""))))) -> ||| | O87: =IFERROR(__xludf.DUMMYFUNCTION("if(ISBLANK(B87),"""",googlefinance(B87,""Marketcap"")/10000000)"),29343.7014327) -> 29343.701
B88: NSE:PIDILITIND | C88: =IFERROR(__xludf.DUMMYFUNCTION("if(ISBLANK(B88),"""",GOOGLEFINANCE(B88,""NAME""))"),"Pidilite Industries Ltd") -> Pidilite Industries Ltd | D88: =if(ISBLANK(B88),"",if(L88<-10%,"B","H")) -> H | E88: =if(ISBLANK(B88),"",if(L88<-15%,"B","H")) -> H | F88: =IF(ISBLANK(B88), "", IF(O88 > 600000, "Mega Cap", IF(O88 > 30000, "Large Cap", IF(O88 > 7500, "Mid Cap", "Small Cap")))) -> Large Cap | G88: =IFERROR(__xludf.DUMMYFUNCTION("if(ISBLANK(B88),"""",GOOGLEFINANCE(B88,""price""))"),1618.8) -> 1618.8 | H88: =if(ISBLANK(B88),"",if(ISBLANK(M88),"",if(M88=0,"Extra",if(G88<M88,"Buy","Hold")))) -> Hold | I88: =IFERROR(__xludf.DUMMYFUNCTION("if(ISBLANK(B88),"""",GOOGLEFINANCE(B88,""CHANGEPCT"")/100)"),0.0012) -> 0.0012 | J88: =IFERROR(__xludf.DUMMYFUNCTION("if(ISBLANK(B88),"""",GOOGLEFINANCE(B88,""HIGH52""))"),1626.7) -> 1626.7 | K88: =IFERROR(__xludf.DUMMYFUNCTION("if(ISBLANK(B88),"""",GOOGLEFINANCE(B88,""LOW52""))"),1259.0) -> 1259 | L88: =if(isblank(B88),"",(G88-J88)/J88) -> -0.0048564579 | M88: =J88-(J88*0.25) -> 1220.025 | N88: =IF(ISBLANK(B88), "", IF(AND(O88 >= 0, O88 <= 7500), "||||", IF(AND(O88 > 7500, O88 <= 30000), "|||", IF(AND(O88 > 30000, O88 <= 600000), "||", IF(O88 > 600000, "|", ""))))) -> || | O88: =IFERROR(__xludf.DUMMYFUNCTION("if(ISBLANK(B88),"""",googlefinance(B88,""Marketcap"")/10000000)"),82434.0079627) -> 82434.008
B89: NSE:PIIND | C89: =IFERROR(__xludf.DUMMYFUNCTION("if(ISBLANK(B89),"""",GOOGLEFINANCE(B89,""NAME""))"),"PI Industries Ltd") -> PI Industries Ltd | D89: =if(ISBLANK(B89),"",if(L89<-10%,"B","H")) -> B | E89: =if(ISBLANK(B89),"",if(L89<-15%,"B","H")) -> B | F89: =IF(ISBLANK(B89), "", IF(O89 > 600000, "Mega Cap", IF(O89 > 30000, "Large Cap", IF(O89 > 7500, "Mid Cap", "Small Cap")))) -> Large Cap | G89: =IFERROR(__xludf.DUMMYFUNCTION("if(ISBLANK(B89),"""",GOOGLEFINANCE(B89,""price""))"),2648.0) -> 2648 | H89: =if(ISBLANK(B89),"",if(ISBLANK(M89),"",if(M89=0,"Extra",if(G89<M89,"Buy","Hold")))) -> Hold | I89: =IFERROR(__xludf.DUMMYFUNCTION("if(ISBLANK(B89),"""",GOOGLEFINANCE(B89,""CHANGEPCT"")/100)"),-0.0106) -> -0.0106 | J89: =IFERROR(__xludf.DUMMYFUNCTION("if(ISBLANK(B89),"""",GOOGLEFINANCE(B89,""HIGH52""))"),4330.0) -> 4330 | K89: =IFERROR(__xludf.DUMMYFUNCTION("if(ISBLANK(B89),"""",GOOGLEFINANCE(B89,""LOW52""))"),2541.0) -> 2541 | L89: =if(isblank(B89),"",(G89-J89)/J89) -> -0.38845266 | M89: =J89-(J89*0.45) -> 2381.5 | N89: =IF(ISBLANK(B89), "", IF(AND(O89 >= 0, O89 <= 7500), "||||", IF(AND(O89 > 7500, O89 <= 30000), "|||", IF(AND(O89 > 30000, O89 <= 600000), "||", IF(O89 > 600000, "|", ""))))) -> || | O89: =IFERROR(__xludf.DUMMYFUNCTION("if(ISBLANK(B89),"""",googlefinance(B89,""Marketcap"")/10000000)"),40171.00736) -> 40171.007
B90: NSE:POLYCAB | C90: =IFERROR(__xludf.DUMMYFUNCTION("if(ISBLANK(B90),"""",GOOGLEFINANCE(B90,""NAME""))"),"Polycab India Ltd") -> Polycab India Ltd | D90: =if(ISBLANK(B90),"",if(L90<-10%,"B","H")) -> H | E90: =if(ISBLANK(B90),"",if(L90<-15%,"B","H")) -> H | F90: =IF(ISBLANK(B90), "", IF(O90 > 600000, "Mega Cap", IF(O90 > 30000, "Large Cap", IF(O90 > 7500, "Mid Cap", "Small Cap")))) -> Large Cap | G90: =IFERROR(__xludf.DUMMYFUNCTION("if(ISBLANK(B90),"""",GOOGLEFINANCE(B90,""price""))"),9364.0) -> 9364 | H90: =if(ISBLANK(B90),"",if(ISBLANK(M90),"",if(M90=0,"Extra",if(G90<M90,"Buy","Hold")))) -> Hold | I90: =IFERROR(__xludf.DUMMYFUNCTION("if(ISBLANK(B90),"""",GOOGLEFINANCE(B90,""CHANGEPCT"")/100)"),-0.023) -> -0.023 | J90: =IFERROR(__xludf.DUMMYFUNCTION("if(ISBLANK(B90),"""",GOOGLEFINANCE(B90,""HIGH52""))"),10126.0) -> 10126 | K90: =IFERROR(__xludf.DUMMYFUNCTION("if(ISBLANK(B90),"""",GOOGLEFINANCE(B90,""LOW52""))"),6605.0) -> 6605 | L90: =if(isblank(B90),"",(G90-J90)/J90) -> -0.075251827 | M90: =J90-(J90*0.4) -> 6075.6 | N90: =IF(ISBLANK(B90), "", IF(AND(O90 >= 0, O90 <= 7500), "||||", IF(AND(O90 > 7500, O90 <= 30000), "|||", IF(AND(O90 > 30000, O90 <= 600000), "||", IF(O90 > 600000, "|", ""))))) -> || | O90: =IFERROR(__xludf.DUMMYFUNCTION("if(ISBLANK(B90),"""",googlefinance(B90,""Marketcap"")/10000000)"),141720.8752037) -> 141720.88
B91: NSE:PRINCEPIPE | C91: =IFERROR(__xludf.DUMMYFUNCTION("if(ISBLANK(B91),"""",GOOGLEFINANCE(B91,""NAME""))"),"Prince Pipes and Fittings Ltd") -> Prince Pipes and Fittings Ltd | D91: =if(ISBLANK(B91),"",if(L91<-10%,"B","H")) -> B | E91: =if(ISBLANK(B91),"",if(L91<-15%,"B","H")) -> B | F91: =IF(ISBLANK(B91), "", IF(O91 > 600000, "Mega Cap", IF(O91 > 30000, "Large Cap", IF(O91 > 7500, "Mid Cap", "Small Cap")))) -> Small Cap | G91: =IFERROR(__xludf.DUMMYFUNCTION("if(ISBLANK(B91),"""",GOOGLEFINANCE(B91,""price""))"),269.9) -> 269.9 | H91: =if(ISBLANK(B91),"",if(ISBLANK(M91),"",if(M91=0,"Extra",if(G91<M91,"Buy","Hold")))) -> Hold | I91: =IFERROR(__xludf.DUMMYFUNCTION("if(ISBLANK(B91),"""",GOOGLEFINANCE(B91,""CHANGEPCT"")/100)"),-0.009000000000000001) -> -0.009 | J91: =IFERROR(__xludf.DUMMYFUNCTION("if(ISBLANK(B91),"""",GOOGLEFINANCE(B91,""HIGH52""))"),376.2) -> 376.2 | K91: =IFERROR(__xludf.DUMMYFUNCTION("if(ISBLANK(B91),"""",GOOGLEFINANCE(B91,""LOW52""))"),205.0) -> 205 | L91: =if(isblank(B91),"",(G91-J91)/J91) -> -0.28256247 | M91: =J91-(J91*0.85) -> 56.43 | N91: =IF(ISBLANK(B91), "", IF(AND(O91 >= 0, O91 <= 7500), "||||", IF(AND(O91 > 7500, O91 <= 30000), "|||", IF(AND(O91 > 30000, O91 <= 600000), "||", IF(O91 > 600000, "|", ""))))) -> |||| | O91: =IFERROR(__xludf.DUMMYFUNCTION("if(ISBLANK(B91),"""",googlefinance(B91,""Marketcap"")/10000000)"),2987.9604925) -> 2987.9605
B92: NSE:RAILTEL | C92: =IFERROR(__xludf.DUMMYFUNCTION("if(ISBLANK(B92),"""",GOOGLEFINANCE(B92,""NAME""))"),"Railtel Corporation of India Ltd") -> Railtel Corporation of India Ltd | D92: =if(ISBLANK(B92),"",if(L92<-10%,"B","H")) -> B | E92: =if(ISBLANK(B92),"",if(L92<-15%,"B","H")) -> B | F92: =IF(ISBLANK(B92), "", IF(O92 > 600000, "Mega Cap", IF(O92 > 30000, "Large Cap", IF(O92 > 7500, "Mid Cap", "Small Cap")))) -> Mid Cap | G92: =IFERROR(__xludf.DUMMYFUNCTION("if(ISBLANK(B92),"""",GOOGLEFINANCE(B92,""price""))"),311.3) -> 311.3 | H92: =if(ISBLANK(B92),"",if(ISBLANK(M92),"",if(M92=0,"Extra",if(G92<M92,"Buy","Hold")))) -> Hold | I92: =IFERROR(__xludf.DUMMYFUNCTION("if(ISBLANK(B92),"""",GOOGLEFINANCE(B92,""CHANGEPCT"")/100)"),0.005699999999999999) -> 0.0057 | J92: =IFERROR(__xludf.DUMMYFUNCTION("if(ISBLANK(B92),"""",GOOGLEFINANCE(B92,""HIGH52""))"),426.0) -> 426 | K92: =IFERROR(__xludf.DUMMYFUNCTION("if(ISBLANK(B92),"""",GOOGLEFINANCE(B92,""LOW52""))"),245.0) -> 245 | L92: =if(isblank(B92),"",(G92-J92)/J92) -> -0.26924883 | M92: =J92-(J92*0.55) -> 191.7 | N92: =IF(ISBLANK(B92), "", IF(AND(O92 >= 0, O92 <= 7500), "||||", IF(AND(O92 > 7500, O92 <= 30000), "|||", IF(AND(O92 > 30000, O92 <= 600000), "||", IF(O92 > 600000, "|", ""))))) -> ||| | O92: =IFERROR(__xludf.DUMMYFUNCTION("if(ISBLANK(B92),"""",googlefinance(B92,""Marketcap"")/10000000)"),9990.8088872) -> 9990.8089
B93: NSE:RELAXO | C93: =IFERROR(__xludf.DUMMYFUNCTION("if(ISBLANK(B93),"""",GOOGLEFINANCE(B93,""NAME""))"),"Relaxo Footwears Ltd") -> Relaxo Footwears Ltd | D93: =if(ISBLANK(B93),"",if(L93<-10%,"B","H")) -> B | E93: =if(ISBLANK(B93),"",if(L93<-15%,"B","H")) -> B | F93: =IF(ISBLANK(B93), "", IF(O93 > 600000, "Mega Cap", IF(O93 > 30000, "Large Cap", IF(O93 > 7500, "Mid Cap", "Small Cap")))) -> Mid Cap | G93: =IFERROR(__xludf.DUMMYFUNCTION("if(ISBLANK(B93),"""",GOOGLEFINANCE(B93,""price""))"),391.5) -> 391.5 | H93: =if(ISBLANK(B93),"",if(ISBLANK(M93),"",if(M93=0,"Extra",if(G93<M93,"Buy","Hold")))) -> Hold | I93: =IFERROR(__xludf.DUMMYFUNCTION("if(ISBLANK(B93),"""",GOOGLEFINANCE(B93,""CHANGEPCT"")/100)"),-0.0231) -> -0.0231 | J93: =IFERROR(__xludf.DUMMYFUNCTION("if(ISBLANK(B93),"""",GOOGLEFINANCE(B93,""HIGH52""))"),526.0) -> 526 | K93: =IFERROR(__xludf.DUMMYFUNCTION("if(ISBLANK(B93),"""",GOOGLEFINANCE(B93,""LOW52""))"),236.5) -> 236.5 | L93: =if(isblank(B93),"",(G93-J93)/J93) -> -0.25570342 | M93: =J93-(J93*0.65) -> 184.1 | N93: =IF(ISBLANK(B93), "", IF(AND(O93 >= 0, O93 <= 7500), "||||", IF(AND(O93 > 7500, O93 <= 30000), "|||", IF(AND(O93 > 30000, O93 <= 600000), "||", IF(O93 > 600000, "|", ""))))) -> ||| | O93: =IFERROR(__xludf.DUMMYFUNCTION("if(ISBLANK(B93),"""",googlefinance(B93,""Marketcap"")/10000000)"),9745.942275) -> 9745.9423
B94: NSE:RELIANCE | C94: =IFERROR(__xludf.DUMMYFUNCTION("if(ISBLANK(B94),"""",GOOGLEFINANCE(B94,""NAME""))"),"Reliance Industries Ltd") -> Reliance Industries Ltd | D94: =if(ISBLANK(B94),"",if(L94<-10%,"B","H")) -> B | E94: =if(ISBLANK(B94),"",if(L94<-15%,"B","H")) -> B | F94: =IF(ISBLANK(B94), "", IF(O94 > 600000, "Mega Cap", IF(O94 > 30000, "Large Cap", IF(O94 > 7500, "Mid Cap", "Small Cap")))) -> Mega Cap | G94: =IFERROR(__xludf.DUMMYFUNCTION("if(ISBLANK(B94),"""",GOOGLEFINANCE(B94,""price""))"),1305.0) -> 1305 | H94: =if(ISBLANK(B94),"",if(ISBLANK(M94),"",if(M94=0,"Extra",if(G94<M94,"Buy","Hold")))) -> Hold | I94: =IFERROR(__xludf.DUMMYFUNCTION("if(ISBLANK(B94),"""",GOOGLEFINANCE(B94,""CHANGEPCT"")/100)"),-0.0123) -> -0.0123 | J94: =IFERROR(__xludf.DUMMYFUNCTION("if(ISBLANK(B94),"""",GOOGLEFINANCE(B94,""HIGH52""))"),1611.8) -> 1611.8 | K94: =IFERROR(__xludf.DUMMYFUNCTION("if(ISBLANK(B94),"""",GOOGLEFINANCE(B94,""LOW52""))"),1253.2) -> 1253.2 | L94: =if(isblank(B94),"",(G94-J94)/J94) -> -0.1903462 | M94: =J94-(J94*0.35) -> 1047.67 | N94: =IF(ISBLANK(B94), "", IF(AND(O94 >= 0, O94 <= 7500), "||||", IF(AND(O94 > 7500, O94 <= 30000), "|||", IF(AND(O94 > 30000, O94 <= 600000), "||", IF(O94 > 600000, "|", ""))))) -> | | O94: =IFERROR(__xludf.DUMMYFUNCTION("if(ISBLANK(B94),"""",googlefinance(B94,""Marketcap"")/10000000)"),1767711.9387287) -> 1767711.9
B95: NSE:RTNINDIA | C95: =IFERROR(__xludf.DUMMYFUNCTION("if(ISBLANK(B95),"""",GOOGLEFINANCE(B95,""NAME""))"),"Rattanindia Enterprises Ltd") -> Rattanindia Enterprises Ltd | D95: =if(ISBLANK(B95),"",if(L95<-10%,"B","H")) -> B | E95: =if(ISBLANK(B95),"",if(L95<-15%,"B","H")) -> B | F95: =IF(ISBLANK(B95), "", IF(O95 > 600000, "Mega Cap", IF(O95 > 30000, "Large Cap", IF(O95 > 7500, "Mid Cap", "Small Cap")))) -> Small Cap | G95: =IFERROR(__xludf.DUMMYFUNCTION("if(ISBLANK(B95),"""",GOOGLEFINANCE(B95,""price""))"),32.9) -> 32.9 | H95: =if(ISBLANK(B95),"",if(ISBLANK(M95),"",if(M95=0,"Extra",if(G95<M95,"Buy","Hold")))) -> Hold | I95: =IFERROR(__xludf.DUMMYFUNCTION("if(ISBLANK(B95),"""",GOOGLEFINANCE(B95,""CHANGEPCT"")/100)"),-0.0126) -> -0.0126 | J95: =IFERROR(__xludf.DUMMYFUNCTION("if(ISBLANK(B95),"""",GOOGLEFINANCE(B95,""HIGH52""))"),69.7) -> 69.7 | K95: =IFERROR(__xludf.DUMMYFUNCTION("if(ISBLANK(B95),"""",GOOGLEFINANCE(B95,""LOW52""))"),24.4) -> 24.4 | L95: =if(isblank(B95),"",(G95-J95)/J95) -> -0.52797704 | M95: =J95-(J95*0.75) -> 17.425 | N95: =IF(ISBLANK(B95), "", IF(AND(O95 >= 0, O95 <= 7500), "||||", IF(AND(O95 > 7500, O95 <= 30000), "|||", IF(AND(O95 > 30000, O95 <= 600000), "||", IF(O95 > 600000, "|", ""))))) -> |||| | O95: =IFERROR(__xludf.DUMMYFUNCTION("if(ISBLANK(B95),"""",googlefinance(B95,""Marketcap"")/10000000)"),4543.1184407) -> 4543.1184
B96: NSE:RVNL | C96: =IFERROR(__xludf.DUMMYFUNCTION("if(ISBLANK(B96),"""",GOOGLEFINANCE(B96,""NAME""))"),"Rail Vikas Nigam Ltd") -> Rail Vikas Nigam Ltd | D96: =if(ISBLANK(B96),"",if(L96<-10%,"B","H")) -> B | E96: =if(ISBLANK(B96),"",if(L96<-15%,"B","H")) -> B | F96: =IF(ISBLANK(B96), "", IF(O96 > 600000, "Mega Cap", IF(O96 > 30000, "Large Cap", IF(O96 > 7500, "Mid Cap", "Small Cap")))) -> Large Cap | G96: =IFERROR(__xludf.DUMMYFUNCTION("if(ISBLANK(B96),"""",GOOGLEFINANCE(B96,""price""))"),232.4) -> 232.4 | H96: =if(ISBLANK(B96),"",if(ISBLANK(M96),"",if(M96=0,"Extra",if(G96<M96,"Buy","Hold")))) -> Hold | I96: =IFERROR(__xludf.DUMMYFUNCTION("if(ISBLANK(B96),"""",GOOGLEFINANCE(B96,""CHANGEPCT"")/100)"),-0.0062) -> -0.0062 | J96: =IFERROR(__xludf.DUMMYFUNCTION("if(ISBLANK(B96),"""",GOOGLEFINANCE(B96,""HIGH52""))"),400.7) -> 400.7 | K96: =IFERROR(__xludf.DUMMYFUNCTION("if(ISBLANK(B96),"""",GOOGLEFINANCE(B96,""LOW52""))"),221.55) -> 221.55 | L96: =if(isblank(B96),"",(G96-J96)/J96) -> -0.42001497 | M96: =J96-(J96*0.5) -> 200.35 | N96: =IF(ISBLANK(B96), "", IF(AND(O96 >= 0, O96 <= 7500), "||||", IF(AND(O96 > 7500, O96 <= 30000), "|||", IF(AND(O96 > 30000, O96 <= 600000), "||", IF(O96 > 600000, "|", ""))))) -> || | O96: =IFERROR(__xludf.DUMMYFUNCTION("if(ISBLANK(B96),"""",googlefinance(B96,""Marketcap"")/10000000)"),48552.045675) -> 48552.046
B97: NSE:SBICARD | C97: =IFERROR(__xludf.DUMMYFUNCTION("if(ISBLANK(B97),"""",GOOGLEFINANCE(B97,""NAME""))"),"SBI Cards and Payment Services Ltd") -> SBI Cards and Payment Services Ltd | D97: =if(ISBLANK(B97),"",if(L97<-10%,"B","H")) -> B | E97: =if(ISBLANK(B97),"",if(L97<-15%,"B","H")) -> B | F97: =IF(ISBLANK(B97), "", IF(O97 > 600000, "Mega Cap", IF(O97 > 30000, "Large Cap", IF(O97 > 7500, "Mid Cap", "Small Cap")))) -> Large Cap | G97: =IFERROR(__xludf.DUMMYFUNCTION("if(ISBLANK(B97),"""",GOOGLEFINANCE(B97,""price""))"),604.4) -> 604.4 | H97: =if(ISBLANK(B97),"",if(ISBLANK(M97),"",if(M97=0,"Extra",if(G97<M97,"Buy","Hold")))) -> Buy | I97: =IFERROR(__xludf.DUMMYFUNCTION("if(ISBLANK(B97),"""",GOOGLEFINANCE(B97,""CHANGEPCT"")/100)"),0.0015) -> 0.0015 | J97: =IFERROR(__xludf.DUMMYFUNCTION("if(ISBLANK(B97),"""",GOOGLEFINANCE(B97,""HIGH52""))"),1004.75) -> 1004.75 | K97: =IFERROR(__xludf.DUMMYFUNCTION("if(ISBLANK(B97),"""",GOOGLEFINANCE(B97,""LOW52""))"),565.45) -> 565.45 | L97: =if(isblank(B97),"",(G97-J97)/J97) -> -0.39845733 | M97: =J97-(J97*0.25) -> 753.5625 | N97: =IF(ISBLANK(B97), "", IF(AND(O97 >= 0, O97 <= 7500), "||||", IF(AND(O97 > 7500, O97 <= 30000), "|||", IF(AND(O97 > 30000, O97 <= 600000), "||", IF(O97 > 600000, "|", ""))))) -> || | O97: =IFERROR(__xludf.DUMMYFUNCTION("if(ISBLANK(B97),"""",googlefinance(B97,""Marketcap"")/10000000)"),57515.5766592) -> 57515.577
B98: NSE:SBIN | C98: =IFERROR(__xludf.DUMMYFUNCTION("if(ISBLANK(B98),"""",GOOGLEFINANCE(B98,""NAME""))"),"State Bank of India") -> State Bank of India | D98: =if(ISBLANK(B98),"",if(L98<-10%,"B","H")) -> B | E98: =if(ISBLANK(B98),"",if(L98<-15%,"B","H")) -> B | F98: =IF(ISBLANK(B98), "", IF(O98 > 600000, "Mega Cap", IF(O98 > 30000, "Large Cap", IF(O98 > 7500, "Mid Cap", "Small Cap")))) -> Mega Cap | G98: =IFERROR(__xludf.DUMMYFUNCTION("if(ISBLANK(B98),"""",GOOGLEFINANCE(B98,""price""))"),1036.2) -> 1036.2 | H98: =if(ISBLANK(B98),"",if(ISBLANK(M98),"",if(M98=0,"Extra",if(G98<M98,"Buy","Hold")))) -> Hold | I98: =IFERROR(__xludf.DUMMYFUNCTION("if(ISBLANK(B98),"""",GOOGLEFINANCE(B98,""CHANGEPCT"")/100)"),-0.0014000000000000002) -> -0.0014 | J98: =IFERROR(__xludf.DUMMYFUNCTION("if(ISBLANK(B98),"""",GOOGLEFINANCE(B98,""HIGH52""))"),1234.7) -> 1234.7 | K98: =IFERROR(__xludf.DUMMYFUNCTION("if(ISBLANK(B98),"""",GOOGLEFINANCE(B98,""LOW52""))"),786.55) -> 786.55 | L98: =if(isblank(B98),"",(G98-J98)/J98) -> -0.1607678 | M98: =J98-(J98*0.3) -> 864.29 | N98: =IF(ISBLANK(B98), "", IF(AND(O98 >= 0, O98 <= 7500), "||||", IF(AND(O98 > 7500, O98 <= 30000), "|||", IF(AND(O98 > 30000, O98 <= 600000), "||", IF(O98 > 600000, "|", ""))))) -> | | O98: =IFERROR(__xludf.DUMMYFUNCTION("if(ISBLANK(B98),"""",googlefinance(B98,""Marketcap"")/10000000)"),957953.4773313) -> 957953.48
B99: NSE:SRF | C99: =IFERROR(__xludf.DUMMYFUNCTION("if(ISBLANK(B99),"""",GOOGLEFINANCE(B99,""NAME""))"),"SRF Ltd") -> SRF Ltd | D99: =if(ISBLANK(B99),"",if(L99<-10%,"B","H")) -> B | E99: =if(ISBLANK(B99),"",if(L99<-15%,"B","H")) -> B | F99: =IF(ISBLANK(B99), "", IF(O99 > 600000, "Mega Cap", IF(O99 > 30000, "Large Cap", IF(O99 > 7500, "Mid Cap", "Small Cap")))) -> Large Cap | G99: =IFERROR(__xludf.DUMMYFUNCTION("if(ISBLANK(B99),"""",GOOGLEFINANCE(B99,""price""))"),2811.3) -> 2811.3 | H99: =if(ISBLANK(B99),"",if(ISBLANK(M99),"",if(M99=0,"Extra",if(G99<M99,"Buy","Hold")))) -> Hold | I99: =IFERROR(__xludf.DUMMYFUNCTION("if(ISBLANK(B99),"""",GOOGLEFINANCE(B99,""CHANGEPCT"")/100)"),-0.0069) -> -0.0069 | J99: =IFERROR(__xludf.DUMMYFUNCTION("if(ISBLANK(B99),"""",GOOGLEFINANCE(B99,""HIGH52""))"),3325.0) -> 3325 | K99: =IFERROR(__xludf.DUMMYFUNCTION("if(ISBLANK(B99),"""",GOOGLEFINANCE(B99,""LOW52""))"),2355.0) -> 2355 | L99: =if(isblank(B99),"",(G99-J99)/J99) -> -0.15449624 | M99: =J99-(J99*0.22) -> 2593.5 | N99: =IF(ISBLANK(B99), "", IF(AND(O99 >= 0, O99 <= 7500), "||||", IF(AND(O99 > 7500, O99 <= 30000), "|||", IF(AND(O99 > 30000, O99 <= 600000), "||", IF(O99 > 600000, "|", ""))))) -> || | O99: =IFERROR(__xludf.DUMMYFUNCTION("if(ISBLANK(B99),"""",googlefinance(B99,""Marketcap"")/10000000)"),83130.63495) -> 83130.635
B100: NSE:SUZLON | C100: =IFERROR(__xludf.DUMMYFUNCTION("if(ISBLANK(B100),"""",GOOGLEFINANCE(B100,""NAME""))"),"Suzlon Energy Ltd") -> Suzlon Energy Ltd | D100: =if(ISBLANK(B100),"",if(L100<-10%,"B","H")) -> B | E100: =if(ISBLANK(B100),"",if(L100<-15%,"B","H")) -> B | F100: =IF(ISBLANK(B100), "", IF(O100 > 600000, "Mega Cap", IF(O100 > 30000, "Large Cap", IF(O100 > 7500, "Mid Cap", "Small Cap")))) -> Large Cap | G100: =IFERROR(__xludf.DUMMYFUNCTION("if(ISBLANK(B100),"""",GOOGLEFINANCE(B100,""price""))"),54.4) -> 54.4 | H100: =if(ISBLANK(B100),"",if(ISBLANK(M100),"",if(M100=0,"Extra",if(G100<M100,"Buy","Hold")))) -> Hold | I100: =IFERROR(__xludf.DUMMYFUNCTION("if(ISBLANK(B100),"""",GOOGLEFINANCE(B100,""CHANGEPCT"")/100)"),-0.019299999999999998) -> -0.0193 | J100: =IFERROR(__xludf.DUMMYFUNCTION("if(ISBLANK(B100),"""",GOOGLEFINANCE(B100,""HIGH52""))"),68.3) -> 68.3 | K100: =IFERROR(__xludf.DUMMYFUNCTION("if(ISBLANK(B100),"""",GOOGLEFINANCE(B100,""LOW52""))"),38.19) -> 38.19 | L100: =if(isblank(B100),"",(G100-J100)/J100) -> -0.20351391 | M100: =J100-(J100*0.45) -> 37.565 | N100: =IF(ISBLANK(B100), "", IF(AND(O100 >= 0, O100 <= 7500), "||||", IF(AND(O100 > 7500, O100 <= 30000), "|||", IF(AND(O100 > 30000, O100 <= 600000), "||", IF(O100 > 600000, "|", ""))))) -> || | O100: =IFERROR(__xludf.DUMMYFUNCTION("if(ISBLANK(B100),"""",googlefinance(B100,""Marketcap"")/10000000)"),74547.0963334) -> 74547.096
B101: NSE:TATACONSUM | C101: =IFERROR(__xludf.DUMMYFUNCTION("if(ISBLANK(B101),"""",GOOGLEFINANCE(B101,""NAME""))"),"Tata Consumer Products Ltd") -> Tata Consumer Products Ltd | D101: =if(ISBLANK(B101),"",if(L101<-10%,"B","H")) -> B | E101: =if(ISBLANK(B101),"",if(L101<-15%,"B","H")) -> H | F101: =IF(ISBLANK(B101), "", IF(O101 > 600000, "Mega Cap", IF(O101 > 30000, "Large Cap", IF(O101 > 7500, "Mid Cap", "Small Cap")))) -> Large Cap | G101: =IFERROR(__xludf.DUMMYFUNCTION("if(ISBLANK(B101),"""",GOOGLEFINANCE(B101,""price""))"),1121.1) -> 1121.1 | H101: =if(ISBLANK(B101),"",if(ISBLANK(M101),"",if(M101=0,"Extra",if(G101<M101,"Buy","Hold")))) -> Hold | I101: =IFERROR(__xludf.DUMMYFUNCTION("if(ISBLANK(B101),"""",GOOGLEFINANCE(B101,""CHANGEPCT"")/100)"),0.0029) -> 0.0029 | J101: =IFERROR(__xludf.DUMMYFUNCTION("if(ISBLANK(B101),"""",GOOGLEFINANCE(B101,""HIGH52""))"),1282.7) -> 1282.7 | K101: =IFERROR(__xludf.DUMMYFUNCTION("if(ISBLANK(B101),"""",GOOGLEFINANCE(B101,""LOW52""))"),1007.2) -> 1007.2 | L101: =if(isblank(B101),"",(G101-J101)/J101) -> -0.12598425 | M101: =J101-(J101*0.3) -> 897.89 | N101: =IF(ISBLANK(B101), "", IF(AND(O101 >= 0, O101 <= 7500), "||||", IF(AND(O101 > 7500, O101 <= 30000), "|||", IF(AND(O101 > 30000, O101 <= 600000), "||", IF(O101 > 600000, "|", ""))))) -> || | O101: =IFERROR(__xludf.DUMMYFUNCTION("if(ISBLANK(B101),"""",googlefinance(B101,""Marketcap"")/10000000)"),110659.1191426) -> 110659.12
B102: NSE:TATAELXSI | C102: =IFERROR(__xludf.DUMMYFUNCTION("if(ISBLANK(B102),"""",GOOGLEFINANCE(B102,""NAME""))"),"Tata Elxsi Ltd") -> Tata Elxsi Ltd | D102: =if(ISBLANK(B102),"",if(L102<-10%,"B","H")) -> B | E102: =if(ISBLANK(B102),"",if(L102<-15%,"B","H")) -> B | F102: =IF(ISBLANK(B102), "", IF(O102 > 600000, "Mega Cap", IF(O102 > 30000, "Large Cap", IF(O102 > 7500, "Mid Cap", "Small Cap")))) -> Mid Cap | G102: =IFERROR(__xludf.DUMMYFUNCTION("if(ISBLANK(B102),"""",GOOGLEFINANCE(B102,""price""))"),3708.0) -> 3708 | H102: =if(ISBLANK(B102),"",if(ISBLANK(M102),"",if(M102=0,"Extra",if(G102<M102,"Buy","Hold")))) -> Hold | I102: =IFERROR(__xludf.DUMMYFUNCTION("if(ISBLANK(B102),"""",GOOGLEFINANCE(B102,""CHANGEPCT"")/100)"),0.013500000000000002) -> 0.0135 | J102: =IFERROR(__xludf.DUMMYFUNCTION("if(ISBLANK(B102),"""",GOOGLEFINANCE(B102,""HIGH52""))"),6439.5) -> 6439.5 | K102: =IFERROR(__xludf.DUMMYFUNCTION("if(ISBLANK(B102),"""",GOOGLEFINANCE(B102,""LOW52""))"),3562.0) -> 3562 | L102: =if(isblank(B102),"",(G102-J102)/J102) -> -0.4241789 | M102: =J102-(J102*0.5) -> 3219.75 | N102: =IF(ISBLANK(B102), "", IF(AND(O102 >= 0, O102 <= 7500), "||||", IF(AND(O102 > 7500, O102 <= 30000), "|||", IF(AND(O102 > 30000, O102 <= 600000), "||", IF(O102 > 600000, "|", ""))))) -> ||| | O102: =IFERROR(__xludf.DUMMYFUNCTION("if(ISBLANK(B102),"""",googlefinance(B102,""Marketcap"")/10000000)"),23100.680556) -> 23100.681
B103: NSE:TATAMOTORS | C103: =IFERROR(__xludf.DUMMYFUNCTION("if(ISBLANK(B103),"""",GOOGLEFINANCE(B103,""NAME""))"),"#N/A") -> #N/A | D103: =if(ISBLANK(B103),"",if(L103<-10%,"B","H")) -> #N/A | E103: =if(ISBLANK(B103),"",if(L103<-15%,"B","H")) -> #N/A | F103: =IF(ISBLANK(B103), "", IF(O103 > 600000, "Mega Cap", IF(O103 > 30000, "Large Cap", IF(O103 > 7500, "Mid Cap", "Small Cap")))) -> #N/A | G103: =IFERROR(__xludf.DUMMYFUNCTION("if(ISBLANK(B103),"""",GOOGLEFINANCE(B103,""price""))"),"#N/A") -> #N/A | H103: =if(ISBLANK(B103),"",if(ISBLANK(M103),"",if(M103=0,"Extra",if(G103<M103,"Buy","Hold")))) -> #N/A | I103: =IFERROR(__xludf.DUMMYFUNCTION("if(ISBLANK(B103),"""",GOOGLEFINANCE(B103,""CHANGEPCT"")/100)"),"#N/A") -> #N/A | J103: =IFERROR(__xludf.DUMMYFUNCTION("if(ISBLANK(B103),"""",GOOGLEFINANCE(B103,""HIGH52""))"),"#N/A") -> #N/A | K103: =IFERROR(__xludf.DUMMYFUNCTION("if(ISBLANK(B103),"""",GOOGLEFINANCE(B103,""LOW52""))"),"#N/A") -> #N/A | L103: =if(isblank(B103),"",(G103-J103)/J103) -> #N/A | M103: =J103-(J103*0.65) -> #N/A | N103: =IF(ISBLANK(B103), "", IF(AND(O103 >= 0, O103 <= 7500), "||||", IF(AND(O103 > 7500, O103 <= 30000), "|||", IF(AND(O103 > 30000, O103 <= 600000), "||", IF(O103 > 600000, "|", ""))))) -> #N/A | O103: =IFERROR(__xludf.DUMMYFUNCTION("if(ISBLANK(B103),"""",googlefinance(B103,""Marketcap"")/10000000)"),"#N/A") -> #N/A
B104: NSE:TATAPOWER | C104: =IFERROR(__xludf.DUMMYFUNCTION("if(ISBLANK(B104),"""",GOOGLEFINANCE(B104,""NAME""))"),"Tata Power Company Ltd") -> Tata Power Company Ltd | D104: =if(ISBLANK(B104),"",if(L104<-10%,"B","H")) -> B | E104: =if(ISBLANK(B104),"",if(L104<-15%,"B","H")) -> B | F104: =IF(ISBLANK(B104), "", IF(O104 > 600000, "Mega Cap", IF(O104 > 30000, "Large Cap", IF(O104 > 7500, "Mid Cap", "Small Cap")))) -> Large Cap | G104: =IFERROR(__xludf.DUMMYFUNCTION("if(ISBLANK(B104),"""",GOOGLEFINANCE(B104,""price""))"),377.1) -> 377.1 | H104: =if(ISBLANK(B104),"",if(ISBLANK(M104),"",if(M104=0,"Extra",if(G104<M104,"Buy","Hold")))) -> Hold | I104: =IFERROR(__xludf.DUMMYFUNCTION("if(ISBLANK(B104),"""",GOOGLEFINANCE(B104,""CHANGEPCT"")/100)"),-0.0012) -> -0.0012 | J104: =IFERROR(__xludf.DUMMYFUNCTION("if(ISBLANK(B104),"""",GOOGLEFINANCE(B104,""HIGH52""))"),464.9) -> 464.9 | K104: =IFERROR(__xludf.DUMMYFUNCTION("if(ISBLANK(B104),"""",GOOGLEFINANCE(B104,""LOW52""))"),342.5) -> 342.5 | L104: =if(isblank(B104),"",(G104-J104)/J104) -> -0.18885782 | M104: =J104-(J104*0.35) -> 302.185 | N104: =IF(ISBLANK(B104), "", IF(AND(O104 >= 0, O104 <= 7500), "||||", IF(AND(O104 > 7500, O104 <= 30000), "|||", IF(AND(O104 > 30000, O104 <= 600000), "||", IF(O104 > 600000, "|", ""))))) -> || | O104: =IFERROR(__xludf.DUMMYFUNCTION("if(ISBLANK(B104),"""",googlefinance(B104,""Marketcap"")/10000000)"),120528.1909805) -> 120528.19
...

Sheet CHECK
A1: =Now() -> 46210.805 | H1: =if(OR((weekday(A1))=1,(weekday(A1))=7),"Market Closed",if(time(hour(now()),minute(now()),second(now()))>TIME(15,30,0),"Market Closed",if((time(hour(now()),minute(now()),second(now()))>TIME(9,15,0)),"Market Open","Market Closed"))) -> Market Closed
A2: BEFORE MARKET
A3: AMERICA | E3: ADRS | J3: ASIA
A4: N.Y & N.DAQ | B4: N.Y & N.DAQ | C4: NASDAQ | D4: N.Y & N.DAQ | J4: NSE | K4: BSE | L4: TOKYO | M4: TAIWAN | N4: HONG KONG | O4: KOREA
A5: Dow Jones | B5: S&500 | C5: Nasdaq | D5: Russell | E5: Infosys | F5: ICICI | G5: WIPRO | H5: HDFC | I5: Dr. Reddy | J5: NIFTY 50 | K5: SENSEX | L5: Nikkei 225 | M5: TWSE | N5: HSI | O5: KOSPI
A6: .DJI | B6: .INX | C6: .IXIC | D6: RUT | E6: INFY | F6: IBN | G6: WIT | H6: HDB | I6: RDY | J6: NIFTY_50 | K6: SENSEX | L6: NI225 | M6: IX0001 | N6: INDEXHANGSENG:HSI | O6: KOSPI
A7: =IFERROR(__xludf.DUMMYFUNCTION("GOOGLEFINANCE(A6)"),53179.02) -> 53179.02 | B7: =IFERROR(__xludf.DUMMYFUNCTION("GOOGLEFINANCE(B6)"),7525.82) -> 7525.82 | C7: =IFERROR(__xludf.DUMMYFUNCTION("GOOGLEFINANCE(C6)"),25928.17) -> 25928.17 | D7: =IFERROR(__xludf.DUMMYFUNCTION("GOOGLEFINANCE(D6)"),3009.54) -> 3009.54 | E7: =IFERROR(__xludf.DUMMYFUNCTION("GOOGLEFINANCE(E6)"),11.36) -> 11.36 | F7: =IFERROR(__xludf.DUMMYFUNCTION("GOOGLEFINANCE(F6)"),29.89) -> 29.89 | G7: =IFERROR(__xludf.DUMMYFUNCTION("GOOGLEFINANCE(G6)"),1.89) -> 1.89 | H7: =IFERROR(__xludf.DUMMYFUNCTION("GOOGLEFINANCE(H6)"),27.29) -> 27.29 | I7: =IFERROR(__xludf.DUMMYFUNCTION("GOOGLEFINANCE(I6)"),14.55) -> 14.55 | J7: =IFERROR(__xludf.DUMMYFUNCTION("GOOGLEFINANCE(J6)"),24398.7) -> 24398.7 | K7: =IFERROR(__xludf.DUMMYFUNCTION("GOOGLEFINANCE(K6)"),78180.72) -> 78180.72 | L7: =IFERROR(__xludf.DUMMYFUNCTION("GOOGLEFINANCE(L6)"),68256.96) -> 68256.96 | M7: =IFERROR(__xludf.DUMMYFUNCTION("GOOGLEFINANCE(M6)"),45479.11) -> 45479.11 | N7: =IFERROR(__xludf.DUMMYFUNCTION("GOOGLEFINANCE(N6)"),23496.89) -> 23496.89 | O7: =IFERROR(__xludf.DUMMYFUNCTION("GOOGLEFINANCE(O6)"),7656.31) -> 7656.31
A8: =IFERROR(__xludf.DUMMYFUNCTION("GOOGLEFINANCE(A6,""Change"")"),123.11) -> 123.11 | B8: =IFERROR(__xludf.DUMMYFUNCTION("GOOGLEFINANCE(B6,""Change"")"),-11.61) -> -11.61 | C8: =IFERROR(__xludf.DUMMYFUNCTION("GOOGLEFINANCE(C6,""Change"")"),-192.99) -> -192.99 | D8: =IFERROR(__xludf.DUMMYFUNCTION("GOOGLEFINANCE(D6,""Change"")"),13.43) -> 13.43 | E8: =IFERROR(__xludf.DUMMYFUNCTION("GOOGLEFINANCE(E6,""Change"")"),0.48) -> 0.48 | F8: =IFERROR(__xludf.DUMMYFUNCTION("GOOGLEFINANCE(F6,""Change"")"),-0.19) -> -0.19 | G8: =IFERROR(__xludf.DUMMYFUNCTION("GOOGLEFINANCE(G6,""Change"")"),0.04) -> 0.04 | H8: =IFERROR(__xludf.DUMMYFUNCTION("GOOGLEFINANCE(H6,""Change"")"),-0.11) -> -0.11 | I8: =IFERROR(__xludf.DUMMYFUNCTION("GOOGLEFINANCE(I6,""Change"")"),0.19) -> 0.19 | J8: =IFERROR(__xludf.DUMMYFUNCTION("GOOGLEFINANCE(J6,""Change"")"),-31.65) -> -31.65 | K8: =IFERROR(__xludf.DUMMYFUNCTION("GOOGLEFINANCE(K6,""Change"")"),-104.35) -> -104.35 | L8: =IFERROR(__xludf.DUMMYFUNCTION("GOOGLEFINANCE(L6,""Change"")"),-1480.73) -> -1480.73 | M8: =IFERROR(__xludf.DUMMYFUNCTION("GOOGLEFINANCE(M6,""Change"")"),-1077.28) -> -1077.28 | N8: =IFERROR(__xludf.DUMMYFUNCTION("GOOGLEFINANCE(N6,""Change"")"),-119.43) -> -119.43 | O8: =IFERROR(__xludf.DUMMYFUNCTION("GOOGLEFINANCE(O6,""Change"")"),-395.02) -> -395.02
A9: =A8/A7 -> 0.0023150107 | B9: =B8/B7 -> -0.001542689 | C9: =C8/C7 -> -0.0074432557 | D9: =D8/D7 -> 0.004462476 | E9: =E8/E7 -> 0.042253521 | F9: =F8/F7 -> -0.006356641 | G9: =G8/G7 -> 0.021164021 | H9: =H8/H7 -> -0.0040307805 | ... O9: =O8/O7 -> -0.051594045
A10: =IFERROR(__xludf.DUMMYFUNCTION("SPARKLINE(INDEX(GOOGLEFINANCE(A6,""Price"",WORKDAY(TODAY(),-252),today()),,2),{""CHARTTYPE"",""COLUMN""})"),"") | B10: =IFERROR(__xludf.DUMMYFUNCTION("SPARKLINE(INDEX(GOOGLEFINANCE(B6,""Price"",WORKDAY(TODAY(),-252),today()),,2),{""CHARTTYPE"",""COLUMN""})"),"") | C10: =IFERROR(__xludf.DUMMYFUNCTION("SPARKLINE(INDEX(GOOGLEFINANCE(C6,""Price"",WORKDAY(TODAY(),-252),today()),,2),{""CHARTTYPE"",""COLUMN""})"),"") | D10: =IFERROR(__xludf.DUMMYFUNCTION("SPARKLINE(INDEX(GOOGLEFINANCE(D6,""Price"",WORKDAY(TODAY(),-252),today()),,2),{""CHARTTYPE"",""COLUMN""})"),"") | E10: =IFERROR(__xludf.DUMMYFUNCTION("SPARKLINE(INDEX(GOOGLEFINANCE(E6,""Price"",WORKDAY(TODAY(),-252),today()),,2),{""CHARTTYPE"",""COLUMN""})"),"") | F10: =IFERROR(__xludf.DUMMYFUNCTION("SPARKLINE(INDEX(GOOGLEFINANCE(F6,""Price"",WORKDAY(TODAY(),-252),today()),,2),{""CHARTTYPE"",""COLUMN""})"),"") | G10: =IFERROR(__xludf.DUMMYFUNCTION("SPARKLINE(INDEX(GOOGLEFINANCE(G6,""Price"",WORKDAY(TODAY(),-252),today()),,2),{""CHARTTYPE"",""COLUMN""})"),"") | H10: =IFERROR(__xludf.DUMMYFUNCTION("SPARKLINE(INDEX(GOOGLEFINANCE(H6,""Price"",WORKDAY(TODAY(),-252),today()),,2),{""CHARTTYPE"",""COLUMN""})"),"") | I10: =IFERROR(__xludf.DUMMYFUNCTION("SPARKLINE(INDEX(GOOGLEFINANCE(I6,""Price"",WORKDAY(TODAY(),-252),today()),,2),{""CHARTTYPE"",""COLUMN""})"),"") | J10: =IFERROR(__xludf.DUMMYFUNCTION("SPARKLINE(INDEX(GOOGLEFINANCE(J6,""Price"",WORKDAY(TODAY(),-252),today()),,2),{""CHARTTYPE"",""COLUMN""})"),"") | K10: =IFERROR(__xludf.DUMMYFUNCTION("SPARKLINE(INDEX(GOOGLEFINANCE(K6,""Price"",WORKDAY(TODAY(),-252),today()),,2),{""CHARTTYPE"",""COLUMN""})"),"") | L10: =IFERROR(__xludf.DUMMYFUNCTION("SPARKLINE(INDEX(GOOGLEFINANCE(L6,""Price"",WORKDAY(TODAY(),-252),today()),,2),{""CHARTTYPE"",""COLUMN""})"),"") | M10: =IFERROR(__xludf.DUMMYFUNCTION("SPARKLINE(INDEX(GOOGLEFINANCE(M6,""Price"",WORKDAY(TODAY(),-252),today()),,2),{""CHARTTYPE"",""COLUMN""})"),"") | N10: =IFERROR(__xludf.DUMMYFUNCTION("SPARKLINE(INDEX(GOOGLEFINANCE(N6,""Price"",WORKDAY(TODAY(),-252),today()),,2),{""CHARTTYPE"",""COLUMN""})"),"") | O10: =IFERROR(__xludf.DUMMYFUNCTION("SPARKLINE(INDEX(GOOGLEFINANCE(O6,""Price"",WORKDAY(TODAY(),-252),today()),,2),{""CHARTTYPE"",""COLUMN""})"),"")
A15: DURING MARKET
A17: Major Stocks
A19: HDFC | B19: ICICI | C19: TCS | D19: Infosys | E19: RELIANCE
A20: HDFCBANK | B20: ICICIBANK | C20: NSE:TCS | D20: INFY | E20: NSE:RELIANCE
A21: =IFERROR(__xludf.DUMMYFUNCTION("GOOGLEFINANCE(A20)"),827.5) -> 827.5 | B21: =IFERROR(__xludf.DUMMYFUNCTION("GOOGLEFINANCE(B20)"),1412.0) -> 1412 | C21: =IFERROR(__xludf.DUMMYFUNCTION("GOOGLEFINANCE(C20)"),2095.9) -> 2095.9 | D21: =IFERROR(__xludf.DUMMYFUNCTION("GOOGLEFINANCE(D20)"),11.36) -> 11.36 | E21: =IFERROR(__xludf.DUMMYFUNCTION("GOOGLEFINANCE(E20)"),1305.0) -> 1305
A22: =IFERROR(__xludf.DUMMYFUNCTION("GOOGLEFINANCE(A20,""Change"")"),-2.35) -> -2.35 | B22: =IFERROR(__xludf.DUMMYFUNCTION("GOOGLEFINANCE(B20,""Change"")"),-14.9) -> -14.9 | C22: =IFERROR(__xludf.DUMMYFUNCTION("GOOGLEFINANCE(C20,""Change"")"),38.3) -> 38.3 | D22: =IFERROR(__xludf.DUMMYFUNCTION("GOOGLEFINANCE(D20,""Change"")"),0.48) -> 0.48 | E22: =IFERROR(__xludf.DUMMYFUNCTION("GOOGLEFINANCE(E20,""Change"")"),-16.3) -> -16.3
A23: =A22/A21 -> -0.0028398792 | B23: =B22/B21 -> -0.010552408 | C23: =C22/C21 -> 0.018273773 | D23: =D22/D21 -> 0.042253521 | E23: =E22/E21 -> -0.012490421
A24: =IFERROR(__xludf.DUMMYFUNCTION("SPARKLINE(INDEX(GOOGLEFINANCE(A20,""Price"",WORKDAY(TODAY(),-252),today()),,2),{""CHARTTYPE"",""COLUMN""})"),"") | B24: =IFERROR(__xludf.DUMMYFUNCTION("SPARKLINE(INDEX(GOOGLEFINANCE(B20,""Price"",WORKDAY(TODAY(),-252),today()),,2),{""CHARTTYPE"",""COLUMN""})"),"") | C24: =IFERROR(__xludf.DUMMYFUNCTION("SPARKLINE(INDEX(GOOGLEFINANCE(C20,""Price"",WORKDAY(TODAY(),-252),today()),,2),{""CHARTTYPE"",""COLUMN""})"),"") | D24: =IFERROR(__xludf.DUMMYFUNCTION("SPARKLINE(INDEX(GOOGLEFINANCE(D20,""Price"",WORKDAY(TODAY(),-252),today()),,2),{""CHARTTYPE"",""COLUMN""})"),"") | E24: =IFERROR(__xludf.DUMMYFUNCTION("SPARKLINE(INDEX(GOOGLEFINANCE(E20,""Price"",WORKDAY(TODAY(),-252),today()),,2),{""CHARTTYPE"",""COLUMN""})"),"")
A29: AFTER MARKET
A31: FII & DII DATA
A32: CRUDE OIL

Sheet Fresh Shares List
A1: =Now() -> 46210.805 | H1: =if(OR((weekday(A1))=1,(weekday(A1))=7),"Market Closed",if(time(hour(now()),minute(now()),second(now()))>TIME(15,30,0),"Market Closed",if((time(hour(now()),minute(now()),second(now()))>TIME(9,15,0)),"Market Open","Market Closed"))) -> Market Closed
A2: Single Stock Analysis | C2: No | D2: TB% | E2: Ticker | G2: Company Name | I2: =IFERROR(__xludf.DUMMYFUNCTION("GOOGLEFINANCE(B3,""Name"")"),"Hindustan Aeronautics Ltd") -> Hindustan Aeronautics Ltd
A3: Stock Overview | B3: NSE:HAL | C3: 1 | D3: =MIN(IFNA(K16:K47,"")) -> -0.70453208 | E3: {=XLOOKUP(D3,K16:K203,A16:A203)} -> BOM:530825 | G3: =IFERROR(__xludf.DUMMYFUNCTION("GOOGLEFINANCE(E3,""NAME"")"),"Daikaffil Chemicals India Ltd") -> Daikaffil Chemicals India Ltd | I3: 12 Month Trend Lines
A4: Stock Price | B4: =IFERROR(__xludf.DUMMYFUNCTION("GOOGLEFINANCE(B3,""price"")"),4401.0) -> 4401 | C4: 2 | D4: =SMALL(IFNA(K16:K47,""),2) -> -0.46011673 | E4: {=XLOOKUP(D4,K16:K204,A16:A204)} -> NSE:ROUTE | G4: =IFERROR(__xludf.DUMMYFUNCTION("GOOGLEFINANCE(E4,""NAME"")"),"Route Mobile Ltd") -> Route Mobile Ltd | I4: =IFERROR(__xludf.DUMMYFUNCTION("SPARKLINE(INDEX(GOOGLEFINANCE(B3,""Price"",WORKDAY(TODAY(),-252),today()),,2),{""CHARTTYPE"",""COLUMN""})"),"")
A5: 52 % Change | B5: =if(isblank(B3),"",(B4-B7)/B7) -> -0.13109576 | C5: 3 | D5: =SMALL(IFNA(K16:K48,""),3) -> -0.45711766 | E5: {=XLOOKUP(D5,K16:K205,A16:A205)} -> NSE:WHIRLPOOL | G5: =IFERROR(__xludf.DUMMYFUNCTION("GOOGLEFINANCE(E5,""NAME"")"),"Whirlpool Of India Ltd") -> Whirlpool Of India Ltd
A6: Signal | B6: =if(B5<-10%,"Buy","Hold") -> Buy | C6: 4 | D6: =SMALL(IFNA(K16:K49,""),4) -> -0.39267016 | E6: {=XLOOKUP(D6,K16:K206,A16:A206)} -> NSE:MHRIL | G6: =IFERROR(__xludf.DUMMYFUNCTION("GOOGLEFINANCE(E6,""NAME"")"),"Mahindra Holidays and Resorts India Ltd") -> Mahindra Holidays and Resorts India Ltd
A7: 52 Week High | B7: =IFERROR(__xludf.DUMMYFUNCTION("GOOGLEFINANCE(B3,""HIGH52"")"),5065.0) -> 5065 | C7: 5 | D7: =SMALL(IFNA(K16:K50,""),5) -> -0.37988281 | E7: {=XLOOKUP(D7,K16:K207,A16:A207)} -> NSE:WESTLIFE | G7: =IFERROR(__xludf.DUMMYFUNCTION("GOOGLEFINANCE(E7,""NAME"")"),"Westlife Foodworld Ltd") -> Westlife Foodworld Ltd
A8: 52 Week Low | B8: =IFERROR(__xludf.DUMMYFUNCTION("GOOGLEFINANCE(B3,""LOW52"")"),3479.1) -> 3479.1 | C8: Days Gainer | E8: =offset(A16:A49,MATCH(MAX(H16:H49),H16:H49,0),0,1) -> NSE:HAL | G8: =(Max(H16:H49)) -> 0.0115
A9: Market Cap (BN) | B9: =IFERROR(__xludf.DUMMYFUNCTION("googlefinance(B3,""Marketcap"")/1000000000"),2942.895888) -> 2942.8959
A10: EPS | B10: =IFERROR(__xludf.DUMMYFUNCTION("GOOGLEFINANCE(B3,""EPS"")"),136.3) -> 136.3 | C10: Days Losser | E10: =offset(A16:A49,MATCH(MIN(H16:H49),H16:H49,0),0,1) -> NSE:DIVISLAB | G10: =(Min(H16:H50)) -> -0.0342
A11: PE | B11: =IFERROR(__xludf.DUMMYFUNCTION("GOOGLEFINANCE(B3,""PE"")"),32.29) -> 32.29
A12: Watchlists
A13: Fresh Shares Check Four Reason*
A15: Ticker | B15: Company Name | C15: 10% TB | D15: 15% TB | E15: Mk Cap | F15: Price | G15: MTB S | H15: % Ch | I15: 52Wk H | J15: 52 Wk L | K15: TB % | L15: MTB | M15: Cap Bar | N15: Mk Cap (In 1 Cr)
A16: BOM:530825 | B16: =IFERROR(__xludf.DUMMYFUNCTION("if(ISBLANK(A16),"""",GOOGLEFINANCE(A16,""NAME""))"),"Daikaffil Chemicals India Ltd") -> Daikaffil Chemicals India Ltd | C16: =if(ISBLANK(A16),"",if(K16<-10%,"Buy","Hold")) -> Buy | D16: =if(ISBLANK(A16),"",if(K16<-15%,"Buy","Hold")) -> Buy | E16: =if(ISBLANK(A16),"",if(N16>1401,"Large cap",if(N16>100,"Mid cap","Small cap"))) -> Small cap | F16: =IFERROR(__xludf.DUMMYFUNCTION("if(ISBLANK(A16),"""",GOOGLEFINANCE(A16,""price""))"),50.2) -> 50.2 | G16: =if(ISBLANK(A16),"",if(L16=0,"Buy@CMP",if(F16<L16,"Buy","Hold"))) -> Buy@CMP | H16: =IFERROR(__xludf.DUMMYFUNCTION("if(ISBLANK(A16),"""",GOOGLEFINANCE(A16,""CHANGEPCT"")/100)"),-0.0199) -> -0.0199 | I16: =IFERROR(__xludf.DUMMYFUNCTION("if(ISBLANK(A16),"""",GOOGLEFINANCE(A16,""HIGH52""))"),169.9) -> 169.9 | J16: =IFERROR(__xludf.DUMMYFUNCTION("if(ISBLANK(A16),"""",GOOGLEFINANCE(A16,""LOW52""))"),28.48) -> 28.48 | K16: =if(isblank(A16),"",(F16-I16)/I16) -> -0.70453208 | L16: 0 | M16: =IF(ISBLANK(A16), "", IF(AND($N16 >= 0, $N16 <= 75), "||||", IF(AND($N16 > 75, $N16 <= 300), "|||", IF(AND($N16 > 300, $N16 <= 6000), "||", IF($N16 > 6000, "|", ""))))) -> |||| | N16: =IFERROR(__xludf.DUMMYFUNCTION("if(ISBLANK(A16),"""",googlefinance(A16,""Marketcap"")/1000000000)"),0.301200004) -> 0.3012
A17: BOM:539837 | B17: =IFERROR(__xludf.DUMMYFUNCTION("if(ISBLANK(A17),"""",GOOGLEFINANCE(A17,""NAME""))"),"Raghav Productivity Enhancers Ltd") -> Raghav Productivity Enhancers Ltd | C17: =if(ISBLANK(A17),"",if(K17<-10%,"Buy","Hold")) -> Hold | D17: =if(ISBLANK(A17),"",if(K17<-15%,"Buy","Hold")) -> Hold | E17: =if(ISBLANK(A17),"",if(N17>1401,"Large cap",if(N17>100,"Mid cap","Small cap"))) -> Small cap | F17: =IFERROR(__xludf.DUMMYFUNCTION("if(ISBLANK(A17),"""",GOOGLEFINANCE(A17,""price""))"),1306.0) -> 1306 | G17: =if(ISBLANK(A17),"",if(L17=0,"Buy@CMP",if(F17<L17,"Buy","Hold"))) -> Buy@CMP | H17: =IFERROR(__xludf.DUMMYFUNCTION("if(ISBLANK(A17),"""",GOOGLEFINANCE(A17,""CHANGEPCT"")/100)"),0.0087) -> 0.0087 | I17: =IFERROR(__xludf.DUMMYFUNCTION("if(ISBLANK(A17),"""",GOOGLEFINANCE(A17,""HIGH52""))"),1319.75) -> 1319.75 | J17: =IFERROR(__xludf.DUMMYFUNCTION("if(ISBLANK(A17),"""",GOOGLEFINANCE(A17,""LOW52""))"),562.9) -> 562.9 | K17: =if(isblank(A17),"",(F17-I17)/I17) -> -0.01041864 | L17: 0 | M17: =IF(ISBLANK(A17), "", IF(AND($N17 >= 0, $N17 <= 75), "||||", IF(AND($N17 > 75, $N17 <= 300), "|||", IF(AND($N17 > 300, $N17 <= 6000), "||", IF($N17 > 6000, "|", ""))))) -> |||| | N17: =IFERROR(__xludf.DUMMYFUNCTION("if(ISBLANK(A17),"""",googlefinance(A17,""Marketcap"")/1000000000)"),60.061319526) -> 60.06132
A18: NSE:AAVAS | B18: =IFERROR(__xludf.DUMMYFUNCTION("if(ISBLANK(A18),"""",GOOGLEFINANCE(A18,""NAME""))"),"Aavas Financiers Ltd") -> Aavas Financiers Ltd | C18: =if(ISBLANK(A18),"",if(K18<-10%,"Buy","Hold")) -> Buy | D18: =if(ISBLANK(A18),"",if(K18<-15%,"Buy","Hold")) -> Buy | E18: =if(ISBLANK(A18),"",if(N18>1401,"Large cap",if(N18>100,"Mid cap","Small cap"))) -> Mid cap | F18: =IFERROR(__xludf.DUMMYFUNCTION("if(ISBLANK(A18),"""",GOOGLEFINANCE(A18,""price""))"),1505.0) -> 1505 | G18: =if(ISBLANK(A18),"",if(L18=0,"Buy@CMP",if(F18<L18,"Buy","Hold"))) -> Buy@CMP | H18: =IFERROR(__xludf.DUMMYFUNCTION("if(ISBLANK(A18),"""",GOOGLEFINANCE(A18,""CHANGEPCT"")/100)"),-0.0059) -> -0.0059 | I18: =IFERROR(__xludf.DUMMYFUNCTION("if(ISBLANK(A18),"""",GOOGLEFINANCE(A18,""HIGH52""))"),2049.0) -> 2049 | J18: =IFERROR(__xludf.DUMMYFUNCTION("if(ISBLANK(A18),"""",GOOGLEFINANCE(A18,""LOW52""))"),1060.4) -> 1060.4 | K18: =if(isblank(A18),"",(F18-I18)/I18) -> -0.26549536 | L18: 0 | M18: =IF(ISBLANK(A18), "", IF(AND($N18 >= 0, $N18 <= 75), "||||", IF(AND($N18 > 75, $N18 <= 300), "|||", IF(AND($N18 > 300, $N18 <= 6000), "||", IF($N18 > 6000, "|", ""))))) -> ||| | N18: =IFERROR(__xludf.DUMMYFUNCTION("if(ISBLANK(A18),"""",googlefinance(A18,""Marketcap"")/1000000000)"),119.761242045) -> 119.76124
A19: NSE:ATUL | B19: =IFERROR(__xludf.DUMMYFUNCTION("if(ISBLANK(A19),"""",GOOGLEFINANCE(A19,""NAME""))"),"Atul Ltd") -> Atul Ltd | C19: =if(ISBLANK(A19),"",if(K19<-10%,"Buy","Hold")) -> Buy | D19: =if(ISBLANK(A19),"",if(K19<-15%,"Buy","Hold")) -> Buy | E19: =if(ISBLANK(A19),"",if(N19>1401,"Large cap",if(N19>100,"Mid cap","Small cap"))) -> Mid cap | F19: =IFERROR(__xludf.DUMMYFUNCTION("if(ISBLANK(A19),"""",GOOGLEFINANCE(A19,""price""))"),6430.0) -> 6430 | G19: =if(ISBLANK(A19),"",if(L19=0,"Buy@CMP",if(F19<L19,"Buy","Hold"))) -> Buy@CMP | H19: =IFERROR(__xludf.DUMMYFUNCTION("if(ISBLANK(A19),"""",GOOGLEFINANCE(A19,""CHANGEPCT"")/100)"),-0.0046) -> -0.0046 | I19: =IFERROR(__xludf.DUMMYFUNCTION("if(ISBLANK(A19),"""",GOOGLEFINANCE(A19,""HIGH52""))"),7788.0) -> 7788 | J19: =IFERROR(__xludf.DUMMYFUNCTION("if(ISBLANK(A19),"""",GOOGLEFINANCE(A19,""LOW52""))"),5560.5) -> 5560.5 | K19: =if(isblank(A19),"",(F19-I19)/I19) -> -0.17437083 | L19: 0 | M19: =IF(ISBLANK(A19), "", IF(AND($N19 >= 0, $N19 <= 75), "||||", IF(AND($N19 > 75, $N19 <= 300), "|||", IF(AND($N19 > 300, $N19 <= 6000), "||", IF($N19 > 6000, "|", ""))))) -> ||| | N19: =IFERROR(__xludf.DUMMYFUNCTION("if(ISBLANK(A19),"""",googlefinance(A19,""Marketcap"")/1000000000)"),189.3105168) -> 189.31052
A20: NSE:AWL | B20: =IFERROR(__xludf.DUMMYFUNCTION("if(ISBLANK(A20),"""",GOOGLEFINANCE(A20,""NAME""))"),"AWL Agri Business Ltd") -> AWL Agri Business Ltd | C20: =if(ISBLANK(A20),"",if(K20<-10%,"Buy","Hold")) -> Buy | D20: =if(ISBLANK(A20),"",if(K20<-15%,"Buy","Hold")) -> Buy | E20: =if(ISBLANK(A20),"",if(N20>1401,"Large cap",if(N20>100,"Mid cap","Small cap"))) -> Mid cap | F20: =IFERROR(__xludf.DUMMYFUNCTION("if(ISBLANK(A20),"""",GOOGLEFINANCE(A20,""price""))"),185.98) -> 185.98 | G20: =if(ISBLANK(A20),"",if(L20=0,"Buy@CMP",if(F20<L20,"Buy","Hold"))) -> Buy@CMP | H20: =IFERROR(__xludf.DUMMYFUNCTION("if(ISBLANK(A20),"""",GOOGLEFINANCE(A20,""CHANGEPCT"")/100)"),-0.025099999999999997) -> -0.0251 | I20: =IFERROR(__xludf.DUMMYFUNCTION("if(ISBLANK(A20),"""",GOOGLEFINANCE(A20,""HIGH52""))"),286.0) -> 286 | J20: =IFERROR(__xludf.DUMMYFUNCTION("if(ISBLANK(A20),"""",GOOGLEFINANCE(A20,""LOW52""))"),171.19) -> 171.19 | K20: =if(isblank(A20),"",(F20-I20)/I20) -> -0.34972028 | L20: 0 | M20: =IF(ISBLANK(A20), "", IF(AND($N20 >= 0, $N20 <= 75), "||||", IF(AND($N20 > 75, $N20 <= 300), "|||", IF(AND($N20 > 300, $N20 <= 6000), "||", IF($N20 > 6000, "|", ""))))) -> ||| | N20: =IFERROR(__xludf.DUMMYFUNCTION("if(ISBLANK(A20),"""",googlefinance(A20,""Marketcap"")/1000000000)"),240.421754645) -> 240.42175
A21: NSE:BRITANNIA | B21: =IFERROR(__xludf.DUMMYFUNCTION("if(ISBLANK(A21),"""",GOOGLEFINANCE(A21,""NAME""))"),"Britannia Industries Ltd") -> Britannia Industries Ltd | C21: =if(ISBLANK(A21),"",if(K21<-10%,"Buy","Hold")) -> Buy | D21: =if(ISBLANK(A21),"",if(K21<-15%,"Buy","Hold")) -> Hold | E21: =if(ISBLANK(A21),"",if(N21>1401,"Large cap",if(N21>100,"Mid cap","Small cap"))) -> Mid cap | F21: =IFERROR(__xludf.DUMMYFUNCTION("if(ISBLANK(A21),"""",GOOGLEFINANCE(A21,""price""))"),5452.0) -> 5452 | G21: =if(ISBLANK(A21),"",if(L21=0,"Buy@CMP",if(F21<L21,"Buy","Hold"))) -> Buy@CMP | H21: =IFERROR(__xludf.DUMMYFUNCTION("if(ISBLANK(A21),"""",GOOGLEFINANCE(A21,""CHANGEPCT"")/100)"),-5.0E-4) -> -0.0005 | I21: =IFERROR(__xludf.DUMMYFUNCTION("if(ISBLANK(A21),"""",GOOGLEFINANCE(A21,""HIGH52""))"),6336.0) -> 6336 | J21: =IFERROR(__xludf.DUMMYFUNCTION("if(ISBLANK(A21),"""",GOOGLEFINANCE(A21,""LOW52""))"),5035.0) -> 5035 | K21: =if(isblank(A21),"",(F21-I21)/I21) -> -0.1395202 | L21: 0 | M21: =IF(ISBLANK(A21), "", IF(AND($N21 >= 0, $N21 <= 75), "||||", IF(AND($N21 > 75, $N21 <= 300), "|||", IF(AND($N21 > 300, $N21 <= 6000), "||", IF($N21 > 6000, "|", ""))))) -> || | N21: =IFERROR(__xludf.DUMMYFUNCTION("if(ISBLANK(A21),"""",googlefinance(A21,""Marketcap"")/1000000000)"),1313.2139716) -> 1313.214
A22: NSE:CHAMBLFERT | B22: =IFERROR(__xludf.DUMMYFUNCTION("if(ISBLANK(A22),"""",GOOGLEFINANCE(A22,""NAME""))"),"Chambal Fertilisers and Chemicals Ltd") -> Chambal Fertilisers and Chemicals Ltd | C22: =if(ISBLANK(A22),"",if(K22<-10%,"Buy","Hold")) -> Buy | D22: =if(ISBLANK(A22),"",if(K22<-15%,"Buy","Hold")) -> Buy | E22: =if(ISBLANK(A22),"",if(N22>1401,"Large cap",if(N22>100,"Mid cap","Small cap"))) -> Mid cap | F22: =IFERROR(__xludf.DUMMYFUNCTION("if(ISBLANK(A22),"""",GOOGLEFINANCE(A22,""price""))"),464.45) -> 464.45 | G22: =if(ISBLANK(A22),"",if(L22=0,"Buy@CMP",if(F22<L22,"Buy","Hold"))) -> Buy@CMP | H22: =IFERROR(__xludf.DUMMYFUNCTION("if(ISBLANK(A22),"""",GOOGLEFINANCE(A22,""CHANGEPCT"")/100)"),-0.024399999999999998) -> -0.0244 | I22: =IFERROR(__xludf.DUMMYFUNCTION("if(ISBLANK(A22),"""",GOOGLEFINANCE(A22,""HIGH52""))"),580.7) -> 580.7 | J22: =IFERROR(__xludf.DUMMYFUNCTION("if(ISBLANK(A22),"""",GOOGLEFINANCE(A22,""LOW52""))"),399.75) -> 399.75 | K22: =if(isblank(A22),"",(F22-I22)/I22) -> -0.20018943 | L22: 0 | M22: =IF(ISBLANK(A22), "", IF(AND($N22 >= 0, $N22 <= 75), "||||", IF(AND($N22 > 75, $N22 <= 300), "|||", IF(AND($N22 > 300, $N22 <= 6000), "||", IF($N22 > 6000, "|", ""))))) -> ||| | N22: =IFERROR(__xludf.DUMMYFUNCTION("if(ISBLANK(A22),"""",googlefinance(A22,""Marketcap"")/1000000000)"),186.08291918) -> 186.08292
A23: NSE:CUMMINSIND | B23: =IFERROR(__xludf.DUMMYFUNCTION("if(ISBLANK(A23),"""",GOOGLEFINANCE(A23,""NAME""))"),"Cummins India Ltd") -> Cummins India Ltd | C23: =if(ISBLANK(A23),"",if(K23<-10%,"Buy","Hold")) -> Buy | D23: =if(ISBLANK(A23),"",if(K23<-15%,"Buy","Hold")) -> Hold | E23: =if(ISBLANK(A23),"",if(N23>1401,"Large cap",if(N23>100,"Mid cap","Small cap"))) -> Large cap | F23: =IFERROR(__xludf.DUMMYFUNCTION("if(ISBLANK(A23),"""",GOOGLEFINANCE(A23,""price""))"),5465.0) -> 5465 | G23: =if(ISBLANK(A23),"",if(L23=0,"Buy@CMP",if(F23<L23,"Buy","Hold"))) -> Buy@CMP | H23: =IFERROR(__xludf.DUMMYFUNCTION("if(ISBLANK(A23),"""",GOOGLEFINANCE(A23,""CHANGEPCT"")/100)"),-0.0203) -> -0.0203 | I23: =IFERROR(__xludf.DUMMYFUNCTION("if(ISBLANK(A23),"""",GOOGLEFINANCE(A23,""HIGH52""))"),6100.0) -> 6100 | J23: =IFERROR(__xludf.DUMMYFUNCTION("if(ISBLANK(A23),"""",GOOGLEFINANCE(A23,""LOW52""))"),3330.3) -> 3330.3 | K23: =if(isblank(A23),"",(F23-I23)/I23) -> -0.10409836 | L23: 0 | M23: =IF(ISBLANK(A23), "", IF(AND($N23 >= 0, $N23 <= 75), "||||", IF(AND($N23 > 75, $N23 <= 300), "|||", IF(AND($N23 > 300, $N23 <= 6000), "||", IF($N23 > 6000, "|", ""))))) -> || | N23: =IFERROR(__xludf.DUMMYFUNCTION("if(ISBLANK(A23),"""",googlefinance(A23,""Marketcap"")/1000000000)"),1514.898) -> 1514.898
A24: NSE:DCMNVL | B24: =IFERROR(__xludf.DUMMYFUNCTION("if(ISBLANK(A24),"""",GOOGLEFINANCE(A24,""NAME""))"),"DCM Nouvelle Ltd") -> DCM Nouvelle Ltd | C24: =if(ISBLANK(A24),"",if(K24<-10%,"Buy","Hold")) -> Buy | D24: =if(ISBLANK(A24),"",if(K24<-15%,"Buy","Hold")) -> Buy | E24: =if(ISBLANK(A24),"",if(N24>1401,"Large cap",if(N24>100,"Mid cap","Small cap"))) -> Small cap | F24: =IFERROR(__xludf.DUMMYFUNCTION("if(ISBLANK(A24),"""",GOOGLEFINANCE(A24,""price""))"),148.2) -> 148.2 | G24: =if(ISBLANK(A24),"",if(L24=0,"Buy@CMP",if(F24<L24,"Buy","Hold"))) -> Buy@CMP | H24: =IFERROR(__xludf.DUMMYFUNCTION("if(ISBLANK(A24),"""",GOOGLEFINANCE(A24,""CHANGEPCT"")/100)"),-0.0342) -> -0.0342 | I24: =IFERROR(__xludf.DUMMYFUNCTION("if(ISBLANK(A24),"""",GOOGLEFINANCE(A24,""HIGH52""))"),203.8) -> 203.8 | J24: =IFERROR(__xludf.DUMMYFUNCTION("if(ISBLANK(A24),"""",GOOGLEFINANCE(A24,""LOW52""))"),95.6) -> 95.6 | K24: =if(isblank(A24),"",(F24-I24)/I24) -> -0.27281649 | L24: 0 | M24: =IF(ISBLANK(A24), "", IF(AND($N24 >= 0, $N24 <= 75), "||||", IF(AND($N24 > 75, $N24 <= 300), "|||", IF(AND($N24 > 300, $N24 <= 6000), "||", IF($N24 > 6000, "|", ""))))) -> |||| | N24: =IFERROR(__xludf.DUMMYFUNCTION("if(ISBLANK(A24),"""",googlefinance(A24,""Marketcap"")/1000000000)"),2.739835945) -> 2.7398359
A25: NSE:DIVISLAB | B25: =IFERROR(__xludf.DUMMYFUNCTION("if(ISBLANK(A25),"""",GOOGLEFINANCE(A25,""NAME""))"),"Divi's Laboratories Ltd") -> Divi's Laboratories Ltd | C25: =if(ISBLANK(A25),"",if(K25<-10%,"Buy","Hold")) -> Hold | D25: =if(ISBLANK(A25),"",if(K25<-15%,"Buy","Hold")) -> Hold | E25: =if(ISBLANK(A25),"",if(N25>1401,"Large cap",if(N25>100,"Mid cap","Small cap"))) -> Large cap | F25: =IFERROR(__xludf.DUMMYFUNCTION("if(ISBLANK(A25),"""",GOOGLEFINANCE(A25,""price""))"),6760.0) -> 6760 | G25: =if(ISBLANK(A25),"",if(L25=0,"Buy@CMP",if(F25<L25,"Buy","Hold"))) -> Buy@CMP | H25: =IFERROR(__xludf.DUMMYFUNCTION("if(ISBLANK(A25),"""",GOOGLEFINANCE(A25,""CHANGEPCT"")/100)"),-0.014199999999999999) -> -0.0142 | I25: =IFERROR(__xludf.DUMMYFUNCTION("if(ISBLANK(A25),"""",GOOGLEFINANCE(A25,""HIGH52""))"),7071.5) -> 7071.5 | J25: =IFERROR(__xludf.DUMMYFUNCTION("if(ISBLANK(A25),"""",GOOGLEFINANCE(A25,""LOW52""))"),5636.5) -> 5636.5 | K25: =if(isblank(A25),"",(F25-I25)/I25) -> -0.04405006 | L25: 0 | M25: =IF(ISBLANK(A25), "", IF(AND($N25 >= 0, $N25 <= 75), "||||", IF(AND($N25 > 75, $N25 <= 300), "|||", IF(AND($N25 > 300, $N25 <= 6000), "||", IF($N25 > 6000, "|", ""))))) -> || | N25: =IFERROR(__xludf.DUMMYFUNCTION("if(ISBLANK(A25),"""",googlefinance(A25,""Marketcap"")/1000000000)"),1803.676043028) -> 1803.676
A26: NSE:ETHOSLTD | B26: =IFERROR(__xludf.DUMMYFUNCTION("if(ISBLANK(A26),"""",GOOGLEFINANCE(A26,""NAME""))"),"Ethos Ltd") -> Ethos Ltd | C26: =if(ISBLANK(A26),"",if(K26<-10%,"Buy","Hold")) -> Buy | D26: =if(ISBLANK(A26),"",if(K26<-15%,"Buy","Hold")) -> Buy | E26: =if(ISBLANK(A26),"",if(N26>1401,"Large cap",if(N26>100,"Mid cap","Small cap"))) -> Small cap | F26: =IFERROR(__xludf.DUMMYFUNCTION("if(ISBLANK(A26),"""",GOOGLEFINANCE(A26,""price""))"),2503.2) -> 2503.2 | G26: =if(ISBLANK(A26),"",if(L26=0,"Buy@CMP",if(F26<L26,"Buy","Hold"))) -> Buy@CMP | H26: =IFERROR(__xludf.DUMMYFUNCTION("if(ISBLANK(A26),"""",GOOGLEFINANCE(A26,""CHANGEPCT"")/100)"),-0.0134) -> -0.0134 | I26: =IFERROR(__xludf.DUMMYFUNCTION("if(ISBLANK(A26),"""",GOOGLEFINANCE(A26,""HIGH52""))"),3245.9) -> 3245.9 | J26: =IFERROR(__xludf.DUMMYFUNCTION("if(ISBLANK(A26),"""",GOOGLEFINANCE(A26,""LOW52""))"),1919.4) -> 1919.4 | K26: =if(isblank(A26),"",(F26-I26)/I26) -> -0.22881173 | L26: 0 | M26: =IF(ISBLANK(A26), "", IF(AND($N26 >= 0, $N26 <= 75), "||||", IF(AND($N26 > 75, $N26 <= 300), "|||", IF(AND($N26 > 300, $N26 <= 6000), "||", IF($N26 > 6000, "|", ""))))) -> |||| | N26: =IFERROR(__xludf.DUMMYFUNCTION("if(ISBLANK(A26),"""",googlefinance(A26,""Marketcap"")/1000000000)"),66.979848301) -> 66.979848
A27: NSE:GILLETTE | B27: =IFERROR(__xludf.DUMMYFUNCTION("if(ISBLANK(A27),"""",GOOGLEFINANCE(A27,""NAME""))"),"Gillette India Ltd") -> Gillette India Ltd | C27: =if(ISBLANK(A27),"",if(K27<-10%,"Buy","Hold")) -> Buy | D27: =if(ISBLANK(A27),"",if(K27<-15%,"Buy","Hold")) -> Buy | E27: =if(ISBLANK(A27),"",if(N27>1401,"Large cap",if(N27>100,"Mid cap","Small cap"))) -> Mid cap | F27: =IFERROR(__xludf.DUMMYFUNCTION("if(ISBLANK(A27),"""",GOOGLEFINANCE(A27,""price""))"),7862.0) -> 7862 | G27: =if(ISBLANK(A27),"",if(L27=0,"Buy@CMP",if(F27<L27,"Buy","Hold"))) -> Buy@CMP | H27: =IFERROR(__xludf.DUMMYFUNCTION("if(ISBLANK(A27),"""",GOOGLEFINANCE(A27,""CHANGEPCT"")/100)"),0.0115) -> 0.0115 | I27: =IFERROR(__xludf.DUMMYFUNCTION("if(ISBLANK(A27),"""",GOOGLEFINANCE(A27,""HIGH52""))"),11500.0) -> 11500 | J27: =IFERROR(__xludf.DUMMYFUNCTION("if(ISBLANK(A27),"""",GOOGLEFINANCE(A27,""LOW52""))"),7206.0) -> 7206 | K27: =if(isblank(A27),"",(F27-I27)/I27) -> -0.31634783 | L27: 0 | M27: =IF(ISBLANK(A27), "", IF(AND($N27 >= 0, $N27 <= 75), "||||", IF(AND($N27 > 75, $N27 <= 300), "|||", IF(AND($N27 > 300, $N27 <= 6000), "||", IF($N27 > 6000, "|", ""))))) -> ||| | N27: =IFERROR(__xludf.DUMMYFUNCTION("if(ISBLANK(A27),"""",googlefinance(A27,""Marketcap"")/1000000000)"),256.18492102) -> 256.18492
A28: NSE:HAL | B28: =IFERROR(__xludf.DUMMYFUNCTION("if(ISBLANK(A28),"""",GOOGLEFINANCE(A28,""NAME""))"),"Hindustan Aeronautics Ltd") -> Hindustan Aeronautics Ltd | C28: =if(ISBLANK(A28),"",if(K28<-10%,"Buy","Hold")) -> Buy | D28: =if(ISBLANK(A28),"",if(K28<-15%,"Buy","Hold")) -> Hold | E28: =if(ISBLANK(A28),"",if(N28>1401,"Large cap",if(N28>100,"Mid cap","Small cap"))) -> Large cap | F28: =IFERROR(__xludf.DUMMYFUNCTION("if(ISBLANK(A28),"""",GOOGLEFINANCE(A28,""price""))"),4401.0) -> 4401 | G28: =if(ISBLANK(A28),"",if(L28=0,"Buy@CMP",if(F28<L28,"Buy","Hold"))) -> Buy@CMP | H28: =IFERROR(__xludf.DUMMYFUNCTION("if(ISBLANK(A28),"""",GOOGLEFINANCE(A28,""CHANGEPCT"")/100)"),-0.0089) -> -0.0089 | I28: =IFERROR(__xludf.DUMMYFUNCTION("if(ISBLANK(A28),"""",GOOGLEFINANCE(A28,""HIGH52""))"),5065.0) -> 5065 | J28: =IFERROR(__xludf.DUMMYFUNCTION("if(ISBLANK(A28),"""",GOOGLEFINANCE(A28,""LOW52""))"),3479.1) -> 3479.1 | K28: =if(isblank(A28),"",(F28-I28)/I28) -> -0.13109576 | L28: 0 | M28: =IF(ISBLANK(A28), "", IF(AND($N28 >= 0, $N28 <= 75), "||||", IF(AND($N28 > 75, $N28 <= 300), "|||", IF(AND($N28 > 300, $N28 <= 6000), "||", IF($N28 > 6000, "|", ""))))) -> || | N28: =IFERROR(__xludf.DUMMYFUNCTION("if(ISBLANK(A28),"""",googlefinance(A28,""Marketcap"")/1000000000)"),2942.895888) -> 2942.8959
A29: NSE:HINDWAREAP | B29: =IFERROR(__xludf.DUMMYFUNCTION("if(ISBLANK(A29),"""",GOOGLEFINANCE(A29,""NAME""))"),"Hindware Home Innovation Ltd") -> Hindware Home Innovation Ltd | C29: =if(ISBLANK(A29),"",if(K29<-10%,"Buy","Hold")) -> Buy | D29: =if(ISBLANK(A29),"",if(K29<-15%,"Buy","Hold")) -> Buy | E29: =if(ISBLANK(A29),"",if(N29>1401,"Large cap",if(N29>100,"Mid cap","Small cap"))) -> Small cap | F29: =IFERROR(__xludf.DUMMYFUNCTION("if(ISBLANK(A29),"""",GOOGLEFINANCE(A29,""price""))"),249.95) -> 249.95 | G29: =if(ISBLANK(A29),"",if(L29=0,"Buy@CMP",if(F29<L29,"Buy","Hold"))) -> Buy@CMP | H29: =IFERROR(__xludf.DUMMYFUNCTION("if(ISBLANK(A29),"""",GOOGLEFINANCE(A29,""CHANGEPCT"")/100)"),0.0) -> 0 | I29: =IFERROR(__xludf.DUMMYFUNCTION("if(ISBLANK(A29),"""",GOOGLEFINANCE(A29,""HIGH52""))"),392.7) -> 392.7 | J29: =IFERROR(__xludf.DUMMYFUNCTION("if(ISBLANK(A29),"""",GOOGLEFINANCE(A29,""LOW52""))"),170.5) -> 170.5 | K29: =if(isblank(A29),"",(F29-I29)/I29) -> -0.36350904 | L29: 0 | M29: =IF(ISBLANK(A29), "", IF(AND($N29 >= 0, $N29 <= 75), "||||", IF(AND($N29 > 75, $N29 <= 300), "|||", IF(AND($N29 > 300, $N29 <= 6000), "||", IF($N29 > 6000, "|", ""))))) -> |||| | N29: =IFERROR(__xludf.DUMMYFUNCTION("if(ISBLANK(A29),"""",googlefinance(A29,""Marketcap"")/1000000000)"),20.907409926) -> 20.90741
A30: NSE:MEGASTAR | B30: =IFERROR(__xludf.DUMMYFUNCTION("if(ISBLANK(A30),"""",GOOGLEFINANCE(A30,""NAME""))"),"Megastar Foods Ltd") -> Megastar Foods Ltd | C30: =if(ISBLANK(A30),"",if(K30<-10%,"Buy","Hold")) -> Hold | D30: =if(ISBLANK(A30),"",if(K30<-15%,"Buy","Hold")) -> Hold | E30: =if(ISBLANK(A30),"",if(N30>1401,"Large cap",if(N30>100,"Mid cap","Small cap"))) -> Small cap | F30: =IFERROR(__xludf.DUMMYFUNCTION("if(ISBLANK(A30),"""",GOOGLEFINANCE(A30,""price""))"),369.0) -> 369 | G30: =if(ISBLANK(A30),"",if(L30=0,"Buy@CMP",if(F30<L30,"Buy","Hold"))) -> Buy@CMP | H30: =IFERROR(__xludf.DUMMYFUNCTION("if(ISBLANK(A30),"""",GOOGLEFINANCE(A30,""CHANGEPCT"")/100)"),0.0033) -> 0.0033 | I30: =IFERROR(__xludf.DUMMYFUNCTION("if(ISBLANK(A30),"""",GOOGLEFINANCE(A30,""HIGH52""))"),377.0) -> 377 | J30: =IFERROR(__xludf.DUMMYFUNCTION("if(ISBLANK(A30),"""",GOOGLEFINANCE(A30,""LOW52""))"),203.0) -> 203 | K30: =if(isblank(A30),"",(F30-I30)/I30) -> -0.021220159 | L30: 0 | M30: =IF(ISBLANK(A30), "", IF(AND($N30 >= 0, $N30 <= 75), "||||", IF(AND($N30 > 75, $N30 <= 300), "|||", IF(AND($N30 > 300, $N30 <= 6000), "||", IF($N30 > 6000, "|", ""))))) -> |||| | N30: =IFERROR(__xludf.DUMMYFUNCTION("if(ISBLANK(A30),"""",googlefinance(A30,""Marketcap"")/1000000000)"),4.1673753) -> 4.1673753
A31: NSE:METROPOLIS | B31: =IFERROR(__xludf.DUMMYFUNCTION("if(ISBLANK(A31),"""",GOOGLEFINANCE(A31,""NAME""))"),"Metropolis Healthcare Ltd") -> Metropolis Healthcare Ltd | C31: =if(ISBLANK(A31),"",if(K31<-10%,"Buy","Hold")) -> Hold | D31: =if(ISBLANK(A31),"",if(K31<-15%,"Buy","Hold")) -> Hold | E31: =if(ISBLANK(A31),"",if(N31>1401,"Large cap",if(N31>100,"Mid cap","Small cap"))) -> Mid cap | F31: =IFERROR(__xludf.DUMMYFUNCTION("if(ISBLANK(A31),"""",GOOGLEFINANCE(A31,""price""))"),563.6) -> 563.6 | G31: =if(ISBLANK(A31),"",if(L31=0,"Buy@CMP",if(F31<L31,"Buy","Hold"))) -> Buy@CMP | H31: =IFERROR(__xludf.DUMMYFUNCTION("if(ISBLANK(A31),"""",GOOGLEFINANCE(A31,""CHANGEPCT"")/100)"),-0.0173) -> -0.0173 | I31: =IFERROR(__xludf.DUMMYFUNCTION("if(ISBLANK(A31),"""",GOOGLEFINANCE(A31,""HIGH52""))"),600.0) -> 600 | J31: =IFERROR(__xludf.DUMMYFUNCTION("if(ISBLANK(A31),"""",GOOGLEFINANCE(A31,""LOW52""))"),412.25) -> 412.25 | K31: =if(isblank(A31),"",(F31-I31)/I31) -> -0.060666667 | L31: 0 | M31: =IF(ISBLANK(A31), "", IF(AND($N31 >= 0, $N31 <= 75), "||||", IF(AND($N31 > 75, $N31 <= 300), "|||", IF(AND($N31 > 300, $N31 <= 6000), "||", IF($N31 > 6000, "|", ""))))) -> ||| | N31: =IFERROR(__xludf.DUMMYFUNCTION("if(ISBLANK(A31),"""",googlefinance(A31,""Marketcap"")/1000000000)"),116.852310138) -> 116.85231
A32: NSE:MHRIL | B32: =IFERROR(__xludf.DUMMYFUNCTION("if(ISBLANK(A32),"""",GOOGLEFINANCE(A32,""NAME""))"),"Mahindra Holidays and Resorts India Ltd") -> Mahindra Holidays and Resorts India Ltd | C32: =if(ISBLANK(A32),"",if(K32<-10%,"Buy","Hold")) -> Buy | D32: =if(ISBLANK(A32),"",if(K32<-15%,"Buy","Hold")) -> Buy | E32: =if(ISBLANK(A32),"",if(N32>1401,"Large cap",if(N32>100,"Mid cap","Small cap"))) -> Small cap | F32: =IFERROR(__xludf.DUMMYFUNCTION("if(ISBLANK(A32),"""",GOOGLEFINANCE(A32,""price""))"),232.0) -> 232 | G32: =if(ISBLANK(A32),"",if(L32=0,"Buy@CMP",if(F32<L32,"Buy","Hold"))) -> Buy@CMP | H32: =IFERROR(__xludf.DUMMYFUNCTION("if(ISBLANK(A32),"""",GOOGLEFINANCE(A32,""CHANGEPCT"")/100)"),-0.0022) -> -0.0022 | I32: =IFERROR(__xludf.DUMMYFUNCTION("if(ISBLANK(A32),"""",GOOGLEFINANCE(A32,""HIGH52""))"),382.0) -> 382 | J32: =IFERROR(__xludf.DUMMYFUNCTION("if(ISBLANK(A32),"""",GOOGLEFINANCE(A32,""LOW52""))"),208.22) -> 208.22 | K32: =if(isblank(A32),"",(F32-I32)/I32) -> -0.39267016 | L32: 0 | M32: =IF(ISBLANK(A32), "", IF(AND($N32 >= 0, $N32 <= 75), "||||", IF(AND($N32 > 75, $N32 <= 300), "|||", IF(AND($N32 > 300, $N32 <= 6000), "||", IF($N32 > 6000, "|", ""))))) -> |||| | N32: =IFERROR(__xludf.DUMMYFUNCTION("if(ISBLANK(A32),"""",googlefinance(A32,""Marketcap"")/1000000000)"),46.791964) -> 46.791964
A33: NSE:MSUMI | B33: =IFERROR(__xludf.DUMMYFUNCTION("if(ISBLANK(A33),"""",GOOGLEFINANCE(A33,""NAME""))"),"Motherson Sumi Wiring India Ltd") -> Motherson Sumi Wiring India Ltd | C33: =if(ISBLANK(A33),"",if(K33<-10%,"Buy","Hold")) -> Buy | D33: =if(ISBLANK(A33),"",if(K33<-15%,"Buy","Hold")) -> Buy | E33: =if(ISBLANK(A33),"",if(N33>1401,"Large cap",if(N33>100,"Mid cap","Small cap"))) -> Mid cap | F33: =IFERROR(__xludf.DUMMYFUNCTION("if(ISBLANK(A33),"""",GOOGLEFINANCE(A33,""price""))"),41.35) -> 41.35 | G33: =if(ISBLANK(A33),"",if(L33=0,"Buy@CMP",if(F33<L33,"Buy","Hold"))) -> Buy@CMP | H33: =IFERROR(__xludf.DUMMYFUNCTION("if(ISBLANK(A33),"""",GOOGLEFINANCE(A33,""CHANGEPCT"")/100)"),0.0076) -> 0.0076 | I33: =IFERROR(__xludf.DUMMYFUNCTION("if(ISBLANK(A33),"""",GOOGLEFINANCE(A33,""HIGH52""))"),53.59) -> 53.59 | J33: =IFERROR(__xludf.DUMMYFUNCTION("if(ISBLANK(A33),"""",GOOGLEFINANCE(A33,""LOW52""))"),35.7) -> 35.7 | K33: =if(isblank(A33),"",(F33-I33)/I33) -> -0.22840082 | L33: 0 | M33: =IF(ISBLANK(A33), "", IF(AND($N33 >= 0, $N33 <= 75), "||||", IF(AND($N33 > 75, $N33 <= 300), "|||", IF(AND($N33 > 300, $N33 <= 6000), "||", IF($N33 > 6000, "|", ""))))) -> ||| | N33: =IFERROR(__xludf.DUMMYFUNCTION("if(ISBLANK(A33),"""",googlefinance(A33,""Marketcap"")/1000000000)"),182.547512077) -> 182.54751
A34: NSE:NHPC | B34: =IFERROR(__xludf.DUMMYFUNCTION("if(ISBLANK(A34),"""",GOOGLEFINANCE(A34,""NAME""))"),"NHPC Ltd") -> NHPC Ltd | C34: =if(ISBLANK(A34),"",if(K34<-10%,"Buy","Hold")) -> Buy | D34: =if(ISBLANK(A34),"",if(K34<-15%,"Buy","Hold")) -> Hold | E34: =if(ISBLANK(A34),"",if(N34>1401,"Large cap",if(N34>100,"Mid cap","Small cap"))) -> Mid cap | F34: =IFERROR(__xludf.DUMMYFUNCTION("if(ISBLANK(A34),"""",GOOGLEFINANCE(A34,""price""))"),78.9) -> 78.9 | G34: =if(ISBLANK(A34),"",if(L34=0,"Buy@CMP",if(F34<L34,"Buy","Hold"))) -> Buy@CMP | H34: =IFERROR(__xludf.DUMMYFUNCTION("if(ISBLANK(A34),"""",GOOGLEFINANCE(A34,""CHANGEPCT"")/100)"),-0.011899999999999999) -> -0.0119 | I34: =IFERROR(__xludf.DUMMYFUNCTION("if(ISBLANK(A34),"""",GOOGLEFINANCE(A34,""HIGH52""))"),89.75) -> 89.75 | J34: =IFERROR(__xludf.DUMMYFUNCTION("if(ISBLANK(A34),"""",GOOGLEFINANCE(A34,""LOW52""))"),71.62) -> 71.62 | K34: =if(isblank(A34),"",(F34-I34)/I34) -> -0.12089136 | L34: 0 | M34: =IF(ISBLANK(A34), "", IF(AND($N34 >= 0, $N34 <= 75), "||||", IF(AND($N34 > 75, $N34 <= 300), "|||", IF(AND($N34 > 300, $N34 <= 6000), "||", IF($N34 > 6000, "|", ""))))) -> || | N34: =IFERROR(__xludf.DUMMYFUNCTION("if(ISBLANK(A34),"""",googlefinance(A34,""Marketcap"")/1000000000)"),792.369834323) -> 792.36983
A35: NSE:ROSSARI | B35: =IFERROR(__xludf.DUMMYFUNCTION("if(ISBLANK(A35),"""",GOOGLEFINANCE(A35,""NAME""))"),"Rossari Biotech Ltd") -> Rossari Biotech Ltd | C35: =if(ISBLANK(A35),"",if(K35<-10%,"Buy","Hold")) -> Buy | D35: =if(ISBLANK(A35),"",if(K35<-15%,"Buy","Hold")) -> Buy | E35: =if(ISBLANK(A35),"",if(N35>1401,"Large cap",if(N35>100,"Mid cap","Small cap"))) -> Small cap | F35: =IFERROR(__xludf.DUMMYFUNCTION("if(ISBLANK(A35),"""",GOOGLEFINANCE(A35,""price""))"),518.9) -> 518.9 | G35: =if(ISBLANK(A35),"",if(L35=0,"Buy@CMP",if(F35<L35,"Buy","Hold"))) -> Buy@CMP | H35: =IFERROR(__xludf.DUMMYFUNCTION("if(ISBLANK(A35),"""",GOOGLEFINANCE(A35,""CHANGEPCT"")/100)"),-0.0229) -> -0.0229 | I35: =IFERROR(__xludf.DUMMYFUNCTION("if(ISBLANK(A35),"""",GOOGLEFINANCE(A35,""HIGH52""))"),766.0) -> 766 | J35: =IFERROR(__xludf.DUMMYFUNCTION("if(ISBLANK(A35),"""",GOOGLEFINANCE(A35,""LOW52""))"),375.0) -> 375 | K35: =if(isblank(A35),"",(F35-I35)/I35) -> -0.32258486 | L35: 0 | M35: =IF(ISBLANK(A35), "", IF(AND($N35 >= 0, $N35 <= 75), "||||", IF(AND($N35 > 75, $N35 <= 300), "|||", IF(AND($N35 > 300, $N35 <= 6000), "||", IF($N35 > 6000, "|", ""))))) -> |||| | N35: =IFERROR(__xludf.DUMMYFUNCTION("if(ISBLANK(A35),"""",googlefinance(A35,""Marketcap"")/1000000000)"),28.74271297) -> 28.742713
A36: NSE:ROUTE | B36: =IFERROR(__xludf.DUMMYFUNCTION("if(ISBLANK(A36),"""",GOOGLEFINANCE(A36,""NAME""))"),"Route Mobile Ltd") -> Route Mobile Ltd | C36: =if(ISBLANK(A36),"",if(K36<-10%,"Buy","Hold")) -> Buy | D36: =if(ISBLANK(A36),"",if(K36<-15%,"Buy","Hold")) -> Buy | E36: =if(ISBLANK(A36),"",if(N36>1401,"Large cap",if(N36>100,"Mid cap","Small cap"))) -> Small cap | F36: =IFERROR(__xludf.DUMMYFUNCTION("if(ISBLANK(A36),"""",GOOGLEFINANCE(A36,""price""))"),555.0) -> 555 | G36: =if(ISBLANK(A36),"",if(L36=0,"Buy@CMP",if(F36<L36,"Buy","Hold"))) -> Buy@CMP | H36: =IFERROR(__xludf.DUMMYFUNCTION("if(ISBLANK(A36),"""",GOOGLEFINANCE(A36,""CHANGEPCT"")/100)"),0.0101) -> 0.0101 | I36: =IFERROR(__xludf.DUMMYFUNCTION("if(ISBLANK(A36),"""",GOOGLEFINANCE(A36,""HIGH52""))"),1028.0) -> 1028 | J36: =IFERROR(__xludf.DUMMYFUNCTION("if(ISBLANK(A36),"""",GOOGLEFINANCE(A36,""LOW52""))"),410.7) -> 410.7 | K36: =if(isblank(A36),"",(F36-I36)/I36) -> -0.46011673 | L36: 0 | M36: =IF(ISBLANK(A36), "", IF(AND($N36 >= 0, $N36 <= 75), "||||", IF(AND($N36 > 75, $N36 <= 300), "|||", IF(AND($N36 > 300, $N36 <= 6000), "||", IF($N36 > 6000, "|", ""))))) -> |||| | N36: =IFERROR(__xludf.DUMMYFUNCTION("if(ISBLANK(A36),"""",googlefinance(A36,""Marketcap"")/1000000000)"),34.92589956) -> 34.9259
A37: NSE:SOLARINDS | B37: =IFERROR(__xludf.DUMMYFUNCTION("if(ISBLANK(A37),"""",GOOGLEFINANCE(A37,""NAME""))"),"Solar Industries India Ltd") -> Solar Industries India Ltd | C37: =if(ISBLANK(A37),"",if(K37<-10%,"Buy","Hold")) -> Hold | D37: =if(ISBLANK(A37),"",if(K37<-15%,"Buy","Hold")) -> Hold | E37: =if(ISBLANK(A37),"",if(N37>1401,"Large cap",if(N37>100,"Mid cap","Small cap"))) -> Large cap | F37: =IFERROR(__xludf.DUMMYFUNCTION("if(ISBLANK(A37),"""",GOOGLEFINANCE(A37,""price""))"),18247.0) -> 18247 | G37: =if(ISBLANK(A37),"",if(L37=0,"Buy@CMP",if(F37<L37,"Buy","Hold"))) -> Buy@CMP | H37: =IFERROR(__xludf.DUMMYFUNCTION("if(ISBLANK(A37),"""",GOOGLEFINANCE(A37,""CHANGEPCT"")/100)"),-0.0158) -> -0.0158 | I37: =IFERROR(__xludf.DUMMYFUNCTION("if(ISBLANK(A37),"""",GOOGLEFINANCE(A37,""HIGH52""))"),18972.0) -> 18972 | J37: =IFERROR(__xludf.DUMMYFUNCTION("if(ISBLANK(A37),"""",GOOGLEFINANCE(A37,""LOW52""))"),11646.0) -> 11646 | K37: =if(isblank(A37),"",(F37-I37)/I37) -> -0.03821421 | L37: 0 | M37: =IF(ISBLANK(A37), "", IF(AND($N37 >= 0, $N37 <= 75), "||||", IF(AND($N37 > 75, $N37 <= 300), "|||", IF(AND($N37 > 300, $N37 <= 6000), "||", IF($N37 > 6000, "|", ""))))) -> || | N37: =IFERROR(__xludf.DUMMYFUNCTION("if(ISBLANK(A37),"""",googlefinance(A37,""Marketcap"")/1000000000)"),1651.17212482) -> 1651.1721
A38: NSE:SONACOMS | B38: =IFERROR(__xludf.DUMMYFUNCTION("if(ISBLANK(A38),"""",GOOGLEFINANCE(A38,""NAME""))"),"Sona Blw Precision Forgings Ltd") -> Sona Blw Precision Forgings Ltd | C38: =if(ISBLANK(A38),"",if(K38<-10%,"Buy","Hold")) -> Hold | D38: =if(ISBLANK(A38),"",if(K38<-15%,"Buy","Hold")) -> Hold | E38: =if(ISBLANK(A38),"",if(N38>1401,"Large cap",if(N38>100,"Mid cap","Small cap"))) -> Mid cap | F38: =IFERROR(__xludf.DUMMYFUNCTION("if(ISBLANK(A38),"""",GOOGLEFINANCE(A38,""price""))"),668.95) -> 668.95 | G38: =if(ISBLANK(A38),"",if(L38=0,"Buy@CMP",if(F38<L38,"Buy","Hold"))) -> Buy@CMP | H38: =IFERROR(__xludf.DUMMYFUNCTION("if(ISBLANK(A38),"""",GOOGLEFINANCE(A38,""CHANGEPCT"")/100)"),0.0022) -> 0.0022 | I38: =IFERROR(__xludf.DUMMYFUNCTION("if(ISBLANK(A38),"""",GOOGLEFINANCE(A38,""HIGH52""))"),674.0) -> 674 | J38: =IFERROR(__xludf.DUMMYFUNCTION("if(ISBLANK(A38),"""",GOOGLEFINANCE(A38,""LOW52""))"),402.3) -> 402.3 | K38: =if(isblank(A38),"",(F38-I38)/I38) -> -0.0074925816 | L38: 0 | M38: =IF(ISBLANK(A38), "", IF(AND($N38 >= 0, $N38 <= 75), "||||", IF(AND($N38 > 75, $N38 <= 300), "|||", IF(AND($N38 > 300, $N38 <= 6000), "||", IF($N38 > 6000, "|", ""))))) -> || | N38: =IFERROR(__xludf.DUMMYFUNCTION("if(ISBLANK(A38),"""",googlefinance(A38,""Marketcap"")/1000000000)"),416.110187053) -> 416.11019
A39: NSE:TALBROAUTO | B39: =IFERROR(__xludf.DUMMYFUNCTION("if(ISBLANK(A39),"""",GOOGLEFINANCE(A39,""NAME""))"),"Talbros Automotive Components Ltd") -> Talbros Automotive Components Ltd | C39: =if(ISBLANK(A39),"",if(K39<-10%,"Buy","Hold")) -> Hold | D39: =if(ISBLANK(A39),"",if(K39<-15%,"Buy","Hold")) -> Hold | E39: =if(ISBLANK(A39),"",if(N39>1401,"Large cap",if(N39>100,"Mid cap","Small cap"))) -> Small cap | F39: =IFERROR(__xludf.DUMMYFUNCTION("if(ISBLANK(A39),"""",GOOGLEFINANCE(A39,""price""))"),401.0) -> 401 | G39: =if(ISBLANK(A39),"",if(L39=0,"Buy@CMP",if(F39<L39,"Buy","Hold"))) -> Buy@CMP | H39: =IFERROR(__xludf.DUMMYFUNCTION("if(ISBLANK(A39),"""",GOOGLEFINANCE(A39,""CHANGEPCT"")/100)"),-0.024700000000000003) -> -0.0247 | I39: =IFERROR(__xludf.DUMMYFUNCTION("if(ISBLANK(A39),"""",GOOGLEFINANCE(A39,""HIGH52""))"),435.0) -> 435 | J39: =IFERROR(__xludf.DUMMYFUNCTION("if(ISBLANK(A39),"""",GOOGLEFINANCE(A39,""LOW52""))"),219.9) -> 219.9 | K39: =if(isblank(A39),"",(F39-I39)/I39) -> -0.07816092 | L39: 0 | M39: =IF(ISBLANK(A39), "", IF(AND($N39 >= 0, $N39 <= 75), "||||", IF(AND($N39 > 75, $N39 <= 300), "|||", IF(AND($N39 > 300, $N39 <= 6000), "||", IF($N39 > 6000, "|", ""))))) -> |||| | N39: =IFERROR(__xludf.DUMMYFUNCTION("if(ISBLANK(A39),"""",googlefinance(A39,""Marketcap"")/1000000000)"),24.728123565) -> 24.728124
A40: NSE:TATVA | B40: =IFERROR(__xludf.DUMMYFUNCTION("if(ISBLANK(A40),"""",GOOGLEFINANCE(A40,""NAME""))"),"Tatva Chintan Pharma Chem Ltd") -> Tatva Chintan Pharma Chem Ltd | C40: =if(ISBLANK(A40),"",if(K40<-10%,"Buy","Hold")) -> Buy | D40: =if(ISBLANK(A40),"",if(K40<-15%,"Buy","Hold")) -> Buy | E40: =if(ISBLANK(A40),"",if(N40>1401,"Large cap",if(N40>100,"Mid cap","Small cap"))) -> Small cap | F40: =IFERROR(__xludf.DUMMYFUNCTION("if(ISBLANK(A40),"""",GOOGLEFINANCE(A40,""price""))"),1240.0) -> 1240 | G40: =if(ISBLANK(A40),"",if(L40=0,"Buy@CMP",if(F40<L40,"Buy","Hold"))) -> Buy@CMP | H40: =IFERROR(__xludf.DUMMYFUNCTION("if(ISBLANK(A40),"""",GOOGLEFINANCE(A40,""CHANGEPCT"")/100)"),-0.0123) -> -0.0123 | I40: =IFERROR(__xludf.DUMMYFUNCTION("if(ISBLANK(A40),"""",GOOGLEFINANCE(A40,""HIGH52""))"),1610.0) -> 1610 | J40: =IFERROR(__xludf.DUMMYFUNCTION("if(ISBLANK(A40),"""",GOOGLEFINANCE(A40,""LOW52""))"),919.75) -> 919.75 | K40: =if(isblank(A40),"",(F40-I40)/I40) -> -0.22981366 | L40: 0 | M40: =IF(ISBLANK(A40), "", IF(AND($N40 >= 0, $N40 <= 75), "||||", IF(AND($N40 > 75, $N40 <= 300), "|||", IF(AND($N40 > 300, $N40 <= 6000), "||", IF($N40 > 6000, "|", ""))))) -> |||| | N40: =IFERROR(__xludf.DUMMYFUNCTION("if(ISBLANK(A40),"""",googlefinance(A40,""Marketcap"")/1000000000)"),29.006142) -> 29.006142
A41: NSE:WESTLIFE | B41: =IFERROR(__xludf.DUMMYFUNCTION("if(ISBLANK(A41),"""",GOOGLEFINANCE(A41,""NAME""))"),"Westlife Foodworld Ltd") -> Westlife Foodworld Ltd | C41: =if(ISBLANK(A41),"",if(K41<-10%,"Buy","Hold")) -> Buy | D41: =if(ISBLANK(A41),"",if(K41<-15%,"Buy","Hold")) -> Buy | E41: =if(ISBLANK(A41),"",if(N41>1401,"Large cap",if(N41>100,"Mid cap","Small cap"))) -> Small cap | F41: =IFERROR(__xludf.DUMMYFUNCTION("if(ISBLANK(A41),"""",GOOGLEFINANCE(A41,""price""))"),508.0) -> 508 | G41: =if(ISBLANK(A41),"",if(L41=0,"Buy@CMP",if(F41<L41,"Buy","Hold"))) -> Buy@CMP | H41: =IFERROR(__xludf.DUMMYFUNCTION("if(ISBLANK(A41),"""",GOOGLEFINANCE(A41,""CHANGEPCT"")/100)"),0.0092) -> 0.0092 | I41: =IFERROR(__xludf.DUMMYFUNCTION("if(ISBLANK(A41),"""",GOOGLEFINANCE(A41,""HIGH52""))"),819.2) -> 819.2 | J41: =IFERROR(__xludf.DUMMYFUNCTION("if(ISBLANK(A41),"""",GOOGLEFINANCE(A41,""LOW52""))"),398.4) -> 398.4 | K41: =if(isblank(A41),"",(F41-I41)/I41) -> -0.37988281 | L41: 0 | M41: =IF(ISBLANK(A41), "", IF(AND($N41 >= 0, $N41 <= 75), "||||", IF(AND($N41 > 75, $N41 <= 300), "|||", IF(AND($N41 > 300, $N41 <= 6000), "||", IF($N41 > 6000, "|", ""))))) -> ||| | N41: =IFERROR(__xludf.DUMMYFUNCTION("if(ISBLANK(A41),"""",googlefinance(A41,""Marketcap"")/1000000000)"),78.8495756) -> 78.849576
A42: NSE:WHIRLPOOL | B42: =IFERROR(__xludf.DUMMYFUNCTION("if(ISBLANK(A42),"""",GOOGLEFINANCE(A42,""NAME""))"),"Whirlpool Of India Ltd") -> Whirlpool Of India Ltd | C42: =if(ISBLANK(A42),"",if(K42<-10%,"Buy","Hold")) -> Buy | D42: =if(ISBLANK(A42),"",if(K42<-15%,"Buy","Hold")) -> Buy | E42: =if(ISBLANK(A42),"",if(N42>1401,"Large cap",if(N42>100,"Mid cap","Small cap"))) -> Mid cap | F42: =IFERROR(__xludf.DUMMYFUNCTION("if(ISBLANK(A42),"""",GOOGLEFINANCE(A42,""price""))"),800.1) -> 800.1 | G42: =if(ISBLANK(A42),"",if(L42=0,"Buy@CMP",if(F42<L42,"Buy","Hold"))) -> Buy@CMP | H42: =IFERROR(__xludf.DUMMYFUNCTION("if(ISBLANK(A42),"""",GOOGLEFINANCE(A42,""CHANGEPCT"")/100)"),-8.0E-4) -> -0.0008 | I42: =IFERROR(__xludf.DUMMYFUNCTION("if(ISBLANK(A42),"""",GOOGLEFINANCE(A42,""HIGH52""))"),1473.8) -> 1473.8 | J42: =IFERROR(__xludf.DUMMYFUNCTION("if(ISBLANK(A42),"""",GOOGLEFINANCE(A42,""LOW52""))"),756.85) -> 756.85 | K42: =if(isblank(A42),"",(F42-I42)/I42) -> -0.45711766 | L42: 0 | M42: =IF(ISBLANK(A42), "", IF(AND($N42 >= 0, $N42 <= 75), "||||", IF(AND($N42 > 75, $N42 <= 300), "|||", IF(AND($N42 > 300, $N42 <= 6000), "||", IF($N42 > 6000, "|", ""))))) -> ||| | N42: =IFERROR(__xludf.DUMMYFUNCTION("if(ISBLANK(A42),"""",googlefinance(A42,""Marketcap"")/1000000000)"),101.4441669) -> 101.44417
E43: =if(ISBLANK(A43),"",if(N43>1401,"Large cap",if(N43>100,"Mid cap","Small cap")))
B44: =IFERROR(__xludf.DUMMYFUNCTION("if(ISBLANK(A44),"""",GOOGLEFINANCE(A44,""NAME""))"),"") | C44: =if(ISBLANK(A44),"",if(K44<-10%,"Buy","Hold")) | D44: =if(ISBLANK(A44),"",if(K44<-15%,"Buy","Hold")) | E44: =if(ISBLANK(A44),"",if(N44>1401,"Large cap",if(N44>100,"Mid cap","Small cap"))) | F44: =IFERROR(__xludf.DUMMYFUNCTION("if(ISBLANK(A44),"""",GOOGLEFINANCE(A44,""price""))"),"") | G44: =if(ISBLANK(A44),"",if(L44=0,"Buy@CMP",if(F44<L44,"Buy","Hold"))) | H44: =IFERROR(__xludf.DUMMYFUNCTION("if(ISBLANK(A44),"""",GOOGLEFINANCE(A44,""CHANGEPCT"")/100)"),"") | I44: =IFERROR(__xludf.DUMMYFUNCTION("if(ISBLANK(A44),"""",GOOGLEFINANCE(A44,""HIGH52""))"),"") | J44: =IFERROR(__xludf.DUMMYFUNCTION("if(ISBLANK(A44),"""",GOOGLEFINANCE(A44,""LOW52""))"),"") | K44: =if(isblank(A44),"",(F44-I44)/I44) | M44: =IF(ISBLANK(A44), "", IF(AND($N44 >= 0, $N44 <= 75), "||||", IF(AND($N44 > 75, $N44 <= 300), "|||", IF(AND($N44 > 300, $N44 <= 6000), "||", IF($N44 > 6000, "|", ""))))) | N44: =IFERROR(__xludf.DUMMYFUNCTION("if(ISBLANK(A44),"""",googlefinance(A44,""Marketcap"")/1000000000)"),"")
B45: =IFERROR(__xludf.DUMMYFUNCTION("if(ISBLANK(A45),"""",GOOGLEFINANCE(A45,""NAME""))"),"") | C45: =if(ISBLANK(A45),"",if(K45<-10%,"Buy","Hold")) | D45: =if(ISBLANK(A45),"",if(K45<-15%,"Buy","Hold")) | E45: =if(ISBLANK(A45),"",if(N45>1401,"Large cap",if(N45>100,"Mid cap","Small cap"))) | F45: =IFERROR(__xludf.DUMMYFUNCTION("if(ISBLANK(A45),"""",GOOGLEFINANCE(A45,""price""))"),"") | G45: =if(ISBLANK(A45),"",if(L45=0,"Buy@CMP",if(F45<L45,"Buy","Hold"))) | H45: =IFERROR(__xludf.DUMMYFUNCTION("if(ISBLANK(A45),"""",GOOGLEFINANCE(A45,""CHANGEPCT"")/100)"),"") | J45: =IFERROR(__xludf.DUMMYFUNCTION("if(ISBLANK(A45),"""",GOOGLEFINANCE(A45,""LOW52""))"),"") | M45: =IF(ISBLANK(A45), "", IF(AND($N45 >= 0, $N45 <= 75), "||||", IF(AND($N45 > 75, $N45 <= 300), "|||", IF(AND($N45 > 300, $N45 <= 6000), "||", IF($N45 > 6000, "|", ""))))) | N45: =IFERROR(__xludf.DUMMYFUNCTION("if(ISBLANK(A45),"""",googlefinance(A45,""Marketcap"")/1000000000)"),"")
B46: =IFERROR(__xludf.DUMMYFUNCTION("if(ISBLANK(A46),"""",GOOGLEFINANCE(A46,""NAME""))"),"") | C46: =if(ISBLANK(A46),"",if(K46<-10%,"Buy","Hold")) | E46: =if(ISBLANK(A46),"",if(N46>1401,"Large cap",if(N46>100,"Mid cap","Small cap"))) | F46: =IFERROR(__xludf.DUMMYFUNCTION("if(ISBLANK(A46),"""",GOOGLEFINANCE(A46,""price""))"),"") | G46: =if(ISBLANK(A46),"",if(L46=0,"Buy@CMP",if(F46<L46,"Buy","Hold"))) | J46: =IFERROR(__xludf.DUMMYFUNCTION("if(ISBLANK(A46),"""",GOOGLEFINANCE(A46,""LOW52""))"),"") | M46: =IF(ISBLANK(A46), "", IF(AND($N46 >= 0, $N46 <= 75), "||||", IF(AND($N46 > 75, $N46 <= 300), "|||", IF(AND($N46 > 300, $N46 <= 6000), "||", IF($N46 > 6000, "|", ""))))) | N46: =IFERROR(__xludf.DUMMYFUNCTION("if(ISBLANK(A46),"""",googlefinance(A46,""Marketcap"")/1000000000)"),"")
C47: =if(ISBLANK(A47),"",if(K47<-10%,"Buy","Hold")) | E47: =if(ISBLANK(A47),"",if(N47>1401,"Large cap",if(N47>100,"Mid cap","Small cap"))) | F47: =IFERROR(__xludf.DUMMYFUNCTION("if(ISBLANK(A47),"""",GOOGLEFINANCE(A47,""price""))"),"") | G47: =if(ISBLANK(A47),"",if(L47=0,"Buy@CMP",if(F47<L47,"Buy","Hold"))) | M47: =IF(ISBLANK(A47), "", IF(AND($N47 >= 0, $N47 <= 75), "||||", IF(AND($N47 > 75, $N47 <= 300), "|||", IF(AND($N47 > 300, $N47 <= 6000), "||", IF($N47 > 6000, "|", "")))))
C48: =if(ISBLANK(A48),"",if(K48<-10%,"Buy","Hold")) | E48: =if(ISBLANK(A48),"",if(N48>1401,"Large cap",if(N48>100,"Mid cap","Small cap"))) | F48: =IFERROR(__xludf.DUMMYFUNCTION("if(ISBLANK(A48),"""",GOOGLEFINANCE(A48,""price""))"),"") | G48: =if(ISBLANK(A48),"",if(L48=0,"Buy@CMP",if(F48<L48,"Buy","Hold"))) | M48: =IF(ISBLANK(A48), "", IF(AND($N48 >= 0, $N48 <= 75), "||||", IF(AND($N48 > 75, $N48 <= 300), "|||", IF(AND($N48 > 300, $N48 <= 6000), "||", IF($N48 > 6000, "|", "")))))
C49: =if(ISBLANK(A49),"",if(K49<-10%,"Buy","Hold")) | E49: =if(ISBLANK(A49),"",if(N49>1401,"Large cap",if(N49>100,"Mid cap","Small cap"))) | G49: =if(ISBLANK(A49),"",if(L49=0,"Buy@CMP",if(F49<L49,"Buy","Hold"))) | M49: =IF(ISBLANK(A49), "", IF(AND($N49 >= 0, $N49 <= 75), "||||", IF(AND($N49 > 75, $N49 <= 300), "|||", IF(AND($N49 > 300, $N49 <= 6000), "||", IF($N49 > 6000, "|", "")))))

Sheet BOD Stgy
B1: BOD STRATEGY
B2: =Now() -> 46210.805 | F2: =if(OR((weekday(A1))=1,(weekday(A1))=7),"Market Closed",if(time(hour(now()),minute(now()),second(now()))>TIME(15,30,0),"Market Closed",if((time(hour(now()),minute(now()),second(now()))>TIME(9,15,0)),"Market Open","Market Closed"))) -> Market Closed | L2: 20 Percent | O2: 25 Percent | R2: 30 Percent | U2: 35 Percent | X2: 40 Percent | AA2: 45 Percent | AD2: 50 Percent | AG2: 55 Percent | AJ2: 60 Percent | AM2: 65 Percent | AP2: 70 Percent | AS2: 75 Percent | AV2: 80 Percent | AY2: 85 Percent | BB2: 90 Percent
A3: Ticker | B3: Total Qty | C3: Purchased Price | D3: Company | E3: Amount Aloated | F3: 52 Wk High | G3: 52 Wk Low | H3: Price | I3: Mk Cap | K3: Mk Cap (BN) | L3: 20% Price | M3: Qty | N3: -0.2 | O3: 25% Price | P3: Qty | Q3: -0.25 | R3: 30% Price | S3: Qty | T3: -0.3 | U3: 35% Price | V3: Qty | W3: -0.35 | X3: 40% Price | Y3: Qty | Z3: -0.4 | AA3: 45% Price | AB3: Qty | AC3: -0.45 | AD3: 50% Price | AE3: Qty | AF3: -0.5 | AG3: 55% Price | AH3: Qty | AI3: -0.55 | AJ3: 60% Price | AK3: Qty | AL3: -0.6 | AM3: 65% Price | AN3: Qty | AO3: -0.65 | AP3: 70% Price | AQ3: Qty | AR3: -0.7 | AS3: 75% Price | AT3: Qty | AU3: -0.75 | AV3: 80% Price | AW3: Qty | AX3: -0.8 | AY3: 85% Price | AZ3: Qty | BA3: -0.85 | BB3: 90% Price | BC3: Qty | BD3: -0.9
A4: {=Sort(myDG(History!B3:B993,History!C3:C993,History!D3:D993,History!E3:E993))} -> BOM:514183 | B4: 11 | C4: 143.25455 | D4: =IFERROR(__xludf.DUMMYFUNCTION("if(ISBLANK(A4),"""",GOOGLEFINANCE(A4,""NAME""))"),"Black Rose Industries Ltd") -> Black Rose Industries Ltd | E4: 5000 | F4: =IFERROR(__xludf.DUMMYFUNCTION("if(ISBLANK(A4),"""",GOOGLEFINANCE(A4,""HIGH52""))"),137.95) -> 137.95 | G4: =IFERROR(__xludf.DUMMYFUNCTION("if(ISBLANK(A4),"""",GOOGLEFINANCE(A4,""LOW52""))"),61.0) -> 61 | H4: =IFERROR(__xludf.DUMMYFUNCTION("if(ISBLANK(A4),"""",GOOGLEFINANCE(A4,""Price""))"),113.4) -> 113.4 | I4: =IF(ISBLANK(A4), "", IF(K4 > 600000, "MG", IF(K4 > 30000, "L", IF(K4 > 7500, "M", "S")))) -> S | J4: =IF(ISBLANK(A4), "", IF(AND(K4>=0, K4<=7500), "||||", IF(AND(K4>7500, K4<=30000), "|||", IF(AND(K4>30000, K4<=600000), "||", IF(K4>600000, "|", ""))))) -> |||| | K4: =IFERROR(__xludf.DUMMYFUNCTION("if(ISBLANK(A4),"""",googlefinance(A4,""Marketcap"")/10000000)"),571.0470062) -> 571.04701 | L4: =if(ISBLANK(A4),"",F4-(F4*0.2)) -> 110.36 | M4: =if(ISBLANK(A4),"",E4/L4) -> 45.30627 | N4: =if(ISBLANK(A4),"",if(H4>L4,"H",if(H4>O4,"B","Next"))) -> H | O4: =if(ISBLANK(A4),"",F4-(F4*0.25)) -> 103.4625 | P4: =if(ISBLANK(A4),"",E4/O4) -> 48.326688 | Q4: =if(ISBLANK(A4),"",if(H4>O4,"H",if(H4>R4,"B","Next"))) -> H | R4: =if(ISBLANK(A4),"",F4-(F4*0.3)) -> 96.565 | S4: =if(ISBLANK(A4),"",E4/R4) -> 51.778595 | T4: =if(ISBLANK(A4),"",if(H4>R4,"H",if(H4>U4,"B","Next"))) -> H | U4: =if(ISBLANK(A4),"",F4-(F4*0.35)) -> 89.6675 | V4: =if(ISBLANK(A4),"",E4/U4) -> 55.761564 | W4: =if(ISBLANK(A4),"",if(H4>U4,"H",if(H4>X4,"B","Next"))) -> H | X4: =if(ISBLANK(A4),"",F4-(F4*0.4)) -> 82.77 | Y4: =if(ISBLANK(A4),"",E4/X4) -> 60.408361 | Z4: =if(ISBLANK(A4),"",if(H4>X4,"H",if(H4>AA4,"B","Next"))) -> H | AA4: =if(ISBLANK(A4),"",F4-(F4*0.45)) -> 75.8725 | AB4: =if(ISBLANK(A4),"",E4/AA4) -> 65.90003 | AC4: =if(ISBLANK(A4),"",if(H4>AA4,"H",if(H4>AD4,"B","Next"))) -> H | AD4: =if(ISBLANK(A4),"",F4-(F4*0.5)) -> 68.975 | AE4: =if(ISBLANK(A4),"",E4/AD4) -> 72.490033 | AF4: =if(ISBLANK(A4),"",if(H4>AD4,"H",if(H4>AG4,"B","Next"))) -> H | AG4: =if(ISBLANK(A4),"",F4-(F4*0.55)) -> 62.0775 | AH4: =if(ISBLANK(A4),"",E4/AG4) -> 80.544481 | AI4: =if(ISBLANK(A4),"",if(H4>AG4,"H",if(H4>AJ4,"B","Next"))) -> H | AJ4: =if(ISBLANK(A4),"",F4-(F4*0.6)) -> 55.18 | AK4: =if(ISBLANK(A4),"",E4/AJ4) -> 90.612541 | AL4: =if(ISBLANK(A4),"",if(H4>AJ4,"H",if(H4>AM4,"B","Next"))) -> H | AM4: =if(ISBLANK(A4),"",F4-(F4*0.65)) -> 48.2825 | AN4: =if(ISBLANK(A4),"",E4/AM4) -> 103.55719 | AO4: =if(ISBLANK(A4),"",if(H4>AM4,"H",if(H4>AP4,"B","Next"))) -> H | AP4: =if(ISBLANK(A4),"",F4-(F4*0.7)) -> 41.385 | AQ4: =if(ISBLANK(A4),"",E4/AP4) -> 120.81672 | AR4: =if(ISBLANK(A4),"",if(H4>AP4,"H",if(H4>AS4,"B","Next"))) -> H | AS4: =if(ISBLANK(A4),"",F4-(F4*0.75)) -> 34.4875 | AT4: =if(ISBLANK(A4),"",E4/AS4) -> 144.98007 | AU4: =if(ISBLANK(A4),"",if(H4>AS4,"H",if(H4>AV4,"B","Next"))) -> H | AV4: =if(ISBLANK(A4),"",F4-(F4*0.8)) -> 27.59 | AW4: =if(ISBLANK(A4),"",E4/AV4) -> 181.22508 | AX4: =if(ISBLANK(A4),"",if(H4>BWI4,"H",if(H4>AY4,"B","Next"))) -> H | AY4: =if(ISBLANK(A4),"",F4-(F4*0.85)) -> 20.6925 | AZ4: =if(ISBLANK(A4),"",E4/AY4) -> 241.63344 | BA4: =if(ISBLANK(A4),"",if(H4>AY4,"H",if(H4>BB4,"B","Next"))) -> H | BB4: =if(ISBLANK(A4),"",F4-(F4*0.9)) -> 13.795 | BC4: =if(ISBLANK(A4),"",E4/BB4) -> 362.45016 | BD4: =if(ISBLANK(A4),"",if(H4>BB4,"H","B")) -> H
A5: BOM:531739 | B5: 55 | C5: 8 | D5: =IFERROR(__xludf.DUMMYFUNCTION("if(ISBLANK(A5),"""",GOOGLEFINANCE(A5,""NAME""))"),"Gennex Laboratories Ltd") -> Gennex Laboratories Ltd | E5: 5000 | F5: =IFERROR(__xludf.DUMMYFUNCTION("if(ISBLANK(A5),"""",GOOGLEFINANCE(A5,""HIGH52""))"),17.25) -> 17.25 | G5: =IFERROR(__xludf.DUMMYFUNCTION("if(ISBLANK(A5),"""",GOOGLEFINANCE(A5,""LOW52""))"),7.05) -> 7.05 | H5: =IFERROR(__xludf.DUMMYFUNCTION("if(ISBLANK(A5),"""",GOOGLEFINANCE(A5,""Price""))"),10.0) -> 10 | I5: =IF(ISBLANK(A5), "", IF(K5 > 600000, "MG", IF(K5 > 30000, "L", IF(K5 > 7500, "M", "S")))) -> S | J5: =IF(ISBLANK(A5), "", IF(AND(K5>=0, K5<=7500), "||||", IF(AND(K5>7500, K5<=30000), "|||", IF(AND(K5>30000, K5<=600000), "||", IF(K5>600000, "|", ""))))) -> |||| | K5: =IFERROR(__xludf.DUMMYFUNCTION("if(ISBLANK(A5),"""",googlefinance(A5,""Marketcap"")/10000000)"),242.9476) -> 242.9476 | L5: =if(ISBLANK(A5),"",F5-(F5*0.2)) -> 13.8 | M5: =if(ISBLANK(A5),"",E5/L5) -> 362.31884 | N5: =if(ISBLANK(A5),"",if(H5>L5,"H",if(H5>O5,"B","Next"))) -> Next | O5: =if(ISBLANK(A5),"",F5-(F5*0.25)) -> 12.9375 | P5: =if(ISBLANK(A5),"",E5/O5) -> 386.47343 | Q5: =if(ISBLANK(A5),"",if(H5>O5,"H",if(H5>R5,"B","Next"))) -> Next | R5: =if(ISBLANK(A5),"",F5-(F5*0.3)) -> 12.075 | S5: =if(ISBLANK(A5),"",E5/R5) -> 414.07867 | T5: =if(ISBLANK(A5),"",if(H5>R5,"H",if(H5>U5,"B","Next"))) -> Next | U5: =if(ISBLANK(A5),"",F5-(F5*0.35)) -> 11.2125 | V5: =if(ISBLANK(A5),"",E5/U5) -> 445.93088 | W5: =if(ISBLANK(A5),"",if(H5>U5,"H",if(H5>X5,"B","Next"))) -> Next | X5: =if(ISBLANK(A5),"",F5-(F5*0.4)) -> 10.35 | Y5: =if(ISBLANK(A5),"",E5/X5) -> 483.09179 | Z5: =if(ISBLANK(A5),"",if(H5>X5,"H",if(H5>AA5,"B","Next"))) -> B | AA5: =if(ISBLANK(A5),"",F5-(F5*0.45)) -> 9.4875 | AB5: =if(ISBLANK(A5),"",E5/AA5) -> 527.00922 | AC5: =if(ISBLANK(A5),"",if(H5>AA5,"H",if(H5>AD5,"B","Next"))) -> H | AD5: =if(ISBLANK(A5),"",F5-(F5*0.5)) -> 8.625 | AE5: =if(ISBLANK(A5),"",E5/AD5) -> 579.71014 | AF5: =if(ISBLANK(A5),"",if(H5>AD5,"H",if(H5>AG5,"B","Next"))) -> H | AG5: =if(ISBLANK(A5),"",F5-(F5*0.55)) -> 7.7625 | AH5: =if(ISBLANK(A5),"",E5/AG5) -> 644.12238 | AI5: =if(ISBLANK(A5),"",if(H5>AG5,"H",if(H5>AJ5,"B","Next"))) -> H | AJ5: =if(ISBLANK(A5),"",F5-(F5*0.6)) -> 6.9 | AK5: =if(ISBLANK(A5),"",E5/AJ5) -> 724.63768 | AL5: =if(ISBLANK(A5),"",if(H5>AJ5,"H",if(H5>AM5,"B","Next"))) -> H | AM5: =if(ISBLANK(A5),"",F5-(F5*0.65)) -> 6.0375 | AN5: =if(ISBLANK(A5),"",E5/AM5) -> 828.15735 | AO5: =if(ISBLANK(A5),"",if(H5>AM5,"H",if(H5>AP5,"B","Next"))) -> H | AP5: =if(ISBLANK(A5),"",F5-(F5*0.7)) -> 5.175 | AQ5: =if(ISBLANK(A5),"",E5/AP5) -> 966.18357 | AR5: =if(ISBLANK(A5),"",if(H5>AP5,"H",if(H5>AS5,"B","Next"))) -> H | AS5: =if(ISBLANK(A5),"",F5-(F5*0.75)) -> 4.3125 | AT5: =if(ISBLANK(A5),"",E5/AS5) -> 1159.4203 | AU5: =if(ISBLANK(A5),"",if(H5>AS5,"H",if(H5>AV5,"B","Next"))) -> H | AV5: =if(ISBLANK(A5),"",F5-(F5*0.8)) -> 3.45 | AW5: =if(ISBLANK(A5),"",E5/AV5) -> 1449.2754 | AX5: =if(ISBLANK(A5),"",if(H5>BWI5,"H",if(H5>AY5,"B","Next"))) -> H | AY5: =if(ISBLANK(A5),"",F5-(F5*0.85)) -> 2.5875 | AZ5: =if(ISBLANK(A5),"",E5/AY5) -> 1932.3672 | BA5: =if(ISBLANK(A5),"",if(H5>AY5,"H",if(H5>BB5,"B","Next"))) -> H | BB5: =if(ISBLANK(A5),"",F5-(F5*0.9)) -> 1.725 | BC5: =if(ISBLANK(A5),"",E5/BB5) -> 2898.5507 | BD5: =if(ISBLANK(A5),"",if(H5>BB5,"H","B")) -> H
A6: NSE:AARTIIND | B6: 6 | C6: 496.41737 | D6: =IFERROR(__xludf.DUMMYFUNCTION("if(ISBLANK(A6),"""",GOOGLEFINANCE(A6,""NAME""))"),"Aarti Industries Ltd") -> Aarti Industries Ltd | E6: 5000 | F6: =IFERROR(__xludf.DUMMYFUNCTION("if(ISBLANK(A6),"""",GOOGLEFINANCE(A6,""HIGH52""))"),523.1) -> 523.1 | G6: =IFERROR(__xludf.DUMMYFUNCTION("if(ISBLANK(A6),"""",GOOGLEFINANCE(A6,""LOW52""))"),338.05) -> 338.05 | H6: =IFERROR(__xludf.DUMMYFUNCTION("if(ISBLANK(A6),"""",GOOGLEFINANCE(A6,""Price""))"),478.6) -> 478.6 | I6: =IF(ISBLANK(A6), "", IF(K6 > 600000, "MG", IF(K6 > 30000, "L", IF(K6 > 7500, "M", "S")))) -> M | J6: =IF(ISBLANK(A6), "", IF(AND(K6>=0, K6<=7500), "||||", IF(AND(K6>7500, K6<=30000), "|||", IF(AND(K6>30000, K6<=600000), "||", IF(K6>600000, "|", ""))))) -> ||| | K6: =IFERROR(__xludf.DUMMYFUNCTION("if(ISBLANK(A6),"""",googlefinance(A6,""Marketcap"")/10000000)"),17360.0952973) -> 17360.095 | L6: =if(ISBLANK(A6),"",F6-(F6*0.2)) -> 418.48 | M6: =if(ISBLANK(A6),"",E6/L6) -> 11.948002 | N6: =if(ISBLANK(A6),"",if(H6>L6,"H",if(H6>O6,"B","Next"))) -> H | O6: =if(ISBLANK(A6),"",F6-(F6*0.25)) -> 392.325 | P6: =if(ISBLANK(A6),"",E6/O6) -> 12.744536 | Q6: =if(ISBLANK(A6),"",if(H6>O6,"H",if(H6>R6,"B","Next"))) -> H | R6: =if(ISBLANK(A6),"",F6-(F6*0.3)) -> 366.17 | S6: =if(ISBLANK(A6),"",E6/R6) -> 13.65486 | T6: =if(ISBLANK(A6),"",if(H6>R6,"H",if(H6>U6,"B","Next"))) -> H | U6: =if(ISBLANK(A6),"",F6-(F6*0.35)) -> 340.015 | V6: =if(ISBLANK(A6),"",E6/U6) -> 14.705234 | W6: =if(ISBLANK(A6),"",if(H6>U6,"H",if(H6>X6,"B","Next"))) -> H | X6: =if(ISBLANK(A6),"",F6-(F6*0.4)) -> 313.86 | Y6: =if(ISBLANK(A6),"",E6/X6) -> 15.93067 | Z6: =if(ISBLANK(A6),"",if(H6>X6,"H",if(H6>AA6,"B","Next"))) -> H | AA6: =if(ISBLANK(A6),"",F6-(F6*0.45)) -> 287.705 | AB6: =if(ISBLANK(A6),"",E6/AA6) -> 17.378912 | AC6: =if(ISBLANK(A6),"",if(H6>AA6,"H",if(H6>AD6,"B","Next"))) -> H | AD6: =if(ISBLANK(A6),"",F6-(F6*0.5)) -> 261.55 | AE6: =if(ISBLANK(A6),"",E6/AD6) -> 19.116804 | AF6: =if(ISBLANK(A6),"",if(H6>AD6,"H",if(H6>AG6,"B","Next"))) -> H | AG6: =if(ISBLANK(A6),"",F6-(F6*0.55)) -> 235.395 | AH6: =if(ISBLANK(A6),"",E6/AG6) -> 21.240893 | AI6: =if(ISBLANK(A6),"",if(H6>AG6,"H",if(H6>AJ6,"B","Next"))) -> H | AJ6: =if(ISBLANK(A6),"",F6-(F6*0.6)) -> 209.24 | AK6: =if(ISBLANK(A6),"",E6/AJ6) -> 23.896005 | AL6: =if(ISBLANK(A6),"",if(H6>AJ6,"H",if(H6>AM6,"B","Next"))) -> H | AM6: =if(ISBLANK(A6),"",F6-(F6*0.65)) -> 183.085 | AN6: =if(ISBLANK(A6),"",E6/AM6) -> 27.30972 | AO6: =if(ISBLANK(A6),"",if(H6>AM6,"H",if(H6>AP6,"B","Next"))) -> H | AP6: =if(ISBLANK(A6),"",F6-(F6*0.7)) -> 156.93 | AQ6: =if(ISBLANK(A6),"",E6/AP6) -> 31.861339 | AR6: =if(ISBLANK(A6),"",if(H6>AP6,"H",if(H6>AS6,"B","Next"))) -> H | AS6: =if(ISBLANK(A6),"",F6-(F6*0.75)) -> 130.775 | AT6: =if(ISBLANK(A6),"",E6/AS6) -> 38.233607 | AU6: =if(ISBLANK(A6),"",if(H6>AS6,"H",if(H6>AV6,"B","Next"))) -> H | AV6: =if(ISBLANK(A6),"",F6-(F6*0.8)) -> 104.62 | AW6: =if(ISBLANK(A6),"",E6/AV6) -> 47.792009 | AX6: =if(ISBLANK(A6),"",if(H6>BWI6,"H",if(H6>AY6,"B","Next"))) -> H | AY6: =if(ISBLANK(A6),"",F6-(F6*0.85)) -> 78.465 | AZ6: =if(ISBLANK(A6),"",E6/AY6) -> 63.722679 | BA6: =if(ISBLANK(A6),"",if(H6>AY6,"H",if(H6>BB6,"B","Next"))) -> H | BB6: =if(ISBLANK(A6),"",F6-(F6*0.9)) -> 52.31 | BC6: =if(ISBLANK(A6),"",E6/BB6) -> 95.584018 | BD6: =if(ISBLANK(A6),"",if(H6>BB6,"H","B")) -> H
A7: NSE:AFFLE | B7: 6 | C7: 954.45833 | D7: =IFERROR(__xludf.DUMMYFUNCTION("if(ISBLANK(A7),"""",GOOGLEFINANCE(A7,""NAME""))"),"Affle 3i Ltd") -> Affle 3i Ltd | E7: 5000 | F7: =IFERROR(__xludf.DUMMYFUNCTION("if(ISBLANK(A7),"""",GOOGLEFINANCE(A7,""HIGH52""))"),2185.9) -> 2185.9 | G7: =IFERROR(__xludf.DUMMYFUNCTION("if(ISBLANK(A7),"""",GOOGLEFINANCE(A7,""LOW52""))"),1251.3) -> 1251.3 | H7: =IFERROR(__xludf.DUMMYFUNCTION("if(ISBLANK(A7),"""",GOOGLEFINANCE(A7,""Price""))"),1465.1) -> 1465.1 | I7: =IF(ISBLANK(A7), "", IF(K7 > 600000, "MG", IF(K7 > 30000, "L", IF(K7 > 7500, "M", "S")))) -> M | J7: =IF(ISBLANK(A7), "", IF(AND(K7>=0, K7<=7500), "||||", IF(AND(K7>7500, K7<=30000), "|||", IF(AND(K7>30000, K7<=600000), "||", IF(K7>600000, "|", ""))))) -> ||| | K7: =IFERROR(__xludf.DUMMYFUNCTION("if(ISBLANK(A7),"""",googlefinance(A7,""Marketcap"")/10000000)"),20605.9572106) -> 20605.957 | L7: =if(ISBLANK(A7),"",F7-(F7*0.2)) -> 1748.72 | M7: =if(ISBLANK(A7),"",E7/L7) -> 2.8592342 | N7: =if(ISBLANK(A7),"",if(H7>L7,"H",if(H7>O7,"B","Next"))) -> Next | O7: =if(ISBLANK(A7),"",F7-(F7*0.25)) -> 1639.425 | P7: =if(ISBLANK(A7),"",E7/O7) -> 3.0498498 | Q7: =if(ISBLANK(A7),"",if(H7>O7,"H",if(H7>R7,"B","Next"))) -> Next | R7: =if(ISBLANK(A7),"",F7-(F7*0.3)) -> 1530.13 | S7: =if(ISBLANK(A7),"",E7/R7) -> 3.2676962 | T7: =if(ISBLANK(A7),"",if(H7>R7,"H",if(H7>U7,"B","Next"))) -> B | U7: =if(ISBLANK(A7),"",F7-(F7*0.35)) -> 1420.835 | V7: =if(ISBLANK(A7),"",E7/U7) -> 3.5190575 | W7: =if(ISBLANK(A7),"",if(H7>U7,"H",if(H7>X7,"B","Next"))) -> H | X7: =if(ISBLANK(A7),"",F7-(F7*0.4)) -> 1311.54 | Y7: =if(ISBLANK(A7),"",E7/X7) -> 3.8123122 | Z7: =if(ISBLANK(A7),"",if(H7>X7,"H",if(H7>AA7,"B","Next"))) -> H | AA7: =if(ISBLANK(A7),"",F7-(F7*0.45)) -> 1202.245 | AB7: =if(ISBLANK(A7),"",E7/AA7) -> 4.1588861 | AC7: =if(ISBLANK(A7),"",if(H7>AA7,"H",if(H7>AD7,"B","Next"))) -> H | AD7: =if(ISBLANK(A7),"",F7-(F7*0.5)) -> 1092.95 | AE7: =if(ISBLANK(A7),"",E7/AD7) -> 4.5747747 | AF7: =if(ISBLANK(A7),"",if(H7>AD7,"H",if(H7>AG7,"B","Next"))) -> H | AG7: =if(ISBLANK(A7),"",F7-(F7*0.55)) -> 983.655 | AH7: =if(ISBLANK(A7),"",E7/AG7) -> 5.083083 | AI7: =if(ISBLANK(A7),"",if(H7>AG7,"H",if(H7>AJ7,"B","Next"))) -> H | AJ7: =if(ISBLANK(A7),"",F7-(F7*0.6)) -> 874.36 | AK7: =if(ISBLANK(A7),"",E7/AJ7) -> 5.7184684 | AL7: =if(ISBLANK(A7),"",if(H7>AJ7,"H",if(H7>AM7,"B","Next"))) -> H | AM7: =if(ISBLANK(A7),"",F7-(F7*0.65)) -> 765.065 | AN7: =if(ISBLANK(A7),"",E7/AM7) -> 6.5353924 | AO7: =if(ISBLANK(A7),"",if(H7>AM7,"H",if(H7>AP7,"B","Next"))) -> H | AP7: =if(ISBLANK(A7),"",F7-(F7*0.7)) -> 655.77 | AQ7: =if(ISBLANK(A7),"",E7/AP7) -> 7.6246245 | AR7: =if(ISBLANK(A7),"",if(H7>AP7,"H",if(H7>AS7,"B","Next"))) -> H | AS7: =if(ISBLANK(A7),"",F7-(F7*0.75)) -> 546.475 | AT7: =if(ISBLANK(A7),"",E7/AS7) -> 9.1495494 | AU7: =if(ISBLANK(A7),"",if(H7>AS7,"H",if(H7>AV7,"B","Next"))) -> H | AV7: =if(ISBLANK(A7),"",F7-(F7*0.8)) -> 437.18 | AW7: =if(ISBLANK(A7),"",E7/AV7) -> 11.436937 | AX7: =if(ISBLANK(A7),"",if(H7>BWI7,"H",if(H7>AY7,"B","Next"))) -> H | AY7: =if(ISBLANK(A7),"",F7-(F7*0.85)) -> 327.885 | AZ7: =if(ISBLANK(A7),"",E7/AY7) -> 15.249249 | BA7: =if(ISBLANK(A7),"",if(H7>AY7,"H",if(H7>BB7,"B","Next"))) -> H | BB7: =if(ISBLANK(A7),"",F7-(F7*0.9)) -> 218.59 | BC7: =if(ISBLANK(A7),"",E7/BB7) -> 22.873873 | BD7: =if(ISBLANK(A7),"",if(H7>BB7,"H","B")) -> H
A8: NSE:ALKYLAMINE | B8: 2 | C8: 2230 | D8: =IFERROR(__xludf.DUMMYFUNCTION("if(ISBLANK(A8),"""",GOOGLEFINANCE(A8,""NAME""))"),"Alkyl Amines Chemicals Ltd") -> Alkyl Amines Chemicals Ltd | E8: 5000 | F8: =IFERROR(__xludf.DUMMYFUNCTION("if(ISBLANK(A8),"""",GOOGLEFINANCE(A8,""HIGH52""))"),2438.8) -> 2438.8 | G8: =IFERROR(__xludf.DUMMYFUNCTION("if(ISBLANK(A8),"""",GOOGLEFINANCE(A8,""LOW52""))"),1212.0) -> 1212 | H8: =IFERROR(__xludf.DUMMYFUNCTION("if(ISBLANK(A8),"""",GOOGLEFINANCE(A8,""Price""))"),1802.0) -> 1802 | I8: =IF(ISBLANK(A8), "", IF(K8 > 600000, "MG", IF(K8 > 30000, "L", IF(K8 > 7500, "M", "S")))) -> M | J8: =IF(ISBLANK(A8), "", IF(AND(K8>=0, K8<=7500), "||||", IF(AND(K8>7500, K8<=30000), "|||", IF(AND(K8>30000, K8<=600000), "||", IF(K8>600000, "|", ""))))) -> ||| | K8: =IFERROR(__xludf.DUMMYFUNCTION("if(ISBLANK(A8),"""",googlefinance(A8,""Marketcap"")/10000000)"),9157.1022823) -> 9157.1023 | L8: =if(ISBLANK(A8),"",F8-(F8*0.2)) -> 1951.04 | M8: =if(ISBLANK(A8),"",E8/L8) -> 2.5627358 | N8: =if(ISBLANK(A8),"",if(H8>L8,"H",if(H8>O8,"B","Next"))) -> Next | O8: =if(ISBLANK(A8),"",F8-(F8*0.25)) -> 1829.1 | P8: =if(ISBLANK(A8),"",E8/O8) -> 2.7335848 | Q8: =if(ISBLANK(A8),"",if(H8>O8,"H",if(H8>R8,"B","Next"))) -> B | R8: =if(ISBLANK(A8),"",F8-(F8*0.3)) -> 1707.16 | S8: =if(ISBLANK(A8),"",E8/R8) -> 2.9288409 | T8: =if(ISBLANK(A8),"",if(H8>R8,"H",if(H8>U8,"B","Next"))) -> H | U8: =if(ISBLANK(A8),"",F8-(F8*0.35)) -> 1585.22 | V8: =if(ISBLANK(A8),"",E8/U8) -> 3.1541363 | W8: =if(ISBLANK(A8),"",if(H8>U8,"H",if(H8>X8,"B","Next"))) -> H | X8: =if(ISBLANK(A8),"",F8-(F8*0.4)) -> 1463.28 | Y8: =if(ISBLANK(A8),"",E8/X8) -> 3.416981 | Z8: =if(ISBLANK(A8),"",if(H8>X8,"H",if(H8>AA8,"B","Next"))) -> H | AA8: =if(ISBLANK(A8),"",F8-(F8*0.45)) -> 1341.34 | AB8: =if(ISBLANK(A8),"",E8/AA8) -> 3.7276157 | AC8: =if(ISBLANK(A8),"",if(H8>AA8,"H",if(H8>AD8,"B","Next"))) -> H | AD8: =if(ISBLANK(A8),"",F8-(F8*0.5)) -> 1219.4 | AE8: =if(ISBLANK(A8),"",E8/AD8) -> 4.1003772 | AF8: =if(ISBLANK(A8),"",if(H8>AD8,"H",if(H8>AG8,"B","Next"))) -> H | AG8: =if(ISBLANK(A8),"",F8-(F8*0.55)) -> 1097.46 | AH8: =if(ISBLANK(A8),"",E8/AG8) -> 4.5559747 | AI8: =if(ISBLANK(A8),"",if(H8>AG8,"H",if(H8>AJ8,"B","Next"))) -> H | AJ8: =if(ISBLANK(A8),"",F8-(F8*0.6)) -> 975.52 | AK8: =if(ISBLANK(A8),"",E8/AJ8) -> 5.1254715 | AL8: =if(ISBLANK(A8),"",if(H8>AJ8,"H",if(H8>AM8,"B","Next"))) -> H | AM8: =if(ISBLANK(A8),"",F8-(F8*0.65)) -> 853.58 | AN8: =if(ISBLANK(A8),"",E8/AM8) -> 5.8576818 | AO8: =if(ISBLANK(A8),"",if(H8>AM8,"H",if(H8>AP8,"B","Next"))) -> H | AP8: =if(ISBLANK(A8),"",F8-(F8*0.7)) -> 731.64 | AQ8: =if(ISBLANK(A8),"",E8/AP8) -> 6.8339621 | AR8: =if(ISBLANK(A8),"",if(H8>AP8,"H",if(H8>AS8,"B","Next"))) -> H | AS8: =if(ISBLANK(A8),"",F8-(F8*0.75)) -> 609.7 | AT8: =if(ISBLANK(A8),"",E8/AS8) -> 8.2007545 | AU8: =if(ISBLANK(A8),"",if(H8>AS8,"H",if(H8>AV8,"B","Next"))) -> H | AV8: =if(ISBLANK(A8),"",F8-(F8*0.8)) -> 487.76 | AW8: =if(ISBLANK(A8),"",E8/AV8) -> 10.250943 | AX8: =if(ISBLANK(A8),"",if(H8>BWI8,"H",if(H8>AY8,"B","Next"))) -> H | AY8: =if(ISBLANK(A8),"",F8-(F8*0.85)) -> 365.82 | AZ8: =if(ISBLANK(A8),"",E8/AY8) -> 13.667924 | BA8: =if(ISBLANK(A8),"",if(H8>AY8,"H",if(H8>BB8,"B","Next"))) -> H | BB8: =if(ISBLANK(A8),"",F8-(F8*0.9)) -> 243.88 | BC8: =if(ISBLANK(A8),"",E8/BB8) -> 20.501886 | BD8: =if(ISBLANK(A8),"",if(H8>BB8,"H","B")) -> H
A9: NSE:ALLCARGO | B9: 99 | C9: 76.780505 | D9: =IFERROR(__xludf.DUMMYFUNCTION("if(ISBLANK(A9),"""",GOOGLEFINANCE(A9,""NAME""))"),"Allcargo Logistics Ltd") -> Allcargo Logistics Ltd | E9: 5000 | F9: =IFERROR(__xludf.DUMMYFUNCTION("if(ISBLANK(A9),"""",GOOGLEFINANCE(A9,""HIGH52""))"),15.89) -> 15.89 | G9: =IFERROR(__xludf.DUMMYFUNCTION("if(ISBLANK(A9),"""",GOOGLEFINANCE(A9,""LOW52""))"),7.11) -> 7.11 | H9: =IFERROR(__xludf.DUMMYFUNCTION("if(ISBLANK(A9),"""",GOOGLEFINANCE(A9,""Price""))"),7.99) -> 7.99 | I9: =IF(ISBLANK(A9), "", IF(K9 > 600000, "MG", IF(K9 > 30000, "L", IF(K9 > 7500, "M", "S")))) -> S | J9: =IF(ISBLANK(A9), "", IF(AND(K9>=0, K9<=7500), "||||", IF(AND(K9>7500, K9<=30000), "|||", IF(AND(K9>30000, K9<=600000), "||", IF(K9>600000, "|", ""))))) -> |||| | K9: =IFERROR(__xludf.DUMMYFUNCTION("if(ISBLANK(A9),"""",googlefinance(A9,""Marketcap"")/10000000)"),1198.2224) -> 1198.2224 | L9: =if(ISBLANK(A9),"",F9-(F9*0.2)) -> 12.712 | M9: =if(ISBLANK(A9),"",E9/L9) -> 393.32914 | N9: =if(ISBLANK(A9),"",if(H9>L9,"H",if(H9>O9,"B","Next"))) -> Next | O9: =if(ISBLANK(A9),"",F9-(F9*0.25)) -> 11.9175 | P9: =if(ISBLANK(A9),"",E9/O9) -> 419.55108 | Q9: =if(ISBLANK(A9),"",if(H9>O9,"H",if(H9>R9,"B","Next"))) -> Next | R9: =if(ISBLANK(A9),"",F9-(F9*0.3)) -> 11.123 | S9: =if(ISBLANK(A9),"",E9/R9) -> 449.51901 | T9: =if(ISBLANK(A9),"",if(H9>R9,"H",if(H9>U9,"B","Next"))) -> Next | U9: =if(ISBLANK(A9),"",F9-(F9*0.35)) -> 10.3285 | V9: =if(ISBLANK(A9),"",E9/U9) -> 484.0974 | W9: =if(ISBLANK(A9),"",if(H9>U9,"H",if(H9>X9,"B","Next"))) -> Next | X9: =if(ISBLANK(A9),"",F9-(F9*0.4)) -> 9.534 | Y9: =if(ISBLANK(A9),"",E9/X9) -> 524.43885 | Z9: =if(ISBLANK(A9),"",if(H9>X9,"H",if(H9>AA9,"B","Next"))) -> Next | AA9: =if(ISBLANK(A9),"",F9-(F9*0.45)) -> 8.7395 | AB9: =if(ISBLANK(A9),"",E9/AA9) -> 572.11511 | AC9: =if(ISBLANK(A9),"",if(H9>AA9,"H",if(H9>AD9,"B","Next"))) -> B | AD9: =if(ISBLANK(A9),"",F9-(F9*0.5)) -> 7.945 | AE9: =if(ISBLANK(A9),"",E9/AD9) -> 629.32662 | AF9: =if(ISBLANK(A9),"",if(H9>AD9,"H",if(H9>AG9,"B","Next"))) -> H | AG9: =if(ISBLANK(A9),"",F9-(F9*0.55)) -> 7.1505 | AH9: =if(ISBLANK(A9),"",E9/AG9) -> 699.2518 | AI9: =if(ISBLANK(A9),"",if(H9>AG9,"H",if(H9>AJ9,"B","Next"))) -> H | AJ9: =if(ISBLANK(A9),"",F9-(F9*0.6)) -> 6.356 | AK9: =if(ISBLANK(A9),"",E9/AJ9) -> 786.65828 | AL9: =if(ISBLANK(A9),"",if(H9>AJ9,"H",if(H9>AM9,"B","Next"))) -> H | AM9: =if(ISBLANK(A9),"",F9-(F9*0.65)) -> 5.5615 | AN9: =if(ISBLANK(A9),"",E9/AM9) -> 899.03803 | AO9: =if(ISBLANK(A9),"",if(H9>AM9,"H",if(H9>AP9,"B","Next"))) -> H | AP9: =if(ISBLANK(A9),"",F9-(F9*0.7)) -> 4.767 | AQ9: =if(ISBLANK(A9),"",E9/AP9) -> 1048.8777 | AR9: =if(ISBLANK(A9),"",if(H9>AP9,"H",if(H9>AS9,"B","Next"))) -> H | AS9: =if(ISBLANK(A9),"",F9-(F9*0.75)) -> 3.9725 | AT9: =if(ISBLANK(A9),"",E9/AS9) -> 1258.6532 | AU9: =if(ISBLANK(A9),"",if(H9>AS9,"H",if(H9>AV9,"B","Next"))) -> H | AV9: =if(ISBLANK(A9),"",F9-(F9*0.8)) -> 3.178 | AW9: =if(ISBLANK(A9),"",E9/AV9) -> 1573.3166 | AX9: =if(ISBLANK(A9),"",if(H9>BWI9,"H",if(H9>AY9,"B","Next"))) -> H | AY9: =if(ISBLANK(A9),"",F9-(F9*0.85)) -> 2.3835 | AZ9: =if(ISBLANK(A9),"",E9/AY9) -> 2097.7554 | BA9: =if(ISBLANK(A9),"",if(H9>AY9,"H",if(H9>BB9,"B","Next"))) -> H | BB9: =if(ISBLANK(A9),"",F9-(F9*0.9)) -> 1.589 | BC9: =if(ISBLANK(A9),"",E9/BB9) -> 3146.6331 | BD9: =if(ISBLANK(A9),"",if(H9>BB9,"H","B")) -> H
A10: NSE:ASIANPAINT | B10: 3 | C10: 2900.5833 | D10: =IFERROR(__xludf.DUMMYFUNCTION("if(ISBLANK(A10),"""",GOOGLEFINANCE(A10,""NAME""))"),"Asian Paints Ltd") -> Asian Paints Ltd | E10: 5000 | F10: =IFERROR(__xludf.DUMMYFUNCTION("if(ISBLANK(A10),"""",GOOGLEFINANCE(A10,""HIGH52""))"),2985.7) -> 2985.7 | G10: =IFERROR(__xludf.DUMMYFUNCTION("if(ISBLANK(A10),"""",GOOGLEFINANCE(A10,""LOW52""))"),2115.0) -> 2115 | H10: =IFERROR(__xludf.DUMMYFUNCTION("if(ISBLANK(A10),"""",GOOGLEFINANCE(A10,""Price""))"),2730.2) -> 2730.2 | I10: =IF(ISBLANK(A10), "", IF(K10 > 600000, "MG", IF(K10 > 30000, "L", IF(K10 > 7500, "M", "S")))) -> L | J10: =IF(ISBLANK(A10), "", IF(AND(K10>=0, K10<=7500), "||||", IF(AND(K10>7500, K10<=30000), "|||", IF(AND(K10>30000, K10<=600000), "||", IF(K10>600000, "|", ""))))) -> || | K10: =IFERROR(__xludf.DUMMYFUNCTION("if(ISBLANK(A10),"""",googlefinance(A10,""Marketcap"")/10000000)"),262067.7477967) -> 262067.75 | L10: =if(ISBLANK(A10),"",F10-(F10*0.2)) -> 2388.56 | M10: =if(ISBLANK(A10),"",E10/L10) -> 2.0933115 | N10: =if(ISBLANK(A10),"",if(H10>L10,"H",if(H10>O10,"B","Next"))) -> H | O10: =if(ISBLANK(A10),"",F10-(F10*0.25)) -> 2239.275 | P10: =if(ISBLANK(A10),"",E10/O10) -> 2.2328655 | Q10: =if(ISBLANK(A10),"",if(H10>O10,"H",if(H10>R10,"B","Next"))) -> H | R10: =if(ISBLANK(A10),"",F10-(F10*0.3)) -> 2089.99 | S10: =if(ISBLANK(A10),"",E10/R10) -> 2.3923559 | T10: =if(ISBLANK(A10),"",if(H10>R10,"H",if(H10>U10,"B","Next"))) -> H | U10: =if(ISBLANK(A10),"",F10-(F10*0.35)) -> 1940.705 | V10: =if(ISBLANK(A10),"",E10/U10) -> 2.5763833 | W10: =if(ISBLANK(A10),"",if(H10>U10,"H",if(H10>X10,"B","Next"))) -> H | X10: =if(ISBLANK(A10),"",F10-(F10*0.4)) -> 1791.42 | Y10: =if(ISBLANK(A10),"",E10/X10) -> 2.7910819 | Z10: =if(ISBLANK(A10),"",if(H10>X10,"H",if(H10>AA10,"B","Next"))) -> H | AA10: =if(ISBLANK(A10),"",F10-(F10*0.45)) -> 1642.135 | AB10: =if(ISBLANK(A10),"",E10/AA10) -> 3.0448167 | AC10: =if(ISBLANK(A10),"",if(H10>AA10,"H",if(H10>AD10,"B","Next"))) -> H | AD10: =if(ISBLANK(A10),"",F10-(F10*0.5)) -> 1492.85 | AE10: =if(ISBLANK(A10),"",E10/AD10) -> 3.3492983 | AF10: =if(ISBLANK(A10),"",if(H10>AD10,"H",if(H10>AG10,"B","Next"))) -> H | AG10: =if(ISBLANK(A10),"",F10-(F10*0.55)) -> 1343.565 | AH10: =if(ISBLANK(A10),"",E10/AG10) -> 3.7214426 | AI10: =if(ISBLANK(A10),"",if(H10>AG10,"H",if(H10>AJ10,"B","Next"))) -> H | AJ10: =if(ISBLANK(A10),"",F10-(F10*0.6)) -> 1194.28 | AK10: =if(ISBLANK(A10),"",E10/AJ10) -> 4.1866229 | AL10: =if(ISBLANK(A10),"",if(H10>AJ10,"H",if(H10>AM10,"B","Next"))) -> H | AM10: =if(ISBLANK(A10),"",F10-(F10*0.65)) -> 1044.995 | AN10: =if(ISBLANK(A10),"",E10/AM10) -> 4.7847119 | AO10: =if(ISBLANK(A10),"",if(H10>AM10,"H",if(H10>AP10,"B","Next"))) -> H | AP10: =if(ISBLANK(A10),"",F10-(F10*0.7)) -> 895.71 | AQ10: =if(ISBLANK(A10),"",E10/AP10) -> 5.5821639 | AR10: =if(ISBLANK(A10),"",if(H10>AP10,"H",if(H10>AS10,"B","Next"))) -> H | AS10: =if(ISBLANK(A10),"",F10-(F10*0.75)) -> 746.425 | AT10: =if(ISBLANK(A10),"",E10/AS10) -> 6.6985966 | AU10: =if(ISBLANK(A10),"",if(H10>AS10,"H",if(H10>AV10,"B","Next"))) -> H | AV10: =if(ISBLANK(A10),"",F10-(F10*0.8)) -> 597.14 | AW10: =if(ISBLANK(A10),"",E10/AV10) -> 8.3732458 | AX10: =if(ISBLANK(A10),"",if(H10>BWI10,"H",if(H10>AY10,"B","Next"))) -> H | AY10: =if(ISBLANK(A10),"",F10-(F10*0.85)) -> 447.855 | AZ10: =if(ISBLANK(A10),"",E10/AY10) -> 11.164328 | BA10: =if(ISBLANK(A10),"",if(H10>AY10,"H",if(H10>BB10,"B","Next"))) -> H | BB10: =if(ISBLANK(A10),"",F10-(F10*0.9)) -> 298.57 | BC10: =if(ISBLANK(A10),"",E10/BB10) -> 16.746492 | BD10: =if(ISBLANK(A10),"",if(H10>BB10,"H","B")) -> H
A11: NSE:ASTRAL | B11: 2 | C11: 1545 | D11: =IFERROR(__xludf.DUMMYFUNCTION("if(ISBLANK(A11),"""",GOOGLEFINANCE(A11,""NAME""))"),"Astral Ltd") -> Astral Ltd | E11: 5000 | F11: =IFERROR(__xludf.DUMMYFUNCTION("if(ISBLANK(A11),"""",GOOGLEFINANCE(A11,""HIGH52""))"),1768.7) -> 1768.7 | G11: =IFERROR(__xludf.DUMMYFUNCTION("if(ISBLANK(A11),"""",GOOGLEFINANCE(A11,""LOW52""))"),1263.7) -> 1263.7 | H11: =IFERROR(__xludf.DUMMYFUNCTION("if(ISBLANK(A11),"""",GOOGLEFINANCE(A11,""Price""))"),1356.9) -> 1356.9 | I11: =IF(ISBLANK(A11), "", IF(K11 > 600000, "MG", IF(K11 > 30000, "L", IF(K11 > 7500, "M", "S")))) -> L | J11: =IF(ISBLANK(A11), "", IF(AND(K11>=0, K11<=7500), "||||", IF(AND(K11>7500, K11<=30000), "|||", IF(AND(K11>30000, K11<=600000), "||", IF(K11>600000, "|", ""))))) -> || | K11: =IFERROR(__xludf.DUMMYFUNCTION("if(ISBLANK(A11),"""",googlefinance(A11,""Marketcap"")/10000000)"),36451.0430988) -> 36451.043 | L11: =if(ISBLANK(A11),"",F11-(F11*0.2)) -> 1414.96 | M11: =if(ISBLANK(A11),"",E11/L11) -> 3.5336688 | N11: =if(ISBLANK(A11),"",if(H11>L11,"H",if(H11>O11,"B","Next"))) -> B | O11: =if(ISBLANK(A11),"",F11-(F11*0.25)) -> 1326.525 | P11: =if(ISBLANK(A11),"",E11/O11) -> 3.7692467 | Q11: =if(ISBLANK(A11),"",if(H11>O11,"H",if(H11>R11,"B","Next"))) -> H | R11: =if(ISBLANK(A11),"",F11-(F11*0.3)) -> 1238.09 | S11: =if(ISBLANK(A11),"",E11/R11) -> 4.0384786 | T11: =if(ISBLANK(A11),"",if(H11>R11,"H",if(H11>U11,"B","Next"))) -> H | U11: =if(ISBLANK(A11),"",F11-(F11*0.35)) -> 1149.655 | V11: =if(ISBLANK(A11),"",E11/U11) -> 4.3491308 | W11: =if(ISBLANK(A11),"",if(H11>U11,"H",if(H11>X11,"B","Next"))) -> H | X11: =if(ISBLANK(A11),"",F11-(F11*0.4)) -> 1061.22 | Y11: =if(ISBLANK(A11),"",E11/X11) -> 4.7115584 | Z11: =if(ISBLANK(A11),"",if(H11>X11,"H",if(H11>AA11,"B","Next"))) -> H | AA11: =if(ISBLANK(A11),"",F11-(F11*0.45)) -> 972.785 | AB11: =if(ISBLANK(A11),"",E11/AA11) -> 5.1398819 | AC11: =if(ISBLANK(A11),"",if(H11>AA11,"H",if(H11>AD11,"B","Next"))) -> H | AD11: =if(ISBLANK(A11),"",F11-(F11*0.5)) -> 884.35 | AE11: =if(ISBLANK(A11),"",E11/AD11) -> 5.6538701 | AF11: =if(ISBLANK(A11),"",if(H11>AD11,"H",if(H11>AG11,"B","Next"))) -> H | AG11: =if(ISBLANK(A11),"",F11-(F11*0.55)) -> 795.915 | AH11: =if(ISBLANK(A11),"",E11/AG11) -> 6.2820779 | AI11: =if(ISBLANK(A11),"",if(H11>AG11,"H",if(H11>AJ11,"B","Next"))) -> H | AJ11: =if(ISBLANK(A11),"",F11-(F11*0.6)) -> 707.48 | AK11: =if(ISBLANK(A11),"",E11/AJ11) -> 7.0673376 | AL11: =if(ISBLANK(A11),"",if(H11>AJ11,"H",if(H11>AM11,"B","Next"))) -> H | AM11: =if(ISBLANK(A11),"",F11-(F11*0.65)) -> 619.045 | AN11: =if(ISBLANK(A11),"",E11/AM11) -> 8.0769572 | AO11: =if(ISBLANK(A11),"",if(H11>AM11,"H",if(H11>AP11,"B","Next"))) -> H | AP11: =if(ISBLANK(A11),"",F11-(F11*0.7)) -> 530.61 | AQ11: =if(ISBLANK(A11),"",E11/AP11) -> 9.4231168 | AR11: =if(ISBLANK(A11),"",if(H11>AP11,"H",if(H11>AS11,"B","Next"))) -> H | AS11: =if(ISBLANK(A11),"",F11-(F11*0.75)) -> 442.175 | AT11: =if(ISBLANK(A11),"",E11/AS11) -> 11.30774 | AU11: =if(ISBLANK(A11),"",if(H11>AS11,"H",if(H11>AV11,"B","Next"))) -> H | AV11: =if(ISBLANK(A11),"",F11-(F11*0.8)) -> 353.74 | AW11: =if(ISBLANK(A11),"",E11/AV11) -> 14.134675 | AX11: =if(ISBLANK(A11),"",if(H11>BWI11,"H",if(H11>AY11,"B","Next"))) -> H | AY11: =if(ISBLANK(A11),"",F11-(F11*0.85)) -> 265.305 | AZ11: =if(ISBLANK(A11),"",E11/AY11) -> 18.846234 | BA11: =if(ISBLANK(A11),"",if(H11>AY11,"H",if(H11>BB11,"B","Next"))) -> H | BB11: =if(ISBLANK(A11),"",F11-(F11*0.9)) -> 176.87 | BC11: =if(ISBLANK(A11),"",E11/BB11) -> 28.26935 | BD11: =if(ISBLANK(A11),"",if(H11>BB11,"H","B")) -> H
A12: NSE:AUBANK | B12: 6 | C12: 579.6 | D12: =IFERROR(__xludf.DUMMYFUNCTION("if(ISBLANK(A12),"""",GOOGLEFINANCE(A12,""NAME""))"),"AU Small Finance Bank Ltd") -> AU Small Finance Bank Ltd | E12: 5000 | F12: =IFERROR(__xludf.DUMMYFUNCTION("if(ISBLANK(A12),"""",GOOGLEFINANCE(A12,""HIGH52""))"),1079.55) -> 1079.55 | G12: =IFERROR(__xludf.DUMMYFUNCTION("if(ISBLANK(A12),"""",GOOGLEFINANCE(A12,""LOW52""))"),682.15) -> 682.15 | H12: =IFERROR(__xludf.DUMMYFUNCTION("if(ISBLANK(A12),"""",GOOGLEFINANCE(A12,""Price""))"),1066.0) -> 1066 | I12: =IF(ISBLANK(A12), "", IF(K12 > 600000, "MG", IF(K12 > 30000, "L", IF(K12 > 7500, "M", "S")))) -> L | J12: =IF(ISBLANK(A12), "", IF(AND(K12>=0, K12<=7500), "||||", IF(AND(K12>7500, K12<=30000), "|||", IF(AND(K12>30000, K12<=600000), "||", IF(K12>600000, "|", ""))))) -> || | K12: =IFERROR(__xludf.DUMMYFUNCTION("if(ISBLANK(A12),"""",googlefinance(A12,""Marketcap"")/10000000)"),79446.9502445) -> 79446.95 | L12: =if(ISBLANK(A12),"",F12-(F12*0.2)) -> 863.64 | M12: =if(ISBLANK(A12),"",E12/L12) -> 5.7894493 | N12: =if(ISBLANK(A12),"",if(H12>L12,"H",if(H12>O12,"B","Next"))) -> H | O12: =if(ISBLANK(A12),"",F12-(F12*0.25)) -> 809.6625 | P12: =if(ISBLANK(A12),"",E12/O12) -> 6.1754126 | Q12: =if(ISBLANK(A12),"",if(H12>O12,"H",if(H12>R12,"B","Next"))) -> H | R12: =if(ISBLANK(A12),"",F12-(F12*0.3)) -> 755.685 | S12: =if(ISBLANK(A12),"",E12/R12) -> 6.6165135 | T12: =if(ISBLANK(A12),"",if(H12>R12,"H",if(H12>U12,"B","Next"))) -> H | U12: =if(ISBLANK(A12),"",F12-(F12*0.35)) -> 701.7075 | V12: =if(ISBLANK(A12),"",E12/U12) -> 7.1254761 | W12: =if(ISBLANK(A12),"",if(H12>U12,"H",if(H12>X12,"B","Next"))) -> H | X12: =if(ISBLANK(A12),"",F12-(F12*0.4)) -> 647.73 | Y12: =if(ISBLANK(A12),"",E12/X12) -> 7.7192657 | Z12: =if(ISBLANK(A12),"",if(H12>X12,"H",if(H12>AA12,"B","Next"))) -> H | AA12: =if(ISBLANK(A12),"",F12-(F12*0.45)) -> 593.7525 | AB12: =if(ISBLANK(A12),"",E12/AA12) -> 8.4210172 | AC12: =if(ISBLANK(A12),"",if(H12>AA12,"H",if(H12>AD12,"B","Next"))) -> H | AD12: =if(ISBLANK(A12),"",F12-(F12*0.5)) -> 539.775 | AE12: =if(ISBLANK(A12),"",E12/AD12) -> 9.2631189 | AF12: =if(ISBLANK(A12),"",if(H12>AD12,"H",if(H12>AG12,"B","Next"))) -> H | AG12: =if(ISBLANK(A12),"",F12-(F12*0.55)) -> 485.7975 | AH12: =if(ISBLANK(A12),"",E12/AG12) -> 10.292354 | AI12: =if(ISBLANK(A12),"",if(H12>AG12,"H",if(H12>AJ12,"B","Next"))) -> H | AJ12: =if(ISBLANK(A12),"",F12-(F12*0.6)) -> 431.82 | AK12: =if(ISBLANK(A12),"",E12/AJ12) -> 11.578899 | AL12: =if(ISBLANK(A12),"",if(H12>AJ12,"H",if(H12>AM12,"B","Next"))) -> H | AM12: =if(ISBLANK(A12),"",F12-(F12*0.65)) -> 377.8425 | AN12: =if(ISBLANK(A12),"",E12/AM12) -> 13.233027 | AO12: =if(ISBLANK(A12),"",if(H12>AM12,"H",if(H12>AP12,"B","Next"))) -> H | AP12: =if(ISBLANK(A12),"",F12-(F12*0.7)) -> 323.865 | AQ12: =if(ISBLANK(A12),"",E12/AP12) -> 15.438531 | AR12: =if(ISBLANK(A12),"",if(H12>AP12,"H",if(H12>AS12,"B","Next"))) -> H | AS12: =if(ISBLANK(A12),"",F12-(F12*0.75)) -> 269.8875 | AT12: =if(ISBLANK(A12),"",E12/AS12) -> 18.526238 | AU12: =if(ISBLANK(A12),"",if(H12>AS12,"H",if(H12>AV12,"B","Next"))) -> H | AV12: =if(ISBLANK(A12),"",F12-(F12*0.8)) -> 215.91 | AW12: =if(ISBLANK(A12),"",E12/AV12) -> 23.157797 | AX12: =if(ISBLANK(A12),"",if(H12>BWI12,"H",if(H12>AY12,"B","Next"))) -> H | AY12: =if(ISBLANK(A12),"",F12-(F12*0.85)) -> 161.9325 | AZ12: =if(ISBLANK(A12),"",E12/AY12) -> 30.877063 | BA12: =if(ISBLANK(A12),"",if(H12>AY12,"H",if(H12>BB12,"B","Next"))) -> H | BB12: =if(ISBLANK(A12),"",F12-(F12*0.9)) -> 107.955 | BC12: =if(ISBLANK(A12),"",E12/BB12) -> 46.315594 | BD12: =if(ISBLANK(A12),"",if(H12>BB12,"H","B")) -> H
A13: NSE:BAJAJHFL | B13: 100 | C13: 162.886 | D13: =IFERROR(__xludf.DUMMYFUNCTION("if(ISBLANK(A13),"""",GOOGLEFINANCE(A13,""NAME""))"),"Bajaj Housing Finance Ltd") -> Bajaj Housing Finance Ltd | E13: 5000 | F13: =IFERROR(__xludf.DUMMYFUNCTION("if(ISBLANK(A13),"""",GOOGLEFINANCE(A13,""HIGH52""))"),124.0) -> 124 | G13: =IFERROR(__xludf.DUMMYFUNCTION("if(ISBLANK(A13),"""",GOOGLEFINANCE(A13,""LOW52""))"),72.65) -> 72.65 | H13: =IFERROR(__xludf.DUMMYFUNCTION("if(ISBLANK(A13),"""",GOOGLEFINANCE(A13,""Price""))"),88.37) -> 88.37 | I13: =IF(ISBLANK(A13), "", IF(K13 > 600000, "MG", IF(K13 > 30000, "L", IF(K13 > 7500, "M", "S")))) -> L | J13: =IF(ISBLANK(A13), "", IF(AND(K13>=0, K13<=7500), "||||", IF(AND(K13>7500, K13<=30000), "|||", IF(AND(K13>30000, K13<=600000), "||", IF(K13>600000, "|", ""))))) -> || | K13: =IFERROR(__xludf.DUMMYFUNCTION("if(ISBLANK(A13),"""",googlefinance(A13,""Marketcap"")/10000000)"),73803.1388934) -> 73803.139 | L13: =if(ISBLANK(A13),"",F13-(F13*0.2)) -> 99.2 | M13: =if(ISBLANK(A13),"",E13/L13) -> 50.403226 | N13: =if(ISBLANK(A13),"",if(H13>L13,"H",if(H13>O13,"B","Next"))) -> Next | O13: =if(ISBLANK(A13),"",F13-(F13*0.25)) -> 93 | P13: =if(ISBLANK(A13),"",E13/O13) -> 53.763441 | Q13: =if(ISBLANK(A13),"",if(H13>O13,"H",if(H13>R13,"B","Next"))) -> B | R13: =if(ISBLANK(A13),"",F13-(F13*0.3)) -> 86.8 | S13: =if(ISBLANK(A13),"",E13/R13) -> 57.603687 | T13: =if(ISBLANK(A13),"",if(H13>R13,"H",if(H13>U13,"B","Next"))) -> H | U13: =if(ISBLANK(A13),"",F13-(F13*0.35)) -> 80.6 | V13: =if(ISBLANK(A13),"",E13/U13) -> 62.034739 | W13: =if(ISBLANK(A13),"",if(H13>U13,"H",if(H13>X13,"B","Next"))) -> H | X13: =if(ISBLANK(A13),"",F13-(F13*0.4)) -> 74.4 | Y13: =if(ISBLANK(A13),"",E13/X13) -> 67.204301 | Z13: =if(ISBLANK(A13),"",if(H13>X13,"H",if(H13>AA13,"B","Next"))) -> H | AA13: =if(ISBLANK(A13),"",F13-(F13*0.45)) -> 68.2 | AB13: =if(ISBLANK(A13),"",E13/AA13) -> 73.313783 | AC13: =if(ISBLANK(A13),"",if(H13>AA13,"H",if(H13>AD13,"B","Next"))) -> H | AD13: =if(ISBLANK(A13),"",F13-(F13*0.5)) -> 62 | AE13: =if(ISBLANK(A13),"",E13/AD13) -> 80.645161 | AF13: =if(ISBLANK(A13),"",if(H13>AD13,"H",if(H13>AG13,"B","Next"))) -> H | AG13: =if(ISBLANK(A13),"",F13-(F13*0.55)) -> 55.8 | AH13: =if(ISBLANK(A13),"",E13/AG13) -> 89.605735 | AI13: =if(ISBLANK(A13),"",if(H13>AG13,"H",if(H13>AJ13,"B","Next"))) -> H | AJ13: =if(ISBLANK(A13),"",F13-(F13*0.6)) -> 49.6 | AK13: =if(ISBLANK(A13),"",E13/AJ13) -> 100.80645 | AL13: =if(ISBLANK(A13),"",if(H13>AJ13,"H",if(H13>AM13,"B","Next"))) -> H | AM13: =if(ISBLANK(A13),"",F13-(F13*0.65)) -> 43.4 | AN13: =if(ISBLANK(A13),"",E13/AM13) -> 115.20737 | AO13: =if(ISBLANK(A13),"",if(H13>AM13,"H",if(H13>AP13,"B","Next"))) -> H | AP13: =if(ISBLANK(A13),"",F13-(F13*0.7)) -> 37.2 | AQ13: =if(ISBLANK(A13),"",E13/AP13) -> 134.4086 | AR13: =if(ISBLANK(A13),"",if(H13>AP13,"H",if(H13>AS13,"B","Next"))) -> H | AS13: =if(ISBLANK(A13),"",F13-(F13*0.75)) -> 31 | AT13: =if(ISBLANK(A13),"",E13/AS13) -> 161.29032 | AU13: =if(ISBLANK(A13),"",if(H13>AS13,"H",if(H13>AV13,"B","Next"))) -> H | AV13: =if(ISBLANK(A13),"",F13-(F13*0.8)) -> 24.8 | AW13: =if(ISBLANK(A13),"",E13/AV13) -> 201.6129 | AX13: =if(ISBLANK(A13),"",if(H13>BWI13,"H",if(H13>AY13,"B","Next"))) -> H | AY13: =if(ISBLANK(A13),"",F13-(F13*0.85)) -> 18.6 | AZ13: =if(ISBLANK(A13),"",E13/AY13) -> 268.8172 | BA13: =if(ISBLANK(A13),"",if(H13>AY13,"H",if(H13>BB13,"B","Next"))) -> H | BB13: =if(ISBLANK(A13),"",F13-(F13*0.9)) -> 12.4 | BC13: =if(ISBLANK(A13),"",E13/BB13) -> 403.22581 | BD13: =if(ISBLANK(A13),"",if(H13>BB13,"H","B")) -> H
